Workbook

Sheet ILO
C4: COMPARATIVO DE COSTOS B/T MOQUEGUA
C5: ILO
C7: Eslora : 134.16 mtrs.
C8: DW : 14,298.00 mtons.
C9: GRT : 8,259.00 mtons.
D12: TRANSTOTAL | F12: OBSERVACIONES
D13: US$ | E13: %
B14: A) | C14: Shifting Expenses
C15: Practicaje | D15: 3000 | E15: =+D15*100/D32 -> 14.583637 | F15: Tarifa Port Opeartions $ 1,500 por maniobra.
C16: Linesmen /amarre y desamarre | D16: 5200 | E16: =+D16*100/$D$32 -> 25.278304 | F16: Tarifa-PSA $ 0.16 x Trb.8,259 .
C17: Towage /Remolcaje | D17: 4000 | E17: =+D17*100/$D$32 -> 19.44485 | F17: Petranso Remolcadores Tarifa $ 0.18 x Trb 8,259, sujeta a 10% descuentos, posicionamiento $ 1400
E18: =+D18*100/$D$32 -> 0
C19: Recargos | D19: 1500 | E19: =+D19*100/$D$32 -> 7.2918186
B21: B) | C21: General Port Expenses | E21: =+D21*100/$D$32 -> 0
C22: Lighthouse Dues | D22: 991 | E22: =+D22*100/$D$32 -> 4.8174615 | F22: Tarifa Direccion de Hidrografia y navegacion
C23: Dockage /Muellaje | D23: 830 | E23: =+D23*100/$D$32 -> 4.0348063 | F23: SPCC, Tarifa deAmarre y desamarre $ 300.00 , y Muelle SPCC $ 0.05 x Trb x dia.
C24: Launch Hire. | D24: 2580 | E24: =+D24*100/$D$32 -> 12.541928 | F24: Transtotal.Fija.Mooring /unmooring por maniobra/por lancha.$ 90.00
C25: Coordinator on board | D25: 400 | E25: =+D25*100/$D$32 -> 1.944485 | F25: Transtotal. Tarifa Fija por Nave.
C26: Sanitary Inspection (Reception/Dispatch) | D26: 520 | E26: =+D26*100/$D$30 -> 52 | F26: Tarifa fija según Sanidad maritima. S/1,284.00
C27: Launch autoridades. | D27: 150 | E27: 0.65416485 | F27: Lanchas de por transporte de Autoridades.
C28: Clearance (In/Out) | D28: 150 | E28: =+D28*100/$D$32 -> 0.72918186 | F28: Tarifa fija según Sanidad maritima.
B29: C) | C29: Agency Expenses | E29: =+D29*100/$D$32 -> 0
C30: Agency Fee | D30: 1000 | E30: =+D30*100/$D$32 -> 4.8612124 | F30: Tarifa fija. Transtotal por Agenciamiento de Nave.
C31: Transportation | D31: 250 | E31: =+D31*100/$D$32 -> 1.2153031 | F31: Tarifa fija. Transtotal por Nave.
C32: T O T A L | D32: =SUM(D14:D31) -> 20571 | E32: =+D32*100/$D$32 -> 100
C34: Carga de 13,500.00TN SUA.
C35: OBSERVACIONES :
C36: *INCLUYE MUELLAJE.
C37: *NO INCLUYE IGV.
C38: *CARGA DE 13,500 TM -SUA

Sheet ilo patio puerto
C4: COMPARATIVO DE COSTOS B/T MOQUEGUA
C5: ILO PATIO PUERTO
D7: TRANSTOTAL | E7: % | F7: OBSERVACIONES
D8: US$
B9: A) | C9: Shifting Expenses
C10: Practicaje | D10: 3000 | E10: =+D10*100/D24 -> 16.059097 | F10: Tarifa Port Opeartions $ 1,500 por maniobra.
C11: Towage /Remolcaje | D11: 4600 | E11: =+D11*100/$D$24 -> 24.623949 | F11: Tarifa-PSA Marine $ 0.16 x Trb.8259
C12: Towage /Remolcaje | D12: 4000 | E12: =+D12*100/$D$24 -> 21.41213 | F12: Petranso Remolcadores Tarifa $ 0.1785 x Trb 8259 sujeta a 10% descuentos, posicionamiento $ 1400
C13: Recargos | D13: 1500 | E13: =+D13*100/$D$24 -> 8.0295487
B14: B) | C14: General Port Expenses | E14: =+D14*100/$D$24 -> 0
C15: Lighthouse Dues | D15: 891 | E15: =+D15*100/$D$24 -> 4.769552 | F15: Tarifa Direccion de Hidrografia y navegacion
C16: Dockage /Muellaje | D16: 1245 | E16: =+D16*100/$D$24 -> 6.6645255 | F16: SPCC, Tarifa deAmarre y desamarre $ 300.00 , y Muelle SPCC $ 0.05 x Trb x dia.
C17: Launch Hire. | D17: 1300 | E17: =+D17*100/$D$24 -> 6.9589422 | F17: Transtotal.Fija.Mooring /unmooring ,pilot,posicionamiento por maniobra/por lancha.
C18: Coordinator on board | D18: 225 | E18: =+D18*100/$D$24 -> 1.2044323 | F18: Transtotal. Tarifa Fija por Nave.
C19: Clearance (In/Out) | D19: 200 | E19: =+D19*100/$D$24 -> 1.0706065 | F19: Region Moquegua. Tarifa
C20: Sanitary Inspection (Reception/Dispatch) | D20: 520 | E20: =+D20*100/$D$24 -> 2.7835769 | F20: Tarifa fija según Sanidad maritima.
B21: C) | C21: Agency Expenses | E21: =+D21*100/$D$24 -> 0
C22: Agency Fee | D22: 1000 | E22: =+D22*100/$D$24 -> 5.3530325 | F22: Tarifa fija. Transtotal por Agenciamiento de Nave.
C23: Transportation | D23: 200 | E23: =+D23*100/$D$24 -> 1.0706065 | F23: Tarifa fija. Transtotal por Nave.
C24: T O T A L | D24: =SUM(D9:D23) -> 18681 | E24: =+D24*100/$D$24 -> 100
D26: 19181
C27: OBSERVACIONES : | D27: =+D26-D24 -> 500
C28: *INCLUYE MUELLAJE.
C29: *NO INCLUYE IGV.
C30: *NO INCLUYE RECARGOS PSA MARINE/PETRANSO
C31: Time in port (hrs) 30 -Carga de 13,500.00TN SUA.

Sheet MATARANI
C4: COMPARATIVO DE COSTOS B/T MOQUEGUA
C5: MATARANI
C7: Eslora : 134.16 mtrs.
C8: DW : 14,298.00 mtons.
C9: GRT : 8,259.00 mtons.
D12: TRANSTOTAL | F12: OBSERVACIONES
D13: US$ | E13: %
B14: A) | C14: Shifting Expenses
C15: 1er Remolcador | D15: 3500 | E15: =+D15*100/D32 -> 22.521073 | F15: Tarifa de servicio integral-Tramarsa . Incluye Remolcaje , Practicaje , Lancha
C16: 2do Remolcador | D16: 3500 | E16: =+D16*100/$D$32 -> 22.521073 | F16: Tarifa de servicio integral-Tramarsa . Incluye Remolcaje , Practicaje , Lancha
C17: Acceso | D17: 280 | E17: =+D17*100/$D$32 -> 1.8016859 | F17: Tarifa de servicio integral-Tramarsa . Acceso $ 70.00 + IGV
C18: Recargos | D18: 1000 | E18: =+D18*100/$D$32 -> 6.4345924 | F18: Tarifa de servicio integral-Tramarsa min .25% max 50%
B20: B) | C20: General Port Expenses
C21: Lighthouse Dues | D21: 891 | E21: =+D21*100/$D$32 -> 5.7332218 | F21: Tarifa Direccion de Hidrografia y Navegacion.
C22: Dockage /Muellaje | D22: 3000 | E22: =+D22*100/$D$32 -> 19.303777 | F22: Tisur Tarifa $0.57 X Hora (24 )X Eslora (134.16)
C23: Launch Hire. | D23: 550 | E23: =+D23*100/$D$32 -> 3.5390258 | F23: Tarifa de Transtotal.Fija.Mooring /unmooring por maniobra/por lancha.
C24: Private & Dangerous cargo Watchmen | E24: =+D24*100/$D$32 -> 0 | F24: Tarifa de Transtotal.Fija.
C25: Sanitary Inspection (Reception/Dispatch) | D25: 670 | E25: =+D25*100/$D$32 -> 4.3111769 | F25: Tarifa Region Moquegua.
C26: Clearance (In/Out) | D26: 200 | E26: =+D26*100/$D$32 -> 1.2869185 | F26: Tarifa APN.
C27: Coordinator on board | D27: 450 | E27: =+D27*100/$D$32 -> 2.8955666 | F27: USD$150* por dia + 18% IGV
B28: C) | C28: Agency Expenses
C29: Agency Fee | D29: 1100 | E29: =+D29*100/$D$32 -> 7.0780516 | F29: Tarifa fija Transtotal por Agenciamiento de Nave.
C30: Transportation/Comunication | D30: 400 | E30: =+D30*100/$D$32 -> 2.5738369 | F30: Tarifa fija Transtotal
C32: T O T A L | D32: =SUM(D15:D30) -> 15541 | E32: =+D32*100/$D$32 -> 100
C34: Carga de 13,500.00TN SUA.
C35: OBSERVACIONES : | E35: *RECARGOS: PSA MARINE
C36: *INCLUYE MUELLAJE. | E36: 25% ENTRE 18 Y 24 HRS. LUN-SAB
C37: *NO INCLUYE IGV. | E37: 50% ENTRE 00 Y 07 HRS. LUN-SAB
E38: 50% DOMINGOS Y FERIADOS

Sheet MARCONA
C4: COMPARATIVO DE COSTOS B/T MOQUEGUA
C5: MARCONA
C6: Eslora : 134.16 mtrs.
C7: DW : 14,298.00 mtons.
C8: GRT : 8,259.00 mtons.
D11: TRANSTOTAL | E11: % | F11: OBSERVACIONES
D12: US$
B13: A) | C13: Shifting Expenses
C14: Practicaje. | E14: =+D14*100/D32 -> 0 | F14: Tarifa PSA MARINE ($4,980*Mnver + 18%vat) por maniobra.
C15: Linesmen /amarre y desamarre | E15: =+D15*100/$D$32 -> 0 | F15: Tarifa PSA MARINE ($4,250*Launchboat + 18%vat) .(incluye 2 lanchas y gavieras )
C16: Towage /Remolcaje | D16: 36000 | E16: =+D16*100/$D$32 -> 92.194222 | F16: Tarifa PSA MARINE ( $18,000*Mnver + 18%vat) por maniobra 2.
B19: B) | C19: General Port Expenses
C20: Ligth Dues. | D20: 248 | E20: =+D20*100/$D$32 -> 0.63511575 | F20: Tarifa Direccion de Hidrografia y navegacion($0.03*GT coming from a national port)
C21: Dockage /Muellaje | D21: 0 | E21: =+D21*100/$D$32 -> 0 | F21: Aún no consideran una tarifa por el Uso de Amarradero o si se requerirá de una Lancha de Permanencia para los operativos,
C22: Launch Hire. | E22: =+D22*100/$D$32 -> 0 | F22: $40X HORA aproximado de 40 horas (Tarifa PSA Marine SA)
C23: Coordinator | D23: 600 | E23: =+D23*100/$D$32 -> 1.5365704 | F23: $ 200 per day +18%
C24: Clearance Expenses (In/Out) | D24: 200 | E24: =+D24*100/$D$32 -> 0.51219012 | F24: Region Moquegua. Tarifa
C25: Sanitary Inspection (Reception/Dispatch) | E25: =+D25*100/$D$32 -> 0 | F25: Tarifa APN.
C26: Launch for Authorities | D26: 200 | E26: =+D26*100/$D$32 -> 0.51219012 | F26: $ 250 * maneuver +18%
C27: Remolcaje Stand by. | D27: 0 | E27: =+D27*100/$D$32 -> 0 | F27: $ 3,000.00 * a partir de 60 horas.
B28: C) | C28: Agency Expenses
C29: Agency Fee | D29: 1400 | E29: =+D29*100/$D$32 -> 3.5853309 | F29: Tarifa fija. Transtotal por Agenciamiento de Nave.
C30: Transportation/Comunication | D30: 400 | E30: =+D30*100/$D$32 -> 1.0243802 | F30: Tarifa fija. Transtotal por Nave.
C32: T O T A L | D32: =SUM(D14:D30) -> 39048 | E32: =+D32*100/$D$32 -> 100
C34: Carga de 13,500.00TN SUA.
C35: OBSERVACIONES : | D35: Las tarifas resaltadas corresponden a servicios licitados por Marcobre, para el cual la empresa ganadora fue PSA Marine; dichas tarifas se encuentran confirmadas. Servicio de Remolcaje Stand By a partir de 60 horas aplica USD 3,000.00 diario por cada remolcador por dia y fraccion. Aún no se ha confirmado por el lado del terminal si estarán considerando una tarifa por el Uso de Amarradero o si se requerirá de una Lancha de Permanencia para los operativos, lo cual incrementaría los costos de la proforma en caso se confirmen. Se está considerando que la nave procede de un Puerto Nacional y será despachada a un Puerto Nacional.
C36: *NO INCLUYE MUELLAJE.
C37: *NO INCLUYE IGV.
C38: * NO APLICA RECARGOS.

Sheet CALLAO
C4: COMPARATIVO DE COSTOS B/T MOQUEGUA
C5: CALLAO
C6: Eslora : 134.16 mtrs.
C7: DW : 14,298.00 mtons.
C8: GRT : 8,259.00 mtons.
D11: TRANSTOTAL | F11: OBSERVACIONES
D12: US$ | E12: %
B13: A) | C13: Shifting Expenses
C14: Pilotage. | D14: 1680 | E14: =+D14*100/D27 -> 11.093502 | F14: Tarifa de Transtotal.Fija.
C15: Remolcaje | D15: 3200 | E15: =+D15*100/$D$27 -> 21.130481 | F15: Petranso Remolcadores Tarifa minima $ 800 por maniobra (2) 2 in 2 out
B17: B) | C17: General Port Expenses
C18: Lighthouse Dues | D18: 248 | E18: =+D18*100/$D$27 -> 1.6376123 | F18: Tarifa Direccion de Hidrografia y Navegacion.
C19: Dockage /Muellaje | D19: =(1.5*158.8) *30 -> 7146 | E19: =+D19*100/$D$27 -> 47.187005 | F19: Tarifa APM $1.50 por hora o fraccion.
C20: Launch Hire. | D20: 1020 | E20: =+D20*100/$D$27 -> 6.7353407 | F20: Tarifa de Transtotal.Fija.Mooring /unmooring por maniobra/por lanch USD .80.00 xh.
C21: Coordinator on board | D21: 450 | E21: =+D21*100/$D$27 -> 2.9714739 | F21: Tarifa fija. Transtotal por Nave.
C22: Sanitary Inspection (Reception/Dispatch) | E22: =+D22*100/$D$27 -> 0 | F22: Tarifa fija según Sanidad maritima.
B23: C) | C23: Agency Expenses
C24: Agency Fee | D24: 1000 | E24: =+D24*100/$D$27 -> 6.6032752 | F24: Tarifa fija Transtotal por Agenciamiento de Nave.
C25: Transportation/comunication | D25: 400 | E25: =+D25*100/$D$27 -> 2.6413101 | F25: Tarifa fija. Transtotal por Nave.
C27: T O T A L | D27: =SUM(D14:D25) -> 15144 | E27: =+D27*100/$D$27 -> 100
C29: Carga de 13,500.00TN SUA.
C30: OBSERVACIONES : | F30: Eslora : 134.16 mtrs.
C31: *INCLUYE MUELLAJE. | F31: DW : 14,298.00 mtons.
C32: *NO INCLUYE IGV. | F32: GRT : 8,259.00 mtons.

Sheet MEJILLONES.A
C2: COMPARATIVO DE COSTOS B/T MOQUEGUA
C3: MEJILLONES
C5: Eslora : 134.16 mtrs.
C6: DW : 14,298.00 mtons.
C7: GRT : 8,259.00 mtons.
D9: B&M | F9: OBSERVACIONES
D10: US$ | E10: %
B11: A) | C11: Shifting Expenses
C12: Pilotage. | D12: =1388.62+420 -> 1808.62 | E12: =+D12*100/D29 -> 3.5932727 | F12: Tarifa fija según Autoridad Maritima.
C13: Towage. | D13: =2800*4 -> 11200 | E13: =+D13*100/$D$29 -> 22.251581 | F13: Tarifa Fija. 2026 $ 2,800. maniobra mooring/unmooring- Remolcadores Ultratug Ltd.
C14: Pilot Insurance. | D14: 330 | E14: =+D14*100/$D$29 -> 0.65562694 | F14: Tarifa Fija Puerto Mejillones.
C15: Linesmen. | D15: 1742.5 | E15: =+D15*100/$D$29 -> 3.4619089 | F15: Tarifa fija según Puerto Mejillones amarradores en tierra.
B17: B) | C17: General Port Expenses
C18: Ligth Dues. | D18: 3400 | E18: =+D18*100/$D$29 -> 6.7549443 | F18: *LIGHT DUES CHILE = USD 4.07 /GRT POR AÑO : USD 33,614.13 /15 viajes aprox
C19: Dockage /Muellaje | D19: =(158.8*36)*3.99 -> 22810.032 | E19: =+D19*100/$D$29 -> 45.317793 | F19: 3.99 *loa*36 h
C20: Launch Hire. | D20: 1800 | E20: =+D20*100/$D$29 -> 3.576147 | F20: T.Fija.Mooring /unmooring por maniobra/por lancha.
C21: Pilot /Authorities Transport. | D21: 1490 | E21: =+D21*100/$D$29 -> 2.960255 | F21: Transporte en lancha de Piloto $ 70.00 c/u y Autoridades $ 220.00 .
C22: ISPS Fee. | D22: 1140.35 | E22: =+D22*100/$D$29 -> 2.2655884 | F22: Tarifa fija según Puerto Mejillones.
C23: Immigration Authorities. | D23: 28 | E23: =+D23*100/$D$29 -> 0.055628953 | F23: Tarifa fija según Policia de Investigacion de Chile.
C24: Health authorities. | D24: 120 | E24: =+D24*100/$D$29 -> 0.2384098 | F24: Tarifa fija según Sanidad Maritima.
C25: Loading Master | D25: 3264 | E25: =+D25*100/$D$29 -> 6.4847465 | F25: Tarifa fija según Puerto Mejillones. $ 62 x th 36 H
B26: C) | C26: Agency Expenses
C27: Agency Fee | D27: 1200 | E27: =+D27*100/$D$29 -> 2.384098 | F27: Tarifa fija.B&M por Agenciamiento de Nave.
C29: T O T A L | D29: =SUM(D12:D28) -> 50333.502 | E29: =+D29*100/$D$29 -> 100
C31: Carga de 13,500.00TN SUA.
C32: OBSERVACIONES :
C33: * INCLUYE MUELLAJE
C34: *LIGHT DUES CHILE = USD 4.07 /GRT POR AÑO : USD 33,614.13( 0.11 incremento 2026 USD 4.07 en USD 1,250.15)
C35: * ADELANTOS POR CADA VIAJE MENSUALES $ 18,000.00 para B&M.
C36: *DE ACUERDO A PROFORMA ENVIADA POR B&M.

Sheet MEJILLONES.INTERACID
C4: COMPARATIVO DE COSTOS B/T MOQUEGUA
C5: MEJILLONES
C6: Eslora : 134.16 mtrs.
C7: DW : 14,298.00 mtons.
C8: GRT : 8,259.00 mtons.
D11: B&M | F11: OBSERVACIONES
D12: US$ | E12: %
B13: A) | C13: Shifting Expenses
C14: Pilotage. | D14: =1151+420 -> 1571 | E14: =+D14*100/D31 -> 3.4260168 | F14: Tarifa fija según Autoridad Maritima.
C15: Towage. | D15: 11200 | E15: =+D15*100/$D$31 -> 24.424817 | F15: Tarifa Fija. 2026 $ 2,800. maniobra mooring/unmooring- Remolcadores Ultratug Ltd.
C16: Pilot Insurance. | D16: 330 | E16: =+D16*100/$D$31 -> 0.7196598 | F16: Tarifa Fija Puerto Mejillones.
C17: Linesmen. | D17: 1107 | E17: =+D17*100/$D$31 -> 2.4141315 | F17: Tarifa fija según Puerto Mejillones amarradores en tierra.
B19: B) | C19: General Port Expenses
C20: Ligth Dues. | D20: 3400 | E20: =+D20*100/$D$31 -> 7.4146767 | F20: *LIGHT DUES CHILE = USD 4.07 /GRT POR AÑO : USD 33,614.13 /15 viajes aprox
C21: Dockage /Muellaje | D21: 20000 | E21: =+D21*100/$D$31 -> 43.615745 | F21: 640 *TH /36 H
C22: Launch Hire. | D22: 1800 | E22: =+D22*100/$D$31 -> 3.9254171 | F22: T.Fija.Mooring /unmooring por maniobra/por lancha.
C23: Pilot /Authorities Transport. | D23: 1490 | E23: =+D23*100/$D$31 -> 3.249373 | F23: Transporte en lancha de Piloto $ 70.00 c/u y Autoridades $ 220.00 .
C24: ISPS Fee. | D24: 917 | E24: =+D24*100/$D$31 -> 1.9997819 | F24: Tarifa fija según Puerto Mejillones.
C25: Immigration Authorities. | D25: 28 | E25: =+D25*100/$D$31 -> 0.061062043 | F25: Tarifa fija según Policia de Investigacion de Chile.
C26: Health authorities. | D26: 120 | E26: =+D26*100/$D$31 -> 0.26169447 | F26: Tarifa fija según Sanidad Maritima.
C27: Loading Master | D27: 2692 | E27: =+D27*100/$D$31 -> 5.8706793 | F27: Tarifa fija según Puerto Mejillones. $ 62 x th 36 H
B28: C) | C28: Agency Expenses
C29: Agency Fee | D29: 1200 | E29: =+D29*100/$D$31 -> 2.6169447 | F29: Tarifa fija.B&M por Agenciamiento de Nave.
C31: T O T A L | D31: =SUM(D14:D30) -> 45855 | E31: =+D31*100/$D$31 -> 100
C33: Carga de 13,500.00TN SUA.
C34: OBSERVACIONES :
C35: * INCLUYE MUELLAJE
C36: *LIGHT DUES CHILE = USD 4.07 /GRT POR AÑO : USD 33,614.13( 0.11 incremento 2026 USD 4.07 en USD 1,250.15)
C37: * ADELANTOS POR CADA VIAJE MENSUALES $ 18,000.00 para B&M.

Sheet MEJILLONES.TERQUIM
C4: COMPARATIVO DE COSTOS B/T MOQUEGUA
C5: TERQUIM
C7: Eslora : 134.16 mtrs.
C8: DW : 14,298.00 mtons.
C9: GRT : 8,259.00 mtons.
D11: B&M | F11: OBSERVACIONES
D12: US$ | E12: %
B13: A) | C13: Shifting Expenses
C14: Pilotage. | D14: =1571+420 -> 1991 | E14: =+D14*100/D32 -> 3.985439 | F14: Tarifa fija según Autoridad Maritima.
C15: Towage. | D15: =2800*3 -> 8400 | E15: =+D15*100/$D$32 -> 16.814509 | F15: Tarifa Fija. 2024 $ 2,800 * 3 por maniobra mooring/unmooring- Remolcadores Ultratug Ltd.
C16: Pilot Insurance. | D16: 330 | E16: =+D16*100/$D$32 -> 0.66056999 | F16: Tarifa Fija por 2 seguros de practico $80.00 c/u.
C17: Linesmen. | D17: 1602 | E17: =+D17*100/$D$32 -> 3.2067671 | F17: Tarifa fija según Puerto Mejillones amarradores en tierra.
C18: Recargos | D18: 1000 | E18: =+D18*100/$D$32 -> 2.0017273
B20: B) | C20: General Port Expenses
C21: Ligth Dues. | D21: 2500 | E21: =+D21*100/$D$32 -> 5.0043181 | F21: *LIGHT DUES CHILE = USD 4.07 /GRT POR AÑO : USD 33,614.13 /15 viajes aprox
C22: Launch Hire. | D22: =1800+420 -> 2220 | E22: =+D22*100/$D$32 -> 4.4438345 | F22: T.Fija.Mooring /unmooring por maniobra/por lancha.
C23: Dockage /Muellaje | D23: =+(5.72*134.16)* 30 -> 23021.856 | E23: =+D23*100/$D$32 -> 46.083477 | F23: 5.72*LOA*TH /30 H Puerto Mejillones terquim
C24: Pilot /Authorities Transport. | D24: 400 | E24: =+D24*100/$D$32 -> 0.8006909 | F24: Transporte en lancha de Piloto $ 70.00 c/u y Autoridades $ 220.00 .
C25: ISPS Fee. | D25: 1191 | E25: =+D25*100/$D$32 -> 2.3840572 | F25: Tarifa fija según Puerto Mejillones.
C26: Immigration Authorities. | D26: 28 | E26: =+D26*100/$D$32 -> 0.056048363 | F26: Tarifa fija según Policia de Investigacion de Chile.
C27: Health authorities. | D27: 650 | E27: =+D27*100/$D$32 -> 1.3011227 | F27: Tarifa fija según Sanidad Maritima.
C28: Loading Master | D28: 2923 | E28: =+D28*100/$D$32 -> 5.8510488 | F28: Tarifa fija según Puerto Mejillones.por nominacion usd 2401.90
B29: C) | C29: Agency Expenses
C30: Agency Fee | D30: 1200 | E30: =+D30*100/$D$32 -> 2.4020727 | F30: Tarifa fija.B&M por Agenciamiento de Nave.
C31: Hose conection/Portalon | D31: 2500 | E31: =+D31*100/$D$32 -> 5.0043181 | F31: Tarifa fija.B&M .
C32: T O T A L | D32: =SUM(D14:D31) -> 49956.856 | E32: =+D32*100/$D$32 -> 100
C34: En base a 30 horas de operación.
C35: Carga de 13,500.00TN SUA.
C36: OBSERVACIONES :
C37: * INCLUYE MUELLAJE
C38: *LIGHT DUES CHILE = USD 4.07 /GRT POR AÑO : USD 33,614.13( 0.11 incremento 2026 USD 4.07 en USD 1,250.15)
C39: * ADELANTOS POR CADA VIAJE MENSUALES $ 18,000.00 para B&M.
C40: *DE ACUERDO A PROFORMA ENVIADA POR B&M .

Sheet BARQUITO
C4: COMPARATIVO DE COSTOS B/T MOQUEGUA
C5: BARQUITO
C7: Eslora : 134.16 mtrs.
C8: DW : 14,298.00 mtons.
C9: GRT : 8,259.00 mtons.
D11: B&M | F11: OBSERVACIONES
D12: US$ | E12: %
B13: A) | C13: Shifting Expenses
C14: Pilotage. | D14: 1803 | E14: =+D14*100/D33 -> 2.1351428 | F14: Tarifa fija según Autoridad Maritima.
C15: Towage. | D15: 38460 | E15: =+D15*100/$D$33 -> 45.544977 | F15: Tarifa Ultratug.(Tarifario Publico )
C16: Pilot Insurance. | D16: 330 | E16: =+D16*100/$D$33 -> 0.39079153 | F16: Tarifa Fija por 2 seguros de practico $80.00 c/u.
C17: Linesmen. | D17: 2350 | E17: =+D17*100/$D$33 -> 2.7829094 | F17: Tarifa fija según SMPs amarradores en tierra.
B19: B) | C19: General Port Expenses
C20: Ligth Dues. | D20: 3500 | E20: =+D20*100/$D$33 -> 4.1447587 | F20: *LIGHT DUES CHILE = USD 4.07 /GRT POR AÑO : USD 33,614.13 /15 viajes aprox
C21: Dockage /Muellaje | D21: 2000 | E21: =+D21*100/$D$33 -> 2.3684335 | F21: USD71.92 por hora (28 H)
C22: Launch Hire./Lanchas | D22: 7433 | E22: =+D22*100/$D$33 -> 8.8022832 | F22: T.Fija.Mooring /unmooring por maniobra/por lancha .Atlantic service.
C23: Pilot /Authorities Transport. | D23: 760 | E23: =+D23*100/$D$33 -> 0.90000474 | F23: Transporte en lancha de Piloto $ 70.00 c/u y Autoridades $ 220.00 .
C24: Tugboat stand by | D24: 18000 | E24: =+D24*100/$D$33 -> 21.315902 | F24: Tarifa Ultratug.( Concepto exigido por Autoridad Martima) $675 por hora.
C25: Immigration Authorities. | D25: 28 | E25: =+D25*100/$D$33 -> 0.033158069 | F25: Tarifa fija según Policia de Investigacion de Chile.
C26: Health authorities. | D26: 130 | E26: =+D26*100/$D$33 -> 0.15394818 | F26: Tarifa fija según Sanidad maritima.
C27: Other port services. | E27: =+D27*100/$D$33 -> 0 | F27: Arriendo & Handling de Espias segun necesidad.
C28: Launchboats Costs | D28: 6000 | E28: =+D28*100/$D$33 -> 7.1053006 | F28: 2nd tug navigation/10hrs rountrip.
B29: C) | C29: Agency Expenses
C30: Loading Master | D30: 2450 | E30: =+D30*100/$D$33 -> 2.9013311
C31: Agency Fee | D31: 1200 | E31: =+D31*100/$D$33 -> 1.4210601 | F31: Tarifa fija.B&M por Agenciamiento de Nave.
C33: T O T A L | D33: =SUM(D14:D32) -> 84444 | E33: =+D33*100/$D$33 -> 100
C36: Carga de 13,500.00TN SUA.
C37: OBSERVACIONES :
C38: * INCLUYE MUELLAJE
C39: *LIGHT DUES CHILE = USD 4.07 /GRT POR AÑO : USD 33,614.13( 0.11 incremento 2026 USD 4.07 en USD 1,250.15)
C40: * ADELANTOS POR CADA VIAJE MENSUALES $ 18,000.00 para B&M.

Sheet RESUMEN PERU
B2: COSTOS PORTUARIOS BT MOQUEGUA 2026 SIN IGV.
B4: PUERTOS DE DESTINO | D4: ILO | E4: ILO-PATIO PUERTO | F4: MATARANI | G4: MARCONA | H4: CALLAO
B5: TRANSTOTAL AGENCIA MARITIMA | D5: SIN IGV * | E5: SIN IGV * | F5: SIN IGV * | G5: SIN IGV * | H5: SIN IGV *
B6: * | D6: USD | E6: USD | F6: USD | G6: USD | H6: USD
B7: Transtotal Agencia Maritima. | D7: =+ILO!D22+ILO!D24+ILO!D25+ILO!D26+ILO!D27+ILO!D28+ILO!D30+ILO!D31+ILO!D19 -> 7541 | E7: =+'ilo patio puerto'!D13+'ilo patio puerto'!D15+'ilo patio puerto'!D17+'ilo patio puerto'!D18+'ilo patio puerto'!D19+'ilo patio puerto'!D20+'ilo patio puerto'!D22+'ilo patio puerto'!D23 -> 5836 | F7: =+MATARANI!D21+MATARANI!D23+MATARANI!D24+MATARANI!D25+MATARANI!D26+MATARANI!D27+MATARANI!D29+MATARANI!D30 -> 4261 | G7: =+MARCONA!D20+MARCONA!D23+MARCONA!D24+MARCONA!D25+MARCONA!D26+MARCONA!D29+MARCONA!D30 -> 3048 | H7: =+CALLAO!D14+CALLAO!D18+CALLAO!D20+CALLAO!D21+CALLAO!D22+CALLAO!D24+CALLAO!D25 -> 4798
B8: Port Operation & Services- Practicaje | D8: 3000 | E8: =+'ilo patio puerto'!D10 -> 3000
B9: Petranso-Petrolera Transoceanica | D9: =+ILO!D17 -> 4000 | E9: =+'ilo patio puerto'!D12 -> 4000 | H9: =+CALLAO!D15 -> 3200
B10: Remolcaje PSA Marine | D10: =+ILO!D16 -> 5200 | E10: =+'ilo patio puerto'!D11 -> 4600 | F10: =+MATARANI!D15+MATARANI!D16+MATARANI!D17 -> 7280 | G10: =+MARCONA!D16 -> 36000
B11: Southern /TISUR/APM | D11: =+ILO!D23 -> 830 | E11: =+'ilo patio puerto'!D16 -> 1245 | F11: =+MATARANI!D22 -> 3000 | H11: =+CALLAO!D19 -> 7146
B13: TOTAL USD | D13: =SUM(D7:D11) -> 20571 | E13: =SUM(E7:E11) -> 18681 | F13: =SUM(F7:F11) -> 14541 | G13: =SUM(G7:G11) -> 39048 | H13: =SUM(H7:H11) -> 15144
B16: *TOTAL USD SIN MUELLAJE | D16: =+D13 -> 20571 | E16: =+E13 -> 18681 | F16: =+F13-F11 -> 11541 | G16: =+G13-G11 -> 39048 | H16: =+H13 -> 15144
B20: * Informacion preparada en base a proformas y tarifas por Agente Maritimo Transtotal , Psa Marine,Petranso, TISUR,APM,Port Operation aplicables a partir de Febrero 2026.
B22: * No incluye IGV.
B23: * No incluye Muellaje
B24: * No incluye recargos.
B25: * Costo PSA Marine en Puerto Marcona ( sin incluir recargos )
B29: H/P Naviera Petral / Sandra Galvez
B30: =+TODAY() -> 46204

Sheet  RESUMEN CHILE
B2: COSTOS PORTUARIOS BT MOQUEGUA 2026
B6: PUERTOS DE DESTINO | D6: MEJILLONES | E6: MEJILLONES INTERACID | F6: TERQUIM | G6: BARQUITO
B7: B&M AGENTES MARITIMOS
B8: * | D8: USD | E8: USD | F8: USD | G8: USD
B9: B&M Agencia Maritima/Puerto Mejillones /Autoridad Maritima | D9: =42850-17000-10400 -> 15450 | E9: =+MEJILLONES.INTERACID!D31-MEJILLONES.INTERACID!D21-MEJILLONES.INTERACID!D15 -> 14655 | F9: =+MEJILLONES.TERQUIM!D32-MEJILLONES.TERQUIM!D15-MEJILLONES.TERQUIM!D23 -> 18535 | G9: =+BARQUITO!D14+BARQUITO!D16+BARQUITO!D17+BARQUITO!D20+BARQUITO!D22+BARQUITO!D23+BARQUITO!D25+BARQUITO!D26+BARQUITO!D27+BARQUITO!D28+BARQUITO!D31 -> 23534
B10: B&M / Dockage-Muellaje | D10: =+MEJILLONES.A!D19 -> 22810.032 | E10: =+MEJILLONES.INTERACID!D21 -> 20000 | F10: =+MEJILLONES.TERQUIM!D23 -> 23021.856 | G10: =+BARQUITO!D21 -> 2000
B11: B&M /Remolcaje Stand by ULTRATUG | D11: =+MEJILLONES.A!D13 -> 11200 | G11: =+BARQUITO!D24 -> 18000
B12: B&M/Remolcaje ULTRATUG | D12: =+MEJILLONES.A!D12 -> 1808.62 | E12: =+MEJILLONES.INTERACID!D15 -> 11200 | F12: =+MEJILLONES.TERQUIM!D15 -> 8400 | G12: =+BARQUITO!D15 -> 38460
B13: *TOTAL USD | D13: =SUM(D9:D12) -> 51268.652 | E13: =SUM(E9:E12) -> 45855 | F13: =SUM(F9:F12) -> 49956.856 | G13: =SUM(G9:G12) -> 81994
B16: TOTAL USD SIN MUELLAJE-REMOLCAJE STAND BY BARQUITO | D16: =+D13-D10 -> 28458.62 | E16: =+E13-E10 -> 25855 | F16: =+F13-F10 -> 26935 | G16: =+G13-G10-G11 -> 61994
B20: * Informacion preparada en base a proformas de Agente Maritimo B&M.
B22: * Incluye cargo de remolcadores correspondiente a regulacion local con tarifa correspondiente según acuerdo con remolcador Ultratug.
B23: para Barquito un aproximado de 40 horas de estadia.
B25: =+'RESUMEN PERU'!B29 -> H/P Naviera Petral / Sandra Galvez
B26: =+TODAY() -> 46204

Sheet Hoja2
B2: B&M AGENTES MARITIMOS | D2: 2017-2023 | E2: 2024 | F2: INCREMENTO
B3: Serv.Transporte Maritimo Atlantic Service. | D3: USD | E3: USD | F3: USD | H3: A. Detalle de servicios. USD 1,800 | L3: 1480 | M3: =+L3-1800 -> -320 | P3: 34 | R3: =+P3*320 -> 10880
B5: Servicio de lanchas marre, desamarre, recepcion , despacho | D5: 1480 | E5: 1800 | F5: =+E5-D5 -> 320 | H5: 2 lanchas para Amarra
B6: Recargos adicionales fondeo/horario normal / por hora | D6: 340 | E6: 340 | F6: =+E6-D6 -> 0 | H6: 1 lancha para desamarra
B7: Recargos adicionales viajes /horario normal / por hora | D7: 150 | E7: 150 | F7: =+E7-D7 -> 0
B8: Recargos adicionales fondeo / feriados y horas nocturnas/ por hora | D8: 510 | E8: 510 | F8: =+E8-D8 -> 0 | H8: 1 recepción
B9: Recargos adicionales por viajes / feriados y horas nocturnas/ por hora | D9: 220 | E9: 220 | F9: =+E9-D9 -> 0
B10: TOTAL USD | D10: =SUM(D5:D6) -> 1820 | E10: =SUM(E5:E6) -> 2140 | F10: =SUM(F5:F8) -> 320 | H10: 1 despacho
H12: B. Servicios adicionales
B13: H/P Naviera Petral | H13: Adicional horario normal (hábil)
B14: Enero 2024.
H15: Fondeo : USD 340 X HR | L15: 350
H16: Viajes : USD 150 X HR | L16: 150
H18: Adicional horario nocturno y festivos
H20: Fondeo : USD 510 X HR | L20: 510
H21: Viajes : USD 225 X HR. | L21: 220

Sheet Hoja1
C4: COMPARATIVO DE COSTOS B/T MOQUEGUA
C5: TERQUIM
D7: B&M | F7: OBSERVACIONES
D8: US$ | E8: %
B9: A) | C9: Shifting Expenses
C10: Towage. | D10: 10400 | E10: =+D10*100/$D$18 -> 46.436864 | F10: Tarifa Fija. 2024 $ 5,200 por maniobra mooring/unmooring- Remolcadores Ultratug Ltd.
B12: B) | C12: General Port Expenses
C13: Ligth Dues. | D13: 5000 | E13: =+D13*100/$D$18 -> 22.325415 | F13: USD 3.74 /GRT por año./3 viajes.
C14: Loading Master | D14: 3996 | E14: =+D14*100/$D$18 -> 17.842472 | F14: Tarifa fija según Puerto Mejillones.por nominacion usd 2401.90
B15: C) | C15: Agency Expenses
C16: Agency Fee | D16: 1200 | E16: =+D16*100/$D$18 -> 5.3580997 | F16: Tarifa fija.B&M por Agenciamiento de Nave.
C17: Hose conection | D17: 1800 | E17: =+D17*100/$D$18 -> 8.0371495
C18: T O T A L | D18: =SUM(D10:D17) -> 22396 | E18: =+D18*100/$D$18 -> 100
C21: OBSERVACIONES :
C22: *NO INCLUYE MUELLAJE
C23: *LIGHT DUES CHILE = USD 3.74 /GRT POR AÑO : USD 30,888.66
C24: * ADELANTOS POR CADA VIAJES MENSUALES $ 18,000.00 para B&M.
C25: *CARGA DE 13,500 TM -SUA

Sheet BOMAR PORT COST 2021-2024
B1: COSTOS PORTUARIOS 2021-2024
B2: BOMAR LYNX
B3: Mtons 13,500.00
B5: PUERTO DE DESTINO | D5: MEJILLONES | E5: MEJILLONES | F5: MEJILLONES | G5: MEJILLONES
B6: B&M AGENTES MARITIMOS | D6: 2021 | E6: 2022 | F6: 2023 | G6: 2024
B7: * | D7: USD | E7: USD | F7: USD | G7: USD
B8: B&M Agencia Maritima/Puerto Mejillones /Autoridad Maritima/Lanchas/Faros y Balizas/Pilot/Loading Master/Salud. | D8: 12500 | E8: 13000 | F8: =42850-17000-10400 -> 15450 | G8: 15450
B9: B&M / Dockage-Muellaje | D9: 15455 | E9: 16000 | F9: 16000 | G9: 17000
B10: B&M /Remolcaje Stand by ULTRATUG
B11: B&M /Lancha Stand by
B12: B&M/Remolcaje ULTRATUG * | D12: 8400 | E12: 9200 | F12: 10000 | G12: 10400
B13: *TOTAL USD | D13: =SUM(D8:D12) -> 36355 | E13: =SUM(E8:E12) -> 38200 | F13: =SUM(F8:F12) -> 41450 | G13: =SUM(G8:G12) -> 42850
B16: TOTAL USD SIN MUELLAJE | D16: =+D13-D9 -> 20900 | E16: =+E13-E9 -> 22200 | F16: =+F13-F9 -> 25450 | G16: =+G13-G9 -> 25850
C18: DIFERENCIAL POR AÑO USD | E18: =+E16-D16 -> 1300 | F18: =+F16-E16 -> 3250 | G18: =+G16-F16 -> 400
C21: DIFERENCIAL POR AÑO % | D21: =+D18*1/D16 -> 0 | E21: =+E18*1/E16 -> 0.058558559 | F21: =+F18*1/F16 -> 0.12770138 | G21: =+G18*1/G16 -> 0.015473888
B23: Nota: El incremento de tarifa en los costos se origina principalmente por el incremento de tarifa de Remolcaje con Ultratug.
B25: *Incluye cargo de remolcadores correspondiente a regulacion local, con tarifa correspondiente acuerdo con Ultratug vigente desde el mes de Agosto 2023 hasta Agosto 2024.
B26: ** De acuerdo a proformas de Agentes Maritimos B&M .
B28: H/P Naviera Petral
B29: 45292
