Workbook

Sheet ilo patio puerto
C4: COMPARATIVO DE COSTOS B/T MOQUEGUA
C5: ILO PATIO PUERTO
D7: TRANSTOTAL | E7: % | F7: OBSERVACIONES
D8: US$
B9: A) | C9: Shifting Expenses
C10: Practicaje | D10: 3000 | E10: =+D10*100/D24 -> 16.059097 | F10: Tarifa Port Opeartions $ 1,500 por maniobra.
C11: Towage /Remolcaje | D11: 4600 | E11: =+D11*100/$D$24 -> 24.623949 | F11: Tarifa-PSA Marine $ 0.16 x Trb.8259
C12: Towage /Remolcaje | D12: 4000 | E12: =+D12*100/$D$24 -> 21.41213 | F12: Petranso Remolcadores Tarifa $ 0.1785 x Trb 8259 sujeta a 10% descuentos, posicionamiento $ 1400
C13: Recargos | D13: 1500 | E13: =+D13*100/$D$24 -> 8.0295487
B14: B) | C14: General Port Expenses | E14: =+D14*100/$D$24 -> 0
C15: Lighthouse Dues | D15: 891 | E15: =+D15*100/$D$24 -> 4.769552 | F15: Tarifa Direccion de Hidrografia y navegacion
C16: Dockage /Muellaje | D16: 1245 | E16: =+D16*100/$D$24 -> 6.6645255 | F16: SPCC, Tarifa deAmarre y desamarre $ 300.00 , y Muelle SPCC $ 0.05 x Trb x dia.
C17: Launch Hire. | D17: 1300 | E17: =+D17*100/$D$24 -> 6.9589422 | F17: Transtotal.Fija.Mooring /unmooring ,pilot,posicionamiento por maniobra/por lancha.
C18: Coordinator on board | D18: 225 | E18: =+D18*100/$D$24 -> 1.2044323 | F18: Transtotal. Tarifa Fija por Nave.
C19: Clearance (In/Out) | D19: 200 | E19: =+D19*100/$D$24 -> 1.0706065 | F19: Region Moquegua. Tarifa
C20: Sanitary Inspection (Reception/Dispatch) | D20: 520 | E20: =+D20*100/$D$24 -> 2.7835769 | F20: Tarifa fija según Sanidad maritima.
B21: C) | C21: Agency Expenses | E21: =+D21*100/$D$24 -> 0
C22: Agency Fee | D22: 1000 | E22: =+D22*100/$D$24 -> 5.3530325 | F22: Tarifa fija. Transtotal por Agenciamiento de Nave.
C23: Transportation | D23: 200 | E23: =+D23*100/$D$24 -> 1.0706065 | F23: Tarifa fija. Transtotal por Nave.
C24: T O T A L | D24: =SUM(D9:D23) -> 18681 | E24: =+D24*100/$D$24 -> 100
D26: 19181
C27: OBSERVACIONES : | D27: =+D26-D24 -> 500
C28: *INCLUYE MUELLAJE.
C29: *NO INCLUYE IGV.
C30: *NO INCLUYE RECARGOS PSA MARINE/PETRANSO
C31: Time in port (hrs) 30 -Carga de 13,500.00TN SUA.

Sheet MARCONA
E4: Moquegua | G4: Tablones | I4: Huemul | K4: Concon Trader
E6: Eslora : 134.16 mtrs. | F6: 134.16 | G6: Eslora : | H6: 158.8 | I6: Eslora : | J6: 161.12 | K6: Eslora : | L6: 145.53
E7: DW : 14,298.00 mtons. | G7: DW : | H7: 16533 | I7: DW : | J7: 22062 | K7: DW : | L7: 19823.15
E8: GRT : 8,259.00 mtons. | F8: 8259 | G8: GRT : | H8: 11365 | I8: GRT : | J8: 13666 | K8: GRT | L8: 11773
E9: carga | F9: 13500 | G9: carga | H9: 14500 | I9: carga | J9: 14500 | K9: carga | L9: 14500
E10: rtimo | F10: 500 | G10: rtimo | H10: 500 | I10: rtimo | J10: 500 | K10: rtimo | L10: 500
E11: horas | F11: =F9/F10+3+2 -> 32 | G11: horas | H11: =H9/H10+3+2 -> 34 | I11: horas | J11: =J9/J10+3+2 -> 34 | K11: horas | L11: =L9/L10+3+2 -> 34
E12: PAIS ORIGEN: | F12: Peru | G12: PAIS ORIGEN: | H12: Peru | I12: PAIS ORIGEN: | J12: Peru | K12: PAIS ORIGEN: | L12: Peru
C14: t/c
C15: ITEMS | D15: TARIFA | E15: CANTIDAD | F15: TRANSTOTAL | G15: CANTIDAD | H15: TRANSTOTAL | I15: CANTIDAD | J15: TRANSTOTAL | K15: CANTIDAD | L15: TRANSTOTAL | M15: OBSERVACIONES
F16: US$ | H16: US$ | J16: US$ | L16: US$
B17: A) | C17: Shifting Expenses
C18: Practicaje + Launch for pílot | D18: 4980 | E18: 2 | F18: =D18*E18 -> 9960 | G18: 2 | H18: =G18*$D$18 -> 9960 | I18: 2 | J18: =I18*$D$18 -> 9960 | K18: 2 | L18: =K18*$D$18 -> 9960 | M18: Tarifa PSA MARINE ($4,980*Mnver + 18%vat) por maniobra.
C19: Linesmen /amarre y desamarre( Por maniobra) | D19: 4450 | E19: 2 | F19: =D19*E19 -> 8900 | G19: 2 | H19: =G19*$D$19 -> 8900 | I19: 2 | J19: =I19*$D$19 -> 8900 | K19: 2 | L19: =K19*$D$19 -> 8900 | M19: Tarifa PSA MARINE ($4,450*Launchboat + 18%vat) .(incluye 2 lanchas y gavieras )
C20: Towage /Remolcaje ( Por maniobra) | D20: 18000 | E20: 2 | F20: =D20*E20 -> 36000 | G20: 2 | H20: =G20*$D$20 -> 36000 | I20: 2 | J20: =I20*$D$20 -> 36000 | K20: 2 | L20: =K20*$D$20 -> 36000 | M20: Tarifa PSA MARINE ( $18,000*Mnver + 18%vat) por maniobra 2.
C21: Port toll /Land transport /terminal fee | D21: 75 | E21: 2 | F21: =D21*E21 -> 150 | G21: 2 | H21: =D21*G21 -> 150 | I21: 2 | J21: =D21*I21 -> 150 | K21: 2 | L21: =D21*K21 -> 150
B22: B) | C22: General Port Expenses
C23: Lighthouse Dues (Aplica si el buque viene de PUERTO NACIONAL) | D23: 0.03 | E23: =IF(F$12="Peru",$D$23,"") -> 0.03 | F23: =IF(E23="","",$D$23*F8) -> 247.77 | G23: =IF(H$12="Peru",$D$23,"") -> 0.03 | H23: =IF(G23="","",$D$23*H8) -> 340.95 | I23: =IF(J$12="Peru",$D$23,"") -> 0.03 | J23: =IF(I23="","",$D$23*J8) -> 409.98 | K23: =IF(L$12="Peru",$D$23,"") -> 0.03 | L23: =IF(K23="","",$D$23*L8) -> 353.19 | M23: Tarifa Direccion de Hidrografia y navegacion.
C24: Lighthouse Dues (Aplica si el buque viene de PUERTO EXTRANJERO) | D24: 0.12 | E24: =IF(F$12="Peru",$D$24,"") -> 0.12 | F24: =IF(E24="","",$D$24*F8) -> 991.08 | G24: =IF(H$12="Peru",$D$24,"") -> 0.12 | H24: =IF(G24="","",$D$24*H8) -> 1363.8 | I24: =IF(J$12="Peru",$D$24,"") -> 0.12 | J24: =IF(I24="","",$D$24*J8) -> 1639.92 | K24: =IF(L$12="Peru",$D$24,"") -> 0.12 | L24: =IF(K24="","",$D$24*L8) -> 1412.76
C25: Coordinator on board | D25: 225 | E25: 2 | F25: =D25*E25 -> 450 | G25: 2 | H25: =D25*G25 -> 450 | I25: 2 | J25: =D25*I25 -> 450 | K25: 2 | L25: =D25*K25 -> 450 | M25: $ 225 per day +18%
C26: Clearance Expenses (In/Out) | D26: 200 | E26: 1 | F26: =D26*E26 -> 200 | G26: 1 | H26: =D26*G26 -> 200 | I26: 1 | J26: =D26*I26 -> 200 | K26: 1 | L26: =D26*K26 -> 200
C27: Sanitary Inspection (Reception/Dispatch) | D27: 670 | E27: 1 | F27: =D27*E27 -> 670 | G27: 1 | H27: =D27*G27 -> 670 | I27: 1 | J27: =D27*I27 -> 670 | K27: 1 | L27: =D27*K27 -> 670 | M27: Tarifa APN.
C28: Launch for Authorities | D28: 200 | E28: 1 | F28: =D28*E28 -> 200 | G28: 1 | H28: =D28*G28 -> 200 | I28: 1 | J28: =D28*I28 -> 200 | K28: 1 | L28: =D28*K28 -> 200 | M28: $ 200 * maneuver +18%
C29: Launch Hire (Stand By) | D29: 40 | E29: =F11 -> 32 | F29: =E29*$D$29 -> 1280 | G29: =H11 -> 34 | H29: =G29*$D$29 -> 1360 | I29: =J11 -> 34 | J29: =I29*$D$29 -> 1360 | K29: =L11 -> 34 | L29: =K29*$D$29 -> 1360 | M29: $40X HORA aproximado de 40 horas (Tarifa PSA Marine SA)
C30: Remolcaje Stand by.( Por maniobra) | D30: 16000 | M30: $ 3,000.00 * a partir de 60 horas.
B31: C) | C31: Agency Expenses
C32: Agency Fee | D32: 1400 | E32: 1 | F32: =D32*E32 -> 1400 | G32: 1 | H32: =D32*G32 -> 1400 | I32: 1 | J32: =D32*I32 -> 1400 | K32: 1 | L32: =D32*K32 -> 1400 | M32: Tarifa fija Transtotal por Agenciamiento de Nave.
C33: Transportation (Autoridades,coordinador y personal operativo) | D33: 200 | E33: 1 | F33: =D33*E33 -> 200 | G33: 1 | H33: =D33*G33 -> 200 | I33: 1 | J33: =D33*I33 -> 200 | K33: 1 | L33: =D33*K33 -> 200 | M33: Tarifa fija Transtotal
C34: Comunication | D34: 250 | E34: 1 | F34: =D34*E34 -> 250 | G34: 1 | H34: =D34*G34 -> 250 | I34: 1 | J34: =D34*I34 -> 250 | K34: 1 | L34: =D34*K34 -> 250 | M34: Tarifa fija Transtotal
C36: T O T A L | F36: =SUM(F18:F35) -> 60898.85 | H36: =SUM(H18:H34) -> 61444.75 | J36: =SUM(J18:J34) -> 61789.9 | L36: =SUM(L18:L34) -> 61505.95
C39: OBSERVACIONES : | F39: Las tarifas resaltadas corresponden a servicios licitados por Marcobre, para el cual la empresa ganadora fue PSA Marine; dichas tarifas se encuentran confirmadas. Servicio de Remolcaje Stand By a partir de 60 horas aplica USD 3,000.00 diario por cada remolcador por dia y fraccion. Aún no se ha confirmado por el lado del terminal si estarán considerando una tarifa por el Uso de Amarradero o si se requerirá de una Lancha de Permanencia para los operativos, lo cual incrementaría los costos de la proforma en caso se confirmen. Se está considerando que la nave procede de un Puerto Nacional y será despachada a un Puerto Nacional.
C40: *NO INCLUYE MUELLAJE.
C41: *NO INCLUYE IGV.
C42: * NO APLICA RECARGOS.

Sheet RESUMEN PERU
B2: COSTOS PORTUARIOS BT MOQUEGUA 2026 SIN IGV.
B4: PUERTOS DE DESTINO | D4: ILO | E4: ILO-PATIO PUERTO | F4: MATARANI | G4: MARCONA | H4: CALLAO
B5: TRANSTOTAL AGENCIA MARITIMA | D5: SIN IGV * | E5: SIN IGV * | F5: SIN IGV * | G5: SIN IGV * | H5: SIN IGV *
B6: * | D6: USD | E6: USD | F6: USD | G6: USD | H6: USD
B7: Transtotal Agencia Maritima. | D7: =+#REF!+#REF!+#REF!+#REF!+#REF!+#REF!+#REF!+#REF!+#REF! -> #REF! | E7: =+'ilo patio puerto'!D13+'ilo patio puerto'!D15+'ilo patio puerto'!D17+'ilo patio puerto'!D18+'ilo patio puerto'!D19+'ilo patio puerto'!D20+'ilo patio puerto'!D22+'ilo patio puerto'!D23 -> 5836 | F7: =+#REF!+#REF!+#REF!+#REF!+#REF!+#REF!+#REF!+#REF! -> #REF! | G7: =+MARCONA!F23+MARCONA!F25+MARCONA!F26+MARCONA!F27+MARCONA!F28+MARCONA!F32+MARCONA!F33 -> 3367.77 | H7: =+#REF!+#REF!+#REF!+#REF!+#REF!+#REF!+#REF! -> #REF!
B8: Port Operation & Services- Practicaje | D8: 3000 | E8: =+'ilo patio puerto'!D10 -> 3000
B9: Petranso-Petrolera Transoceanica | D9: =+#REF! -> #REF! | E9: =+'ilo patio puerto'!D12 -> 4000 | H9: =+#REF! -> #REF!
B10: Remolcaje PSA Marine | D10: =+#REF! -> #REF! | E10: =+'ilo patio puerto'!D11 -> 4600 | F10: =+#REF!+#REF!+#REF! -> #REF! | G10: =+MARCONA!F20 -> 36000
B11: Southern /TISUR/APM | D11: =+#REF! -> #REF! | E11: =+'ilo patio puerto'!D16 -> 1245 | F11: =+#REF! -> #REF! | H11: =+#REF! -> #REF!
B13: TOTAL USD | D13: =SUM(D7:D11) -> #REF! | E13: =SUM(E7:E11) -> 18681 | F13: =SUM(F7:F11) -> #REF! | G13: =SUM(G7:G11) -> 39367.77 | H13: =SUM(H7:H11) -> #REF!
B16: *TOTAL USD SIN MUELLAJE | D16: =+D13 -> #REF! | E16: =+E13 -> 18681 | F16: =+F13-F11 -> #REF! | G16: =+G13-G11 -> 39367.77 | H16: =+H13 -> #REF!
B20: * Informacion preparada en base a proformas y tarifas por Agente Maritimo Transtotal , Psa Marine,Petranso, TISUR,APM,Port Operation aplicables a partir de Febrero 2026.
B22: * No incluye IGV.
B23: * No incluye Muellaje
B24: * No incluye recargos.
B25: * Costo PSA Marine en Puerto Marcona ( sin incluir recargos )
B29: H/P Naviera Petral / Sandra Galvez
B30: =+TODAY() -> 46211

Sheet  RESUMEN CHILE
B2: COSTOS PORTUARIOS BT MOQUEGUA 2026
B6: PUERTOS DE DESTINO | D6: MEJILLONES | E6: MEJILLONES INTERACID | F6: TERQUIM | G6: BARQUITO
B7: B&M AGENTES MARITIMOS
B8: * | D8: USD | E8: USD | F8: USD | G8: USD
B9: B&M Agencia Maritima/Puerto Mejillones /Autoridad Maritima | D9: =42850-17000-10400 -> 15450 | E9: =+#REF!-#REF!-#REF! -> #REF! | F9: =+#REF!-#REF!-#REF! -> #REF! | G9: =+#REF!+#REF!+#REF!+#REF!+#REF!+#REF!+#REF!+#REF!+#REF!+#REF!+#REF! -> #REF!
B10: B&M / Dockage-Muellaje | D10: =+#REF! -> #REF! | E10: =+#REF! -> #REF! | F10: =+#REF! -> #REF! | G10: =+#REF! -> #REF!
B11: B&M /Remolcaje Stand by ULTRATUG | D11: =+#REF! -> #REF! | G11: =+#REF! -> #REF!
B12: B&M/Remolcaje ULTRATUG | D12: =+#REF! -> #REF! | E12: =+#REF! -> #REF! | F12: =+#REF! -> #REF! | G12: =+#REF! -> #REF!
B13: *TOTAL USD | D13: =SUM(D9:D12) -> #REF! | E13: =SUM(E9:E12) -> #REF! | F13: =SUM(F9:F12) -> #REF! | G13: =SUM(G9:G12) -> #REF!
B16: TOTAL USD SIN MUELLAJE-REMOLCAJE STAND BY BARQUITO | D16: =+D13-D10 -> #REF! | E16: =+E13-E10 -> #REF! | F16: =+F13-F10 -> #REF! | G16: =+G13-G10-G11 -> #REF!
B20: * Informacion preparada en base a proformas de Agente Maritimo B&M.
B22: * Incluye cargo de remolcadores correspondiente a regulacion local con tarifa correspondiente según acuerdo con remolcador Ultratug.
B23: para Barquito un aproximado de 40 horas de estadia.
B25: =+'RESUMEN PERU'!B29 -> H/P Naviera Petral / Sandra Galvez
B26: =+TODAY() -> 46211

Sheet Hoja2
B2: B&M AGENTES MARITIMOS | D2: 2017-2023 | E2: 2024 | F2: INCREMENTO
B3: Serv.Transporte Maritimo Atlantic Service. | D3: USD | E3: USD | F3: USD | H3: A. Detalle de servicios. USD 1,800 | L3: 1480 | M3: =+L3-1800 -> -320 | P3: 34 | R3: =+P3*320 -> 10880
B5: Servicio de lanchas marre, desamarre, recepcion , despacho | D5: 1480 | E5: 1800 | F5: =+E5-D5 -> 320 | H5: 2 lanchas para Amarra
B6: Recargos adicionales fondeo/horario normal / por hora | D6: 340 | E6: 340 | F6: =+E6-D6 -> 0 | H6: 1 lancha para desamarra
B7: Recargos adicionales viajes /horario normal / por hora | D7: 150 | E7: 150 | F7: =+E7-D7 -> 0
B8: Recargos adicionales fondeo / feriados y horas nocturnas/ por hora | D8: 510 | E8: 510 | F8: =+E8-D8 -> 0 | H8: 1 recepción
B9: Recargos adicionales por viajes / feriados y horas nocturnas/ por hora | D9: 220 | E9: 220 | F9: =+E9-D9 -> 0
B10: TOTAL USD | D10: =SUM(D5:D6) -> 1820 | E10: =SUM(E5:E6) -> 2140 | F10: =SUM(F5:F8) -> 320 | H10: 1 despacho
H12: B. Servicios adicionales
B13: H/P Naviera Petral | H13: Adicional horario normal (hábil)
B14: Enero 2024.
H15: Fondeo : USD 340 X HR | L15: 350
H16: Viajes : USD 150 X HR | L16: 150
H18: Adicional horario nocturno y festivos
H20: Fondeo : USD 510 X HR | L20: 510
H21: Viajes : USD 225 X HR. | L21: 220

Sheet Hoja1
C4: COMPARATIVO DE COSTOS B/T MOQUEGUA
C5: TERQUIM
D7: B&M | F7: OBSERVACIONES
D8: US$ | E8: %
B9: A) | C9: Shifting Expenses
C10: Towage. | D10: 10400 | E10: =+D10*100/$D$18 -> 46.436864 | F10: Tarifa Fija. 2024 $ 5,200 por maniobra mooring/unmooring- Remolcadores Ultratug Ltd.
B12: B) | C12: General Port Expenses
C13: Ligth Dues. | D13: 5000 | E13: =+D13*100/$D$18 -> 22.325415 | F13: USD 3.74 /GRT por año./3 viajes.
C14: Loading Master | D14: 3996 | E14: =+D14*100/$D$18 -> 17.842472 | F14: Tarifa fija según Puerto Mejillones.por nominacion usd 2401.90
B15: C) | C15: Agency Expenses
C16: Agency Fee | D16: 1200 | E16: =+D16*100/$D$18 -> 5.3580997 | F16: Tarifa fija.B&M por Agenciamiento de Nave.
C17: Hose conection | D17: 1800 | E17: =+D17*100/$D$18 -> 8.0371495
C18: T O T A L | D18: =SUM(D10:D17) -> 22396 | E18: =+D18*100/$D$18 -> 100
C21: OBSERVACIONES :
C22: *NO INCLUYE MUELLAJE
C23: *LIGHT DUES CHILE = USD 3.74 /GRT POR AÑO : USD 30,888.66
C24: * ADELANTOS POR CADA VIAJES MENSUALES $ 18,000.00 para B&M.
C25: *CARGA DE 13,500 TM -SUA

Sheet BOMAR PORT COST 2021-2024
B1: COSTOS PORTUARIOS 2021-2024
B2: BOMAR LYNX
B3: Mtons 13,500.00
B5: PUERTO DE DESTINO | D5: MEJILLONES | E5: MEJILLONES | F5: MEJILLONES | G5: MEJILLONES
B6: B&M AGENTES MARITIMOS | D6: 2021 | E6: 2022 | F6: 2023 | G6: 2024
B7: * | D7: USD | E7: USD | F7: USD | G7: USD
B8: B&M Agencia Maritima/Puerto Mejillones /Autoridad Maritima/Lanchas/Faros y Balizas/Pilot/Loading Master/Salud. | D8: 12500 | E8: 13000 | F8: =42850-17000-10400 -> 15450 | G8: 15450
B9: B&M / Dockage-Muellaje | D9: 15455 | E9: 16000 | F9: 16000 | G9: 17000
B10: B&M /Remolcaje Stand by ULTRATUG
B11: B&M /Lancha Stand by
B12: B&M/Remolcaje ULTRATUG * | D12: 8400 | E12: 9200 | F12: 10000 | G12: 10400
B13: *TOTAL USD | D13: =SUM(D8:D12) -> 36355 | E13: =SUM(E8:E12) -> 38200 | F13: =SUM(F8:F12) -> 41450 | G13: =SUM(G8:G12) -> 42850
B16: TOTAL USD SIN MUELLAJE | D16: =+D13-D9 -> 20900 | E16: =+E13-E9 -> 22200 | F16: =+F13-F9 -> 25450 | G16: =+G13-G9 -> 25850
C18: DIFERENCIAL POR AÑO USD | E18: =+E16-D16 -> 1300 | F18: =+F16-E16 -> 3250 | G18: =+G16-F16 -> 400
C21: DIFERENCIAL POR AÑO % | D21: =+D18*1/D16 -> 0 | E21: =+E18*1/E16 -> 0.058558559 | F21: =+F18*1/F16 -> 0.12770138 | G21: =+G18*1/G16 -> 0.015473888
B23: Nota: El incremento de tarifa en los costos se origina principalmente por el incremento de tarifa de Remolcaje con Ultratug.
B25: *Incluye cargo de remolcadores correspondiente a regulacion local, con tarifa correspondiente acuerdo con Ultratug vigente desde el mes de Agosto 2023 hasta Agosto 2024.
B26: ** De acuerdo a proformas de Agentes Maritimos B&M .
B28: H/P Naviera Petral
B29: 45292
