Workbook
Name cr_control_presupuesto_consolidado: [1]Consolidado!#REF!

Sheet Presentacion

Sheet PETRAL
Z1: =+MONTH(B3) -> 5
B2: Control Presupuestal
B3: 46143 | D3: NAVIERA PETRAL
Q5: REAL | R5: PRESUP. | V5: PPTO. | X5: Real Acum.
B6: (US$ Dólares) | D6: ENE | E6: FEB | F6: MAR | G6: ABR | H6: MAY | I6: JUN | J6: JUL | K6: AGO | L6: SET | M6: OCT | N6: NOV | O6: DIC | Q6: ACUMUL. | R6: ACUMUL. | S6: VARIACION | T6: % | V6: ANUAL | X6: =+B3-365 -> 45778
B8: VENTAS | D8: 1722066.9 | E8: 2111191.9 | F8: 2658974.7 | G8: 1923319.5 | H8: 2702829.5 | I8: 0 | J8: 0 | K8: 0 | L8: 0 | M8: 0 | N8: 0 | O8: 0 | Q8: 11118382 | R8: 9709260 | S8: 1409122.5 | T8: 14.513181 | V8: 22433750 | X8: 8456501.7
A9: * HIRE | B9: HIRE | D9: 1041229.4 | E9: 1827318.9 | F9: 1992698.2 | G9: 1361976.8 | H9: 2170959.6 | I9: 0 | J9: 0 | K9: 0 | L9: 0 | M9: 0 | N9: 0 | O9: 0 | Q9: 8394183 | R9: 7732260 | S9: 661923.05 | T9: 8.5605379 | V9: 18193750 | X9: 6133555
A10: * VENTAS TERCEROS | B10: VENTA DE TERCEROS | D10: 0 | E10: 0 | F10: 0 | G10: 0 | H10: 0 | I10: 0 | J10: 0 | K10: 0 | L10: 0 | M10: 0 | N10: 0 | O10: 0 | Q10: 0 | R10: 0 | S10: 0 | T10: 0 | V10: 0 | X10: 0
A11: * DEMORAS | B11: DEMORAS | D11: 604689.25 | E11: 215350 | F11: 562537.01 | G11: 484964.72 | H11: 465646.06 | I11: 0 | J11: 0 | K11: 0 | L11: 0 | M11: 0 | N11: 0 | O11: 0 | Q11: 2333187 | R11: 1610000 | S11: 723187.04 | T11: 44.91845 | V11: 3460000 | X11: 2034225.3
A12: * INGRESOS DE PUERTO | B12: INGRESOS DE PUERTO | D12: 76148.21 | E12: 68522.9 | F12: 103739.51 | G12: 76377.98 | H12: 66223.77 | I12: 0 | J12: 0 | K12: 0 | L12: 0 | M12: 0 | N12: 0 | O12: 0 | Q12: 391012.37 | R12: 367000 | S12: 24012.37 | T12: 6.5428801 | V12: 780000 | X12: 288721.44
A13: 703117 OTROS ING OPERAC E | B13: OTROS INGRESOS | D13: 0 | E13: 0 | F13: 0 | G13: 0 | H13: 0 | I13: 0 | J13: 0 | K13: 0 | L13: 0 | M13: 0 | N13: 0 | O13: 0 | Q13: 0 | R13: 0 | S13: 0 | T13: 0 | V13: 0 | X13: 0
B15: COSTOS DIRECTOS | D15: -493471.6 | E15: -715684.56 | F15: -581044.39 | G15: -449259.96 | H15: -682277.99 | I15: 0 | J15: 0 | K15: 0 | L15: 0 | M15: 0 | N15: 0 | O15: 0 | Q15: -2921738.5 | R15: -2944787.4 | S15: 23048.93 | T15: -0.78270268 | V15: -6890694.2 | X15: -2465161.8
A16: * COMBUSTIBLE | B16: COMBUSTIBLE | D16: -177692.04 | E16: -232201.91 | F16: -187359 | G16: -189898.4 | H16: -237922.54 | I16: 0 | J16: 0 | K16: 0 | L16: 0 | M16: 0 | N16: 0 | O16: 0 | Q16: -1025073.9 | R16: -1207787.4 | S16: 182713.54 | T16: -15.127955 | V16: -2892694.1 | X16: -1077494.6
A17: * GASTOS DE PUERTO | B17: GASTOS DE PUERTO | D17: -315779.56 | E17: -483482.65 | F17: -390235.4 | G17: -259361.56 | H17: -330840.45 | I17: 0 | J17: 0 | K17: 0 | L17: 0 | M17: 0 | N17: 0 | O17: 0 | Q17: -1779699.6 | R17: -1737000 | S17: -42699.62 | T17: 2.4582395 | V17: -3998000 | X17: -1387667.2
A18: * COSTOS DEMORAS | B18: COSTOS DE DEMORA | D18: 0 | E18: 0 | F18: 0 | G18: 0 | H18: -112500 | I18: 0 | J18: 0 | K18: 0 | L18: 0 | M18: 0 | N18: 0 | O18: 0 | Q18: -112500 | R18: 0 | S18: -112500 | T18: 0 | V18: 0 | X18: 0
B19: COMISION BROCKERAGE | D19: 0 | E19: 0 | F19: 0 | G19: 0 | H19: 0 | I19: 0 | J19: 0 | K19: 0 | L19: 0 | M19: 0 | N19: 0 | O19: 0 | Q19: 0 | R19: 0 | S19: 0 | T19: 0 | V19: 0 | X19: 0
A20: * COMISIONES VARIAS | B20: COMISIONES VARIAS | D20: 0 | E20: 0 | F20: 0 | G20: 0 | H20: 0 | I20: 0 | J20: 0 | K20: 0 | L20: 0 | M20: 0 | N20: 0 | O20: 0 | Q20: 0 | R20: 0 | S20: 0 | T20: 0 | V20: 0 | X20: 0
A21: * OTROS COSTOS DIRECTOS | B21: OTROS COSTOS DIRECTOS | D21: 0 | E21: 0 | F21: -3449.99 | G21: 0 | H21: -1015 | I21: 0 | J21: 0 | K21: 0 | L21: 0 | M21: 0 | N21: 0 | O21: 0 | Q21: -4464.99 | R21: 0 | S21: -4464.99 | T21: 0 | V21: 0 | X21: 0
B22: GASTO PUERTO POR RECIBIR | D22: 0 | E22: 0 | F22: 0 | G22: 0 | H22: 0 | I22: 0 | J22: 0 | K22: 0 | L22: 0 | M22: 0 | N22: 0 | O22: 0 | Q22: 0 | R22: 0 | S22: 0 | T22: 0 | V22: 0 | X22: 0
B24: TIME CHARTER EQUIVALENT | D24: 1228595.3 | E24: 1395507.3 | F24: 2077930.3 | G24: 1474059.6 | H24: 2020551.5 | I24: 0 | J24: 0 | K24: 0 | L24: 0 | M24: 0 | N24: 0 | O24: 0 | Q24: 8196644 | R24: 6764472.6 | S24: 1432171.4 | T24: 21.171959 | V24: 15543056 | X24: 5991339.9
A26: 638101 FLETES NAVES TERCER | B26: COSTO DE ARRIENDO NAVES | D26: 0 | E26: 0 | F26: 0 | G26: 0 | H26: -417912.29 | I26: 0 | J26: 0 | K26: 0 | L26: 0 | M26: 0 | N26: 0 | O26: 0 | Q26: -417912.29 | R26: 0 | S26: -417912.29 | T26: 0 | V26: 0 | X26: 0
B28: MARGEN BRUTO | D28: 1228595.3 | E28: 1395507.3 | F28: 2077930.3 | G28: 1474059.6 | H28: 1602639.2 | I28: 0 | J28: 0 | K28: 0 | L28: 0 | M28: 0 | N28: 0 | O28: 0 | Q28: 7778731.7 | R28: 6764472.6 | S28: 1014259.1 | T28: 14.993913 | V28: 15543056 | X28: 3336817.2
B30: GTOS. PERSONAL A BORDO | D30: -307128.8 | E30: -401979.63 | F30: -337687.38 | G30: -324665.38 | H30: -343379.91 | I30: 0 | J30: 0 | K30: 0 | L30: 0 | M30: 0 | N30: 0 | O30: 0 | Q30: -1714841.1 | R30: -1856283.8 | S30: 141442.66 | T30: -7.619668 | V30: -4344043 | X30: -1548284.2
B31: GASTOS DE PERSONAL | D31: -307128.8 | E31: -401979.63 | F31: -337687.38 | G31: -324665.38 | H31: -343379.91 | I31: 0 | J31: 0 | K31: 0 | L31: 0 | M31: 0 | N31: 0 | O31: 0 | Q31: -1714841.1 | R31: -1856283.8 | S31: 141442.66 | T31: -7.619668 | V31: -4344043 | X31: -1548284.2
T32: 0
A33: * SUELDOS | B33: SUELDOS | D33: -185547.12 | E33: -279897.96 | F33: -193455.21 | G33: -203027.9 | H33: -209116.51 | I33: 0 | J33: 0 | K33: 0 | L33: 0 | M33: 0 | N33: 0 | O33: 0 | Q33: -1071044.7 | R33: -1046041.4 | S33: -25003.26 | T33: 2.3902743 | V33: -2411431.3 | X33: -982081.21
A34: * VACACIONES | B34: VACACIONES | D34: -12772.42 | E34: -13543.83 | F34: -12200.26 | G34: -12032.7 | H34: -19470.34 | I34: 0 | J34: 0 | K34: 0 | L34: 0 | M34: 0 | N34: 0 | O34: 0 | Q34: -70019.55 | R34: -80142.5 | S34: 10122.95 | T34: -12.631188 | V34: -195395.54 | X34: -45239.64
A35: * GRATIFICACIONES | B35: GRATIFICACIONES | D35: -19794.73 | E35: -22656.3 | F35: -32887.92 | G35: -28723.68 | H35: -36745.98 | I35: 0 | J35: 0 | K35: 0 | L35: 0 | M35: 0 | N35: 0 | O35: 0 | Q35: -140808.61 | R35: -212141.82 | S35: 71333.21 | T35: -33.625247 | V35: -487906.62 | X35: -116457.09
A36: * BENEFICIOS SOCIALES | B36: BENEFICIOS SOCIALES | D36: -22418.72 | E36: -15939.07 | F36: -18340.52 | G36: -802.07 | H36: -14930.08 | I36: 0 | J36: 0 | K36: 0 | L36: 0 | M36: 0 | N36: 0 | O36: 0 | Q36: -72430.46 | R36: -91666.2 | S36: 19235.74 | T36: -20.98455 | V36: -223491.6 | X36: -64643.3
A37: * ESSALUD | B37: ESSALUD | D37: -12214.01 | E37: -17548.28 | F37: -11487.45 | G37: -11360.94 | H37: -12646.21 | I37: 0 | J37: 0 | K37: 0 | L37: 0 | M37: 0 | N37: 0 | O37: 0 | Q37: -65256.89 | R37: -71318.9 | S37: 6062.01 | T37: -8.4998647 | V37: -173882.9 | X37: -56582.01
A38: * E.P.S. /GASTOS MEDICOS | B38: E.P.S. /GASTOS MEDICOS | D38: -7964.11 | E38: -9812.63 | F38: -6099.32 | G38: -895.91 | H38: -11480.44 | I38: 0 | J38: 0 | K38: 0 | L38: 0 | M38: 0 | N38: 0 | O38: 0 | Q38: -36252.41 | R38: -36000 | S38: -252.41 | T38: 0.70113889 | V38: -86400 | X38: -40647.63
A39: * VESTUARIO | B39: VESTUARIO | D39: -7854.87 | E39: -8.7 | F39: 0 | G39: -415.46 | H39: -156.38 | I39: 0 | J39: 0 | K39: 0 | L39: 0 | M39: 0 | N39: 0 | O39: 0 | Q39: -8435.41 | R39: -8500 | S39: 64.59 | T39: -0.75988235 | V39: -20400 | X39: -5359.92
A40: * CAPACITACION | B40: CAPACITACION | D40: -185.37 | E40: -335.49 | F40: -47.72 | G40: -754.84 | H40: -859.98 | I40: 0 | J40: 0 | K40: 0 | L40: 0 | M40: 0 | N40: 0 | O40: 0 | Q40: -2183.4 | R40: -8000 | S40: 5816.6 | T40: -72.7075 | V40: -19200 | X40: -2213.04
A41: * TRASLADO DE TRIPULACION | B41: TRASLADO DE TRIPULACION | D41: -14053.24 | E41: -18198.72 | F41: -13049.19 | G41: -19878.66 | H41: -13985.06 | I41: 0 | J41: 0 | K41: 0 | L41: 0 | M41: 0 | N41: 0 | O41: 0 | Q41: -79164.87 | R41: -72000 | S41: -7164.87 | T41: 9.9512083 | V41: -172800 | X41: -49183.5
A42: * OTROS GTOS. DE PERSONAL | B42: OTROS GTOS. DE PERSONAL | D42: -24369.17 | E42: -24024.36 | F42: -23445.91 | G42: -23774.74 | H42: -23986.35 | I42: 0 | J42: 0 | K42: 0 | L42: 0 | M42: 0 | N42: 0 | O42: 0 | Q42: -119600.53 | R42: -131033.6 | S42: 11433.07 | T42: -8.7252964 | V42: -314480.64 | X42: -117930.19
A43: * VIVERES DE TRIPULACION | B43: VIVERES DE TRIPULACION | D43: 44.96 | E43: -14.29 | F43: -26673.88 | G43: -22998.48 | H43: -2.58 | I43: 0 | J43: 0 | K43: 0 | L43: 0 | M43: 0 | N43: 0 | O43: 0 | Q43: -49644.27 | R43: -99439.3 | S43: 49795.03 | T43: -50.075805 | V43: -238654.32 | X43: -67946.71
B45: GASTOS DE LA NAVE | D45: -117932.96 | E45: -220527.16 | F45: -172453.84 | G45: -251079.25 | H45: -229408.29 | I45: 0 | J45: 0 | K45: 0 | L45: 0 | M45: 0 | N45: 0 | O45: 0 | Q45: -991401.5 | R45: -769690 | S45: -221711.5 | T45: 28.805298 | V45: -1828384 | X45: -881805.23
A46: * LUBRICANTES | B46: LUBRICANTES | D46: -27161.45 | E46: -53104.49 | F46: -5587.31 | G46: -4539.43 | H46: -36685.46 | I46: 0 | J46: 0 | K46: 0 | L46: 0 | M46: 0 | N46: 0 | O46: 0 | Q46: -127078.14 | R46: -81880 | S46: -45198.14 | T46: 55.200464 | V46: -235840 | X46: -64100.86
A47: * REPUESTOS Y MANTENIMIEN | B47: REPUESTOS Y MANTENIMIENTO | D47: -18503.14 | E47: -95346.84 | F47: -106898.64 | G47: -118927.73 | H47: -92465 | I47: 0 | J47: 0 | K47: 0 | L47: 0 | M47: 0 | N47: 0 | O47: 0 | Q47: -432141.35 | R47: -349350 | S47: -82791.35 | T47: 23.698683 | V47: -783600 | X47: -423284.52
A48: * MATERIAL CONSUMIBLE | B48: MATERIAL CONSUMIBLE | D48: -39873.04 | E48: -13267.93 | F48: -23365.59 | G48: -60533.11 | H48: -46452.08 | I48: 0 | J48: 0 | K48: 0 | L48: 0 | M48: 0 | N48: 0 | O48: 0 | Q48: -183491.75 | R48: -129000 | S48: -54491.75 | T48: 42.241667 | V48: -309600 | X48: -159038.21
A49: * CERTIF. /INSPECCION | B49: CERTIF. /INSPECCION | D49: -4647.35 | E49: -20553.46 | F49: -3113.7 | G49: -29879.21 | H49: -16929.9 | I49: 0 | J49: 0 | K49: 0 | L49: 0 | M49: 0 | N49: 0 | O49: 0 | Q49: -75123.62 | R49: -40900 | S49: -34223.62 | T49: 83.676333 | V49: -94800 | X49: -56112.89
B50: OTROS COSTOS | D50: -2435.98 | E50: -12942.44 | F50: -8176.6 | G50: -11887.77 | H50: -11563.85 | I50: 0 | J50: 0 | K50: 0 | L50: 0 | M50: 0 | N50: 0 | O50: 0 | Q50: -47006.64 | R50: -42000 | S50: -5006.64 | T50: 11.920571 | V50: -100800 | X50: -52708.75
A51: * SQE | B51: SQE | D51: 0 | E51: 0 | F51: 0 | G51: 0 | H51: 0 | I51: 0 | J51: 0 | K51: 0 | L51: 0 | M51: 0 | N51: 0 | O51: 0 | Q51: 0 | R51: 0 | S51: 0 | T51: 0 | V51: 0 | X51: 0
B52: VIGILANCIA Y SEGURIDAD PRIVADA | D52: 0 | E52: 0 | F52: 0 | G52: 0 | H52: 0 | I52: 0 | J52: 0 | K52: 0 | L52: 0 | M52: 0 | N52: 0 | O52: 0 | Q52: 0 | R52: 0 | S52: 0 | T52: 0 | V52: 0 | X52: 0
B53: AGENCIMIENTO | D53: 0 | E53: 0 | F53: 0 | G53: 0 | H53: 0 | I53: 0 | J53: 0 | K53: 0 | L53: 0 | M53: 0 | N53: 0 | O53: 0 | Q53: 0 | R53: 0 | S53: 0 | T53: 0 | V53: 0 | X53: 0
A54: * COMUNICACIONES | B54: COMUNICACIONES | D54: -2735.98 | E54: -5542.44 | F54: -5776.6 | G54: -5017.4 | H54: -9609.85 | I54: 0 | J54: 0 | K54: 0 | L54: 0 | M54: 0 | N54: 0 | O54: 0 | Q54: -28682.27 | R54: -32000 | S54: 3317.73 | T54: -10.367906 | V54: -76800 | X54: -41771.79
A55: * OTROS GTOS. DE LA NAVE | B55: OTROS GTOS. DE LA NAVE | D55: 300 | E55: -7400 | F55: -2400 | G55: -6870.37 | H55: -1954 | I55: 0 | J55: 0 | K55: 0 | L55: 0 | M55: 0 | N55: 0 | O55: 0 | Q55: -18324.37 | R55: -10000 | S55: -8324.37 | T55: 83.2437 | V55: -24000 | X55: -10936.96
A56: * GASTO ADM.DIRECTO FLOTA | B56: GASTO ADM.DIRECTO FLOTA | D56: -25312 | E56: -25312 | F56: -25312 | G56: -25312 | H56: -25312 | I56: 0 | J56: 0 | K56: 0 | L56: 0 | M56: 0 | N56: 0 | O56: 0 | Q56: -126560 | R56: -126560 | S56: 0 | T56: 0 | V56: -303744 | X56: -126560
A58: * DEPRECIACION CARENA DIQUE | B58: DEPRECIACION CARENA DIQUE | D58: -101341.53 | E58: -101341.54 | F58: -101341.54 | G58: -101341.53 | H58: -101341.53 | I58: 0 | J58: 0 | K58: 0 | L58: 0 | M58: 0 | N58: 0 | O58: 0 | Q58: -506707.67 | R58: -506707.65 | S58: -0.02 | T58: 3.9470492e-06 | V58: -1216098.4 | X58: -58764.41
B60: SEGUROS | D60: -24263.21 | E60: -21915.23 | F60: -24108.91 | G60: -23361.83 | H60: -24140.71 | I60: 0 | J60: 0 | K60: 0 | L60: 0 | M60: 0 | N60: 0 | O60: 0 | Q60: -117789.89 | R60: -115868.81 | S60: -1921.08 | T60: 1.6579785 | V60: -281879.17 | X60: -46898.15
A61: * CASCO Y MAQUINA | B61: CASCO Y MAQUINA | D61: -15886.12 | E61: -14348.77 | F61: -15886.12 | G61: -15373.65 | H61: -15886.11 | I61: 0 | J61: 0 | K61: 0 | L61: 0 | M61: 0 | N61: 0 | O61: 0 | Q61: -77380.77 | R61: -75283.83 | S61: -2096.94 | T61: 2.785379 | V61: -183975.03 | X61: -23271.89
A62: * PANDI | B62: PANDI | D62: -6708.78 | E62: -6059.58 | F62: -6554.48 | G62: -6373.67 | H62: -6586.13 | I62: 0 | J62: 0 | K62: 0 | L62: 0 | M62: 0 | N62: 0 | O62: 0 | Q62: -32282.64 | R62: -32458.6 | S62: 175.96 | T62: -0.54210594 | V62: -78179.56 | X62: -25056.61
A63: * DEDUCIBLES Y OTROS | B63: DEDUCIBLES Y OTROS | D63: -1668.31 | E63: -1506.88 | F63: -1668.31 | G63: -1614.51 | H63: -1668.47 | I63: 0 | J63: 0 | K63: 0 | L63: 0 | M63: 0 | N63: 0 | O63: 0 | Q63: -8126.48 | R63: -8126.38 | S63: -0.1 | T63: 0.0012305602 | V63: -19724.58 | X63: 1430.35
B65: OPERATING COST | D65: -550666.5 | E65: -745763.56 | F65: -635591.67 | G65: -700447.99 | H65: -698270.44 | I65: 0 | J65: 0 | K65: 0 | L65: 0 | M65: 0 | N65: 0 | O65: 0 | Q65: -3330740.2 | R65: -3248550.2 | S65: -82189.94 | T65: 2.5300499 | V65: -7670404.5 | X65: -2535752
B67: BARE BOAT EQUIVALENT | D67: 677928.8 | E67: 649743.73 | F67: 1442338.6 | G67: 773611.59 | H67: 1322281.1 | I67: 0 | J67: 0 | K67: 0 | L67: 0 | M67: 0 | N67: 0 | O67: 0 | Q67: 4865903.8 | R67: 3515922.4 | S67: 1349981.4 | T67: 38.396225 | V67: 7872651.4 | X67: 3455587.9
A69: * DEPRECIACION NAVES | B69: DEPRECIACION NAVES | D69: -153898.72 | E69: -153802.41 | F69: -153837.96 | G69: -154150.1 | H69: -154031.5 | I69: 0 | J69: 0 | K69: 0 | L69: 0 | M69: 0 | N69: 0 | O69: 0 | Q69: -769720.69 | R69: -763199.3 | S69: -6521.39 | T69: 0.85448061 | V69: -1831678.3 | X69: -758012.65
B70: COSTO IGV | D70: 0 | E70: 0 | F70: 0 | G70: 0 | H70: 0 | I70: 0 | J70: 0 | K70: 0 | L70: 0 | M70: 0 | N70: 0 | O70: 0 | Q70: 0 | R70: 0 | S70: 0 | T70: 0 | V70: 0 | X70: 0
T71: 0
B72: RESULTADO DE NAVE | D72: 0 | E72: 0 | F72: 0 | G72: 0 | H72: 0 | I72: 0 | J72: 0 | K72: 0 | L72: 0 | M72: 0 | N72: 0 | O72: 0 | Q72: 0 | R72: 0 | S72: 0 | T72: 0 | V72: 0 | X72: 0
T73: 0
A74: ** GTOS. ADMINIST. NAVE | B74: GTOS. ADMINISTRAT. NAVE | D74: -1923.31 | E74: -1142.94 | F74: -1269.02 | G74: -1102.82 | H74: -1093.5 | I74: 0 | J74: 0 | K74: 0 | L74: 0 | M74: 0 | N74: 0 | O74: 0 | Q74: -6531.59 | R74: -5530.35 | S74: -1017.06 | T74: 18.390518 | V74: -13272.84 | X74: -6052.14
B75: GTOS. REPRESENTACION | D75: 0 | E75: 0 | F75: 0 | G75: 0 | H75: 0 | I75: 0 | J75: 0 | K75: 0 | L75: 0 | M75: 0 | N75: 0 | O75: 0 | Q75: 0 | R75: 0 | S75: 0 | T75: 0 | V75: 0 | X75: 0
B76: GTOS. VIAJE | D76: 0 | E76: 0 | F76: 0 | G76: 0 | H76: 0 | I76: 0 | J76: 0 | K76: 0 | L76: 0 | M76: 0 | N76: 0 | O76: 0 | Q76: 0 | R76: 0 | S76: 0 | T76: 0 | V76: 0 | X76: 0
A77: * GTOS. INFORMATICA | B77: GTOS. INFORMATICA | D77: -1826.31 | E77: -1142.94 | F77: -1269.02 | G77: 0 | H77: 0 | I77: 0 | J77: 0 | K77: 0 | L77: 0 | M77: 0 | N77: 0 | O77: 0 | Q77: -4238.27 | R77: -3318.21 | S77: -920.06 | T77: 27.7276 | V77: -13272.84 | X77: -1861.88
A78: * GTOS. HONORARIOS | B78: GTOS. Honorarios | D78: 0 | E78: 0 | F78: 0 | G78: 0 | H78: 0 | I78: 0 | J78: 0 | K78: 0 | L78: 0 | M78: 0 | N78: 0 | O78: 0 | Q78: 0 | R78: 0 | S78: 0 | T78: 0 | V78: 0 | X78: 0
B79: SUSCRIPCIONES/PUBLICIDAD | D79: 0 | E79: 0 | F79: 0 | G79: 0 | H79: 0 | I79: 0 | J79: 0 | K79: 0 | L79: 0 | M79: 0 | N79: 0 | O79: 0 | Q79: 0 | R79: 0 | S79: 0 | T79: 0 | V79: 0 | X79: 0
A80: * UTILES DE ESCRITORIO | B80: UTILES DE ESCRITORIO | D80: -97 | E80: 0 | F80: 0 | G80: 0 | H80: 0 | I80: 0 | J80: 0 | K80: 0 | L80: 0 | M80: 0 | N80: 0 | O80: 0 | Q80: -97 | R80: 0 | S80: -97 | T80: 0 | V80: 0 | X80: -12.93
T81: 0
T82: 0
T83: 0
T84: 0
T85: 0
A87: 639413 SERV ADM. RELACION | B87: M1 - MARGEN DIRECTO | D87: 522106.77 | E87: 494798.38 | F87: 1287231.6 | G87: 618358.67 | H87: 749243.76 | I87: 0 | J87: 0 | K87: 0 | L87: 0 | M87: 0 | N87: 0 | O87: 0 | Q87: 3671739.2 | R87: 2747192.7 | S87: 924530.71 | T87: 33.653653 | V87: 6027700.2 | X87: 2691523.1
A88: ** GASTOS DE PERSONAL
A89: ** GASTOS GENERALES | B89: GTOS. ADMINIST. GENERALES | D89: -114226.45 | E89: -133812.52 | F89: -117013.5 | G89: -97741.73 | H89: -84057.05 | I89: 0 | J89: 0 | K89: 0 | L89: 0 | M89: 0 | N89: 0 | O89: 0 | Q89: -546851.25 | R89: -471036.41 | S89: -75814.84 | T89: 16.095325 | V89: -1085068 | X89: -372848.38
A90: * GTOS . ADMINIST. DEPRECIACI | B90: GTOS . ADMINIST. DEPRECIACION | D90: -442.07 | E90: -442.08 | F90: -442.06 | G90: -402.94 | H90: -402.95 | I90: 0 | J90: 0 | K90: 0 | L90: 0 | M90: 0 | N90: 0 | O90: 0 | Q90: -2132.1 | R90: -2049.3 | S90: -82.8 | T90: 4.040404 | V90: -4918.32 | X90: -2425.49
B91: GTOS.ADM.DIRECTO FLOTA | D91: 0 | E91: 0 | F91: 0 | G91: 0 | H91: 0 | I91: 0 | J91: 0 | K91: 0 | L91: 0 | M91: 0 | N91: 0 | O91: 0 | Q91: 0 | R91: 0 | S91: 0 | T91: 0 | V91: 0 | X91: 0
B93: M3 - MARGEN OPERACIONAL | D93: 407438.25 | E93: 360543.78 | F93: 1169776.1 | G93: 520214 | H93: 664783.76 | I93: 0 | J93: 0 | K93: 0 | L93: 0 | M93: 0 | N93: 0 | O93: 0 | Q93: 3122755.9 | R93: 2274107 | S93: 848648.89 | T93: 37.317896 | V93: 4937713.8 | X93: 2316249.2
B95: OTROS INGR./EGRESOS | D95: -22390.03 | E95: 26879.22 | F95: -3281.47 | G95: -65041.96 | H95: -11906.87 | I95: 0 | J95: 0 | K95: 0 | L95: 0 | M95: 0 | N95: 0 | O95: 0 | Q95: -75741.11 | R95: -42158.79 | S95: -33582.32 | T95: 79.656745 | V95: -104287.1 | X95: -121097.23
A96: * INGRESOS FINANCIEROS | B96: INGRESOS FINANCIEROS | D96: 15490.9 | E96: 24326.8 | F96: 17151.87 | G96: 13391.97 | H96: 8336.37 | I96: 0 | J96: 0 | K96: 0 | L96: 0 | M96: 0 | N96: 0 | O96: 0 | Q96: 78697.91 | R96: 80892.46 | S96: -2194.55 | T96: -2.7129228 | V96: 168732.24 | X96: 53737.58
A97: * GASTOS FINANCIEROS | B97: GASTOS FINANCIEROS | D97: -17880.99 | E97: -16205.69 | F97: -17716.87 | G97: -14601.1 | H97: -17036.4 | I97: 0 | J97: 0 | K97: 0 | L97: 0 | M97: 0 | N97: 0 | O97: 0 | Q97: -83441.05 | R97: -98485.05 | S97: 15044 | T97: -15.275415 | V97: -211953.14 | X97: -139779.93
B98: ING. (GTOS.) AÑO ANTERIOR | D98: 0 | E98: 0 | F98: 0 | G98: 0 | H98: 0 | I98: 0 | J98: 0 | K98: 0 | L98: 0 | M98: 0 | N98: 0 | O98: 0 | Q98: 0 | R98: 0 | S98: 0 | T98: 0 | V98: 0 | X98: 0
A99: * ING. (GTOS.) GESTION | B99: ING. (GTOS.) GESTION | D99: -1.07 | E99: -3676.68 | F99: -1987.44 | G99: -47172.01 | H99: -2474.29 | I99: 0 | J99: 0 | K99: 0 | L99: 0 | M99: 0 | N99: 0 | O99: 0 | Q99: -55311.49 | R99: -34566.2 | S99: -20745.29 | T99: 60.016114 | V99: -85066.2 | X99: -57885.89
B100: NPETRAL/PERSEUS | D100: 0 | E100: 0 | F100: 0 | G100: 0 | H100: 0 | I100: 0 | J100: 0 | K100: 0 | L100: 0 | M100: 0 | N100: 0 | O100: 0 | Q100: 0 | R100: 0 | S100: 0 | T100: 0 | V100: 0 | X100: 0
B101: INT.MINORITARIO Y RES.RENADSA | D101: 0 | E101: 0 | F101: 0 | G101: 0 | H101: 0 | I101: 0 | J101: 0 | K101: 0 | L101: 0 | M101: 0 | N101: 0 | O101: 0 | Q101: 0 | R101: 0 | S101: 0 | T101: 0 | V101: 0 | X101: 0
A102: * RESULT. DE TRASLACION/DIF. | B102: RESULT. DE TRASLACION | D102: -19998.87 | E102: 22434.79 | F102: -729.03 | G102: -16660.82 | H102: -732.55 | I102: 0 | J102: 0 | K102: 0 | L102: 0 | M102: 0 | N102: 0 | O102: 0 | Q102: -15686.48 | R102: 10000 | S102: -25686.48 | T102: -256.8648 | V102: 24000 | X102: 22831.01
B104: M4 - RESULTADO ANTES IMPTO | D104: 385048.22 | E104: 387423 | F104: 1166494.6 | G104: 455172.04 | H104: 652876.89 | I104: 0 | J104: 0 | K104: 0 | L104: 0 | M104: 0 | N104: 0 | O104: 0 | Q104: 3047014.8 | R104: 2231948.2 | S104: 815066.57 | T104: 36.518167 | V104: 4833426.7 | X104: 2195152
B106: TIME CHARTER EQUIVALENT (TCE) | D106: 0 | E106: 0 | F106: 0 | G106: 0 | H106: 0 | I106: 0 | J106: 0 | K106: 0 | L106: 0 | M106: 0 | N106: 0 | O106: 0 | Q106: 0 | R106: 0 | S106: -14947.644 | T106: 0 | V106: 0 | X106: 0
B107: COSTO DIA NAVE (DRC) | D107: 0 | E107: 0 | F107: 0 | G107: 0 | H107: 0 | I107: 0 | J107: 0 | K107: 0 | L107: 0 | M107: 0 | N107: 0 | O107: 0 | Q107: 0 | R107: 0 | S107: 8540.7156 | T107: 0 | V107: 0 | X107: 0
B108: RESULTADO DIARIO | D108: 8138.6082 | E108: 8138.6082 | F108: 8138.6082 | G108: 8138.6082 | H108: 8138.6082 | I108: 8138.6082 | J108: 8138.6082 | K108: 8138.6082 | L108: 8138.6082 | M108: 8138.6082 | N108: 8138.6082 | O108: 8138.6082 | Q108: 6670.0466 | R108: 8138.6082 | S108: 2905.9568 | T108: 35.70582 | V108: 8138.6082 | X108: 6670.0466
B109: DIAS OFF-HIRE | D109: 0 | E109: 0 | F109: 0 | G109: 0 | H109: 0 | I109: 0 | J109: 0 | K109: 0 | L109: 0 | M109: 0 | N109: 0 | O109: 0 | Q109: 0 | R109: 0 | T109: 0 | V109: 0 | X109: 0
B110: DIAS OPERATIVOS | D110: 28 | E110: 28 | F110: 28 | G110: 28 | H110: 28 | I110: 28 | J110: 28 | K110: 28 | L110: 28 | M110: 28 | N110: 28 | O110: 28 | Q110: 0 | R110: 28 | T110: 0 | V110: 28 | X110: 0
B111: DIAS DE EXCEPCION | D111: 28 | E111: 28 | F111: 28 | G111: 28 | H111: 28 | I111: 28 | J111: 28 | K111: 28 | L111: 28 | M111: 28 | N111: 28 | O111: 28 | Q111: 0 | R111: 28 | T111: 0 | V111: 28 | X111: 0
B112: NRO DE FAENAS | Q112: 0 | T112: 0 | X112: 0
T113: 0
B114: EBITDA | D114: 663120.57 | E114: 616129.81 | F114: 1425397.6 | G114: 776108.57 | H114: 920559.74 | I114: 0 | J114: 0 | K114: 0 | L114: 0 | M114: 0 | N114: 0 | O114: 0 | Q114: 4401316.3 | R114: 3546063.2 | S114: 855237.28 | T114: 24.117936 | V114: 7990408.8 | X114: 3135451.8
D116: =+Moquegua!D104+'Flota Contratada'!D103+'Gastos Adm'!D56+Tablones!D104 -> 385048.22 | E116: =+Moquegua!E104+'Flota Contratada'!E103+'Gastos Adm'!E56+Tablones!E104 -> 387423 | F116: =+Moquegua!F104+'Flota Contratada'!F103+'Gastos Adm'!F56+Tablones!F104 -> 1166494.6 | G116: =+Moquegua!G104+'Flota Contratada'!G103+'Gastos Adm'!G56+Tablones!G104 -> 455172.04 | H116: =+Moquegua!H104+'Flota Contratada'!H103+'Gastos Adm'!H56+Tablones!H104 -> 652876.89 | I116: =+Moquegua!I104+'Flota Contratada'!I103+'Gastos Adm'!I56+Tablones!I104 -> 0 | J116: =+Moquegua!J104+'Flota Contratada'!J103+'Gastos Adm'!J56+Tablones!J104 -> 0 | K116: =+Moquegua!K104+'Flota Contratada'!K103+'Gastos Adm'!K56+Tablones!K104 -> 0 | ... T116: =+Moquegua!T104+'Flota Contratada'!T103+'Gastos Adm'!T56+Tablones!T104 -> 102.94446 | V116: 4833426.8 | X116: =+Moquegua!X104+'Flota Contratada'!X103+'Gastos Adm'!X56+Tablones!X104 -> 2195152
D118: =+D104-D116 -> 0 | E118: =+E104-E116 -> 0 | F118: =+F104-F116 -> 0 | G118: =+G104-G116 -> 0 | H118: =+H104-H116 -> 0 | I118: =+I104-I116 -> 0 | J118: =+J104-J116 -> 0 | K118: =+K104-K116 -> 0 | ... S118: =+S104-S116 -> -1.2805685e-09 | V118: 0 | X118: =+X104-X116 -> 0

Sheet PETRAL GRR3
B2: US$ Dolar | C2: Enero | D2: Febrero | E2: Marzo | F2: Abril | G2: Mayo | H2: Junio | I2: Julio | J2: Agosto | K2: Setiembre | L2: Octubre | M2: Noviembre | N2: Diciembre | O2: Acum. 2026 | P2: Ppto.Acum a 3 | Q2: Variacion | R2: Ppto Anual | S2: % | T2: Ppto Mens | U2: Real A o anterior
B3: ** VENTAS | C3: -1722066.9 | D3: -2111191.9 | E3: -2658974.7 | F3: 0 | G3: 0 | H3: 0 | I3: 0 | J3: 0 | K3: 0 | L3: 0 | M3: 0 | N3: 0 | O3: -6492233.4 | P3: -5898825 | Q3: 593408.44 | R3: -22433750 | S3: -10.0598 | T3: -1997375 | U3: 0
B4: 704121 FLETES A TERC-NAV P | C4: 0 | D4: 0 | E4: 0 | F4: 0 | G4: 0 | H4: 0 | I4: 0 | J4: 0 | K4: 0 | L4: 0 | M4: 0 | N4: 0 | O4: 0 | P4: -4677825 | Q4: -4677825 | R4: -18193750 | S4: 100 | T4: -1594375 | U4: 0
B5: 703213 FLETES A T-NAV PR L | C5: -1041229.4 | D5: -1827318.9 | E5: -1992698.2 | F5: 0 | G5: 0 | H5: 0 | I5: 0 | J5: 0 | K5: 0 | L5: 0 | M5: 0 | N5: 0 | O5: -4861246.6 | P5: 0 | Q5: 4861246.6 | R5: 0 | S5: 0 | T5: 0 | U5: 0
B6: * HIRE | C6: -1041229.4 | D6: -1827318.9 | E6: -1992698.2 | F6: 0 | G6: 0 | H6: 0 | I6: 0 | J6: 0 | K6: 0 | L6: 0 | M6: 0 | N6: 0 | O6: -4861246.6 | P6: -4677825 | Q6: 183421.56 | R6: -18193750 | S6: -3.9211 | T6: -1594375 | U6: 0
B7: 704123 DEMORAS | C7: 0 | D7: 0 | E7: 0 | F7: 0 | G7: 0 | H7: 0 | I7: 0 | J7: 0 | K7: 0 | L7: 0 | M7: 0 | N7: 0 | O7: 0 | P7: -980000 | Q7: -980000 | R7: -3460000 | S7: 100 | T7: -340000 | U7: 0
B8: 703115 DEMORAS EXPORTACION | C8: 87307.99 | D8: 311956.22 | E8: -405189.18 | F8: 0 | G8: 0 | H8: 0 | I8: 0 | J8: 0 | K8: 0 | L8: 0 | M8: 0 | N8: 0 | O8: -5924.97 | P8: 0 | Q8: 5924.97 | R8: 0 | S8: 0 | T8: 0 | U8: 0
B9: 703215 DEMORAS -LOCAL | C9: -691997.24 | D9: -527306.22 | E9: -157347.83 | F9: 0 | G9: 0 | H9: 0 | I9: 0 | J9: 0 | K9: 0 | L9: 0 | M9: 0 | N9: 0 | O9: -1376651.3 | P9: 0 | Q9: 1376651.3 | R9: 0 | S9: 0 | T9: 0 | U9: 0
B10: * DEMORAS | C10: -604689.25 | D10: -215350 | E10: -562537.01 | F10: 0 | G10: 0 | H10: 0 | I10: 0 | J10: 0 | K10: 0 | L10: 0 | M10: 0 | N10: 0 | O10: -1382576.3 | P10: -980000 | Q10: 402576.26 | R10: -3460000 | S10: -41.0792 | T10: -340000 | U10: 0
B11: 704136 SERV DE ATENC EN PU | C11: 0 | D11: 0 | E11: 0 | F11: 0 | G11: 0 | H11: 0 | I11: 0 | J11: 0 | K11: 0 | L11: 0 | M11: 0 | N11: 0 | O11: 0 | P11: -241000 | Q11: -241000 | R11: -780000 | S11: 100 | T11: -63000 | U11: 0
B12: 703118 SERV ATENC EN PUE E | C12: -295.62 | D12: 14295.62 | E12: 6000 | F12: 0 | G12: 0 | H12: 0 | I12: 0 | J12: 0 | K12: 0 | L12: 0 | M12: 0 | N12: 0 | O12: 20000 | P12: 0 | Q12: -20000 | R12: 0 | S12: 0 | T12: 0 | U12: 0
B13: 703218 SERV ATENC EN PUE L | C13: -75852.59 | D13: -82818.52 | E13: -109739.51 | F13: 0 | G13: 0 | H13: 0 | I13: 0 | J13: 0 | K13: 0 | L13: 0 | M13: 0 | N13: 0 | O13: -268410.62 | P13: 0 | Q13: 268410.62 | R13: 0 | S13: 0 | T13: 0 | U13: 0
B14: * INGRESOS DE PUERTO | C14: -76148.21 | D14: -68522.9 | E14: -103739.51 | F14: 0 | G14: 0 | H14: 0 | I14: 0 | J14: 0 | K14: 0 | L14: 0 | M14: 0 | N14: 0 | O14: -248410.62 | P14: -241000 | Q14: 7410.62 | R14: -780000 | S14: -3.0749 | T14: -63000 | U14: 0
... B222: ******* EBITDA | C222: -663120.57 | D222: -616129.81 | E222: -1425397.6 | F222: 0 | G222: 0 | H222: 0 | I222: 0 | J222: 0 | K222: 0 | L222: 0 | M222: 0 | N222: 0 | O222: -2704648 | P222: -2166328.5 | Q222: 538319.53 | R222: -7990408.8 | S222: -24.8494 | T222: -769572.46 | U222: 0

Sheet Hoja1
B2: US$ Dolar | C2: Enero | D2: Febrero | E2: Marzo | F2: Abril | G2: Mayo | H2: Junio | I2: Julio | J2: Agosto | K2: Setiembre | L2: Octubre | M2: Noviembre | N2: Diciembre | O2: Acum. 2025 | P2: Ppto.Acum a 11 | Q2: Variacion | R2: Ppto Anual | S2: % | T2: Ppto Mens | U2: Real A o anterior
B3: *** VENTAS | C3: 0 | D3: 0 | E3: 0 | F3: 0 | G3: 0 | H3: 0 | I3: 0 | J3: 0 | K3: 0 | L3: -17278289 | M3: -1529551.4 | N3: 0 | O3: -18807841 | P3: -18366587 | Q3: 441253.29 | R3: -19976053 | S3: -2.4025 | T3: -1849240.7 | U3: 0
B4: 704121 FLETES A TERC-NAV | C4: 0 | D4: 0 | E4: 0 | F4: 0 | G4: 0 | H4: 0 | I4: 0 | J4: 0 | K4: 0 | L4: 0 | M4: 0 | N4: 0 | O4: 0 | P4: -14954265 | Q4: -14954265 | R4: -16266065 | S4: 100 | T4: -1521575 | U4: 0
B5: 703213 FLETES A T-NAV PR | C5: 0 | D5: 0 | E5: 0 | F5: 0 | G5: 0 | H5: 0 | I5: 0 | J5: 0 | K5: 0 | L5: -12453731 | M5: -1110701.1 | N5: 0 | O5: -13564433 | P5: 0 | Q5: 13564433 | R5: 0 | S5: 0 | T5: 0 | U5: 0
B6: * HIRE | C6: 0 | D6: 0 | E6: 0 | F6: 0 | G6: 0 | H6: 0 | I6: 0 | J6: 0 | K6: 0 | L6: -12453731 | M6: -1110701.1 | N6: 0 | O6: -13564433 | P6: -14954265 | Q6: -1389832.4 | R6: -16266065 | S6: 9.2939 | T6: -1521575 | U6: 0
B7: 704123 DEMORAS | C7: 0 | D7: 0 | E7: 0 | F7: 0 | G7: 0 | H7: 0 | I7: 0 | J7: 0 | K7: 0 | L7: 0 | M7: 0 | N7: 0 | O7: 0 | P7: -2768322.3 | Q7: -2768322.3 | R7: -3019987.9 | S7: 100 | T7: -251665.66 | U7: 0
B8: 703115 DEMORAS EXPORTACIO | C8: 0 | D8: 0 | E8: 0 | F8: 0 | G8: 0 | H8: 0 | I8: 0 | J8: 0 | K8: 0 | L8: -165339.11 | M8: 199540.87 | N8: 0 | O8: 34201.76 | P8: 0 | Q8: -34201.76 | R8: 0 | S8: 0 | T8: 0 | U8: 0
B9: 703215 DEMORAS -LOCAL | C9: 0 | D9: 0 | E9: 0 | F9: 0 | G9: 0 | H9: 0 | I9: 0 | J9: 0 | K9: 0 | L9: -4150714 | M9: -558872.76 | N9: 0 | O9: -4709586.8 | P9: 0 | Q9: 4709586.8 | R9: 0 | S9: 0 | T9: 0 | U9: 0
B10: * DEMORAS | C10: 0 | D10: 0 | E10: 0 | F10: 0 | G10: 0 | H10: 0 | I10: 0 | J10: 0 | K10: 0 | L10: -4316053.1 | M10: -359331.89 | N10: 0 | O10: -4675385 | P10: -2768322.3 | Q10: 1907062.7 | R10: -3019987.9 | S10: -68.8888 | T10: -251665.66 | U10: 0
B11: 704136 SERV DE ATENC EN P | C11: 0 | D11: 0 | E11: 0 | F11: 0 | G11: 0 | H11: 0 | I11: 0 | J11: 0 | K11: 0 | L11: 0 | M11: 0 | N11: 0 | O11: 0 | P11: -644000 | Q11: -644000 | R11: -690000 | S11: 100 | T11: -76000 | U11: 0
B12: 703118 SERV ATENC EN PUE | C12: 0 | D12: 0 | E12: 0 | F12: 0 | G12: 0 | H12: 0 | I12: 0 | J12: 0 | K12: 0 | L12: 19018 | M12: 29096 | N12: 0 | O12: 48114 | P12: 0 | Q12: -48114 | R12: 0 | S12: 0 | T12: 0 | U12: 0
B13: 703218 SERV ATENC EN PUE | C13: 0 | D13: 0 | E13: 0 | F13: 0 | G13: 0 | H13: 0 | I13: 0 | J13: 0 | K13: 0 | L13: -527522.55 | M13: -88614.44 | N13: 0 | O13: -616136.99 | P13: 0 | Q13: 616136.99 | R13: 0 | S13: 0 | T13: 0 | U13: 0
B14: * INGRESOS DE PUERTO | C14: 0 | D14: 0 | E14: 0 | F14: 0 | G14: 0 | H14: 0 | I14: 0 | J14: 0 | K14: 0 | L14: -508504.55 | M14: -59518.44 | N14: 0 | O14: -568022.99 | P14: -644000 | Q14: -75977.01 | R14: -690000 | S14: 11.7977 | T14: -76000 | U14: 0
... B240: ******** EBITDA | C240: 0 | D240: 0 | E240: 0 | F240: 0 | G240: 0 | H240: 0 | I240: 0 | J240: 0 | K240: 0 | L240: -6681820 | M240: -500897.96 | N240: 0 | O240: -7182718 | P240: -6704365 | Q240: 478352.9 | R240: -7251419.3 | S240: -7.1349 | T240: -788830.47 | U240: 0

Sheet Moquegua
Z1: =+PETRAL!Z1 -> 5
B2: Control Presupuestal
B3: =+PETRAL!B3 -> 46143 | D3: MOQUEGUA
Q5: REAL | R5: PRESUP. | V5: PPTO. | X5: Real Acum.
B6: (US$ Dólares) | D6: ENE | E6: FEB | F6: MAR | G6: ABR | H6: MAY | I6: JUN | J6: JUL | K6: AGO | L6: SET | M6: OCT | N6: NOV | O6: DIC | Q6: ACUMUL. | R6: ACUMUL. | S6: VARIACION | T6: % | V6: ANUAL | X6: =+PETRAL!X6 -> 45778
B8: VENTAS | D8: 551026.33 | E8: 1155413 | F8: 1436461.6 | G8: 865657.45 | H8: 1314549.9 | I8: 0 | J8: 0 | K8: 0 | L8: 0 | M8: 0 | N8: 0 | O8: 0 | Q8: 5323108.3 | R8: 4461285 | S8: 861823.31 | T8: 19.317827 | V8: 11408070 | X8: 3443429.9
A9: * HIRE | B9: HIRE | D9: 197159.69 | E9: 1018421.9 | F9: 1132813.4 | G9: 547915.66 | H9: 1220211.7 | I9: 0 | J9: 0 | K9: 0 | L9: 0 | M9: 0 | N9: 0 | O9: 0 | Q9: 4116522.4 | R9: 3684285 | S9: 432237.39 | T9: 11.731921 | V9: 9558070 | X9: 2472155.7
B10: VENTA DE TERCEROS | D10: 0 | E10: 0 | F10: 0 | G10: 0 | H10: 0 | I10: 0 | J10: 0 | K10: 0 | L10: 0 | M10: 0 | N10: 0 | O10: 0 | Q10: 0 | R10: 0 | S10: 0 | T10: 0 | V10: 0 | X10: 0
A11: * DEMORAS | B11: DEMORAS | D11: 331565.33 | E11: 130225.35 | F11: 226211.46 | G11: 296523.81 | H11: 61681.01 | I11: 0 | J11: 0 | K11: 0 | L11: 0 | M11: 0 | N11: 0 | O11: 0 | Q11: 1046207 | R11: 710000 | S11: 336206.96 | T11: 47.353093 | V11: 1710000 | X11: 873246.01
A12: * INGRESOS DE PUERTO | B12: INGRESOS DE PUERTO | D12: 22301.31 | E12: 6765.71 | F12: 77436.73 | G12: 21217.98 | H12: 32657.23 | I12: 0 | J12: 0 | K12: 0 | L12: 0 | M12: 0 | N12: 0 | O12: 0 | Q12: 160378.96 | R12: 67000 | S12: 93378.96 | T12: 139.37158 | V12: 140000 | X12: 98028.16
A13: * OTROS INGRESOS | B13: OTROS INGRESOS | D13: 0 | E13: 0 | F13: 0 | G13: 0 | H13: 0 | I13: 0 | J13: 0 | K13: 0 | L13: 0 | M13: 0 | N13: 0 | O13: 0 | Q13: 0 | R13: 0 | S13: 0 | T13: 0 | V13: 0 | X13: 0
B15: COSTOS DIRECTOS | D15: -113464.26 | E15: -270359.16 | F15: -447348.26 | G15: -144973.84 | H15: -318588.34 | I15: 0 | J15: 0 | K15: 0 | L15: 0 | M15: 0 | N15: 0 | O15: 0 | Q15: -1294733.9 | R15: -1142642.6 | S15: -152091.28 | T15: 13.310486 | V15: -2977950.8 | X15: -886349.17
A16: * COMBUSTIBLE | B16: COMBUSTIBLE | D16: -58113.65 | E16: -104266.83 | F16: -109571.24 | G16: -82631.52 | H16: -99174.25 | I16: 0 | J16: 0 | K16: 0 | L16: 0 | M16: 0 | N16: 0 | O16: 0 | Q16: -453757.49 | R16: -410642.58 | S16: -43114.91 | T16: 10.499376 | V16: -1123950.8 | X16: -377896.13
A17: * GASTOS DE PUERTO | B17: GASTOS DE PUERTO | D17: -55350.61 | E17: -166092.33 | F17: -337777.02 | G17: -62342.32 | H17: -219414.09 | I17: 0 | J17: 0 | K17: 0 | L17: 0 | M17: 0 | N17: 0 | O17: 0 | Q17: -840976.37 | R17: -732000 | S17: -108976.37 | T17: 14.887482 | V17: -1854000 | X17: -508453.04
B18: COSTOS DE DEMORA | D18: 0 | E18: 0 | F18: 0 | G18: 0 | H18: 0 | I18: 0 | J18: 0 | K18: 0 | L18: 0 | M18: 0 | N18: 0 | O18: 0 | Q18: 0 | R18: 0 | S18: 0 | T18: 0 | V18: 0 | X18: 0
B19: COMISION BROCKERAGE | D19: 0 | E19: 0 | F19: 0 | G19: 0 | H19: 0 | I19: 0 | J19: 0 | K19: 0 | L19: 0 | M19: 0 | N19: 0 | O19: 0 | Q19: 0 | R19: 0 | S19: 0 | T19: 0 | V19: 0 | X19: 0
A20: * COMISIONES VARIAS | B20: COMISIONES VARIAS | D20: 0 | E20: 0 | F20: 0 | G20: 0 | H20: 0 | I20: 0 | J20: 0 | K20: 0 | L20: 0 | M20: 0 | N20: 0 | O20: 0 | Q20: 0 | R20: 0 | S20: 0 | T20: 0 | V20: 0 | X20: 0
A21: * OTROS COSTOS DIRECTOS | B21: OTROS COSTOS DIRECTOS | D21: 0 | E21: 0 | F21: 0 | G21: 0 | H21: 0 | I21: 0 | J21: 0 | K21: 0 | L21: 0 | M21: 0 | N21: 0 | O21: 0 | Q21: 0 | R21: 0 | S21: 0 | T21: 0 | V21: 0 | X21: 0
B22: GASTO PUERTO POR RECIBIR | D22: 0 | E22: 0 | F22: 0 | G22: 0 | H22: 0 | I22: 0 | J22: 0 | K22: 0 | L22: 0 | M22: 0 | N22: 0 | O22: 0 | Q22: 0 | R22: 0 | S22: 0 | T22: 0 | V22: 0 | X22: 0
B24: TIME CHARTER EQUIVALENT | D24: 437562.07 | E24: 885053.82 | F24: 989113.38 | G24: 720683.61 | H24: 995961.57 | I24: 0 | J24: 0 | K24: 0 | L24: 0 | M24: 0 | N24: 0 | O24: 0 | Q24: 4028374.4 | R24: 3318642.4 | S24: 709732.03 | T24: 21.386216 | V24: 8430119.2 | X24: 2557080.7
B26: COSTO DE ARRIENDO NAVES | D26: 0 | E26: 0 | F26: 0 | G26: 0 | H26: 0 | I26: 0 | J26: 0 | K26: 0 | L26: 0 | M26: 0 | N26: 0 | O26: 0 | Q26: 0 | R26: 0 | S26: 0 | T26: 0 | V26: 0 | X26: 0
B28: MARGEN BRUTO | D28: 437562.07 | E28: 885053.82 | F28: 989113.38 | G28: 720683.61 | H28: 995961.57 | I28: 0 | J28: 0 | K28: 0 | L28: 0 | M28: 0 | N28: 0 | O28: 0 | Q28: 4028374.4 | R28: 3318642.4 | S28: 709732.03 | T28: 21.386216 | V28: 8430119.2 | X28: 2557080.7
B30: GTOS. PERSONAL A BORDO | D30: -140045.31 | E30: -202734.27 | F30: -168711.03 | G30: -163794.23 | H30: -178734.37 | I30: 0 | J30: 0 | K30: 0 | L30: 0 | M30: 0 | N30: 0 | O30: 0 | Q30: -854019.21 | R30: -928141.88 | S30: 74122.67 | T30: -7.9861357 | V30: -2172021.5 | X30: -767899.81
B31: GASTOS DE PERSONAL | D31: -140045.31 | E31: -202734.27 | F31: -168711.03 | G31: -163794.23 | H31: -178734.37 | I31: 0 | J31: 0 | K31: 0 | L31: 0 | M31: 0 | N31: 0 | O31: 0 | Q31: -854019.21 | R31: -928141.88 | S31: 74122.67 | T31: -7.9861357 | V31: -2172021.5 | X31: -767899.81
A33: * SUELDOS | B33: SUELDOS | D33: -79110.27 | E33: -133896.9 | F33: -99027.32 | G33: -103985.94 | H33: -114436.43 | I33: 0 | J33: 0 | K33: 0 | L33: 0 | M33: 0 | N33: 0 | O33: 0 | Q33: -530456.86 | R33: -523020.72 | S33: -7436.14 | T33: 1.4217678 | V33: -1205715.7 | X33: -507276.36
A34: * VACACIONES | B34: VACACIONES | D34: -6825.94 | E34: -8346.57 | F34: -4085.82 | G34: -8127.8 | H34: -8509.89 | I34: 0 | J34: 0 | K34: 0 | L34: 0 | M34: 0 | N34: 0 | O34: 0 | Q34: -35896.02 | R34: -40071.25 | S34: 4175.23 | T34: -10.419515 | V34: -97697.77 | X34: -22304.81
A35: * GRATIFICACIONES | B35: GRATIFICACIONES | D35: -10356.88 | E35: -11849.02 | F35: -14640.11 | G35: -15733.28 | H35: -17093.28 | I35: 0 | J35: 0 | K35: 0 | L35: 0 | M35: 0 | N35: 0 | O35: 0 | Q35: -69672.57 | R35: -106070.91 | S35: 36398.34 | T35: -34.315101 | V35: -243953.31 | X35: -53578.04
A36: * BENEFICIOS SOCIALES | B36: BENEFICIOS SOCIALES | D36: -11520.37 | E36: -8410.7 | F36: -7077.03 | G36: -4051.38 | H36: -7148.94 | I36: 0 | J36: 0 | K36: 0 | L36: 0 | M36: 0 | N36: 0 | O36: 0 | Q36: -38208.42 | R36: -45833.1 | S36: 7624.68 | T36: -16.63575 | V36: -111745.8 | X36: -31952.9
A37: * ESSALUD | B37: ESSALUD | D37: -6369.62 | E37: -9129.82 | F37: -5583.53 | G37: -6030.76 | H37: -6852.64 | I37: 0 | J37: 0 | K37: 0 | L37: 0 | M37: 0 | N37: 0 | O37: 0 | Q37: -33966.37 | R37: -35659.45 | S37: 1693.08 | T37: -4.7479139 | V37: -86941.45 | X37: -26122.15
A38: * E.P.S. /GASTOS MEDICOS | B38: E.P.S. /GASTOS MEDICOS | D38: -4023.82 | E38: -5056.51 | F38: -3173.09 | G38: -516.69 | H38: -6128.46 | I38: 0 | J38: 0 | K38: 0 | L38: 0 | M38: 0 | N38: 0 | O38: 0 | Q38: -18898.57 | R38: -18000 | S38: -898.57 | T38: 4.9920556 | V38: -43200 | X38: -19870.67
A39: * VESTUARIO | B39: VESTUARIO | D39: -2419.44 | E39: 0 | F39: 0 | G39: -402.71 | H39: -156.38 | I39: 0 | J39: 0 | K39: 0 | L39: 0 | M39: 0 | N39: 0 | O39: 0 | Q39: -2978.53 | R39: -4250 | S39: 1271.47 | T39: -29.916941 | V39: -10200 | X39: -2746.29
A40: * CAPACITACION | B40: CAPACITACION | D40: -156.44 | E40: -295.35 | F40: -47.72 | G40: -555.83 | H40: -281.72 | I40: 0 | J40: 0 | K40: 0 | L40: 0 | M40: 0 | N40: 0 | O40: 0 | Q40: -1337.06 | R40: -4000 | S40: 2662.94 | T40: -66.5735 | V40: -9600 | X40: -739.16
A41: * TRASLADO DE TRIPULACION | B41: TRASLADO DE TRIPULACION | D41: -7072.59 | E41: -13714 | F41: -4612.19 | G41: -12497.59 | H41: -6070.33 | I41: 0 | J41: 0 | K41: 0 | L41: 0 | M41: 0 | N41: 0 | O41: 0 | Q41: -43966.7 | R41: -36000 | S41: -7966.7 | T41: 22.129722 | V41: -86400 | X41: -14256.23
A42: * OTROS GTOS. DE PERSONAL | B42: OTROS GTOS. DE PERSONAL | D42: -12215.63 | E42: -12035.4 | F42: -11745.88 | G42: -11887.18 | H42: -12004.45 | I42: 0 | J42: 0 | K42: 0 | L42: 0 | M42: 0 | N42: 0 | O42: 0 | Q42: -59888.54 | R42: -65516.8 | S42: 5628.26 | T42: -8.59056 | V42: -157240.32 | X42: -59147.39
A43: * VIVERES DE TRIPULACION | B43: VIVERES DE TRIPULACION | D43: 25.69 | E43: 0 | F43: -18718.34 | G43: -5.07 | H43: -51.85 | I43: 0 | J43: 0 | K43: 0 | L43: 0 | M43: 0 | N43: 0 | O43: 0 | Q43: -18749.57 | R43: -49719.65 | S43: 30970.08 | T43: -62.289417 | V43: -119327.16 | X43: -29905.81
B45: GASTOS DE LA NAVE | D45: -44172.86 | E45: -88911.86 | F45: -75689.03 | G45: -158573.23 | H45: -132015.16 | I45: 0 | J45: 0 | K45: 0 | L45: 0 | M45: 0 | N45: 0 | O45: 0 | Q45: -499362.14 | R45: -369020 | S45: -130342.14 | T45: 35.321159 | V45: -916492 | W45: 0 | X45: -511345.58
A46: * LUBRICANTES | B46: LUBRICANTES | D46: -8861.45 | E46: -25087.68 | F46: -5586 | G46: -7.86 | H46: -12192.14 | I46: 0 | J46: 0 | K46: 0 | L46: 0 | M46: 0 | N46: 0 | O46: 0 | Q46: -51735.13 | R46: -40940 | S46: -10795.13 | T46: 26.368173 | V46: -116020 | X46: -19931.04
A47: * REPUESTOS Y MANTENIMIEN | B47: REPUESTOS Y MANTENIMIENTO | D47: -8167.26 | E47: -19649.35 | F47: -44576.58 | G47: -82427.27 | H47: -72038.39 | I47: 0 | J47: 0 | K47: 0 | L47: 0 | M47: 0 | N47: 0 | O47: 0 | Q47: -226858.85 | R47: -160350 | S47: -66508.85 | T47: 41.4773 | V47: -399600 | X47: -304164.95
A48: * MATERIAL CONSUMIBLE | B48: MATERIAL CONSUMIBLE | D48: -10263.24 | E48: -8892.01 | F48: -5841.37 | G48: -38130.09 | H48: -22994.97 | I48: 0 | J48: 0 | K48: 0 | L48: 0 | M48: 0 | N48: 0 | O48: 0 | Q48: -86121.68 | R48: -63000 | S48: -23121.68 | T48: 36.701079 | V48: -151200 | X48: -70471.33
A49: * CERTIF. /INSPECCION | B49: CERTIF. /INSPECCION | D49: -4031.75 | E49: -16839.8 | F49: -2077.21 | G49: -19266.19 | H49: -4878.42 | I49: 0 | J49: 0 | K49: 0 | L49: 0 | M49: 0 | N49: 0 | O49: 0 | Q49: -47093.37 | R49: -20450 | S49: -26643.37 | T49: 130.28543 | V49: -47400 | X49: -33893.45
B50: OTROS COSTOS | D50: -193.16 | E50: -5787.02 | F50: -4951.87 | G50: -6085.82 | H50: -7255.24 | I50: 0 | J50: 0 | K50: 0 | L50: 0 | M50: 0 | N50: 0 | O50: 0 | Q50: -24273.11 | R50: -21000 | S50: -3273.11 | T50: 15.586238 | V50: -50400 | X50: -19604.81
A51: * SQE | B51: SQE | D51: 0 | E51: 0 | F51: 0 | G51: 0 | H51: 0 | I51: 0 | J51: 0 | K51: 0 | L51: 0 | M51: 0 | N51: 0 | O51: 0 | Q51: 0 | R51: 0 | S51: 0 | T51: 0 | V51: 0 | X51: 0
B52: VIGILANCIA Y SEGURIDAD PRIVADA | D52: 0 | E52: 0 | F52: 0 | G52: 0 | H52: 0 | I52: 0 | J52: 0 | K52: 0 | L52: 0 | M52: 0 | N52: 0 | O52: 0 | Q52: 0 | R52: 0 | S52: 0 | T52: 0 | V52: 0 | X52: 0
B53: AGENCIMIENTO | D53: 0 | E53: 0 | F53: 0 | G53: 0 | H53: 0 | I53: 0 | J53: 0 | K53: 0 | L53: 0 | M53: 0 | N53: 0 | O53: 0 | Q53: 0 | R53: 0 | S53: 0 | T53: 0 | V53: 0 | X53: 0
A54: * COMUNICACIONES | B54: COMUNICACIONES | D54: -293.16 | E54: -1397.02 | F54: -3751.87 | G54: -3185.82 | H54: -6955.24 | I54: 0 | J54: 0 | K54: 0 | L54: 0 | M54: 0 | N54: 0 | O54: 0 | Q54: -15583.11 | R54: -16000 | S54: 416.89 | T54: -2.6055625 | V54: -38400 | X54: -13998.83
A55: * OTROS GTOS. DE LA NAVE | B55: OTROS GTOS. DE LA NAVE | D55: 100 | E55: -4390 | F55: -1200 | G55: -2900 | H55: -300 | I55: 0 | J55: 0 | K55: 0 | L55: 0 | M55: 0 | N55: 0 | O55: 0 | Q55: -8690 | R55: -5000 | S55: -3690 | T55: 73.8 | V55: -12000 | X55: -5605.98
A56: * GASTO ADM.DIRECTO FLOTA | B56: GASTO ADM.DIRECTO FLOTA | D56: -12656 | E56: -12656 | F56: -12656 | G56: -12656 | H56: -12656 | I56: 0 | J56: 0 | K56: 0 | L56: 0 | M56: 0 | N56: 0 | O56: 0 | Q56: -63280 | R56: -63280 | S56: 0 | T56: 0 | V56: -151872 | X56: -63280
A58: * DEPRECIACION CARENA DIQUE | B58: DEPRECIACION CARENA DIQUE | D58: -60873.37 | E58: -60873.37 | F58: -60873.38 | G58: -60873.37 | H58: -60873.37 | I58: 0 | J58: 0 | K58: 0 | L58: 0 | M58: 0 | N58: 0 | O58: 0 | Q58: -304366.86 | R58: -304366.85 | S58: -0.01 | T58: 3.2855089e-06 | V58: -730480.44 | X58: -58764.41
B60: SEGUROS | D60: -12563.92 | E60: -11348.06 | F60: -12471.38 | G60: -12087.43 | H60: -12490.41 | I60: 0 | J60: 0 | K60: 0 | L60: 0 | M60: 0 | N60: 0 | O60: 0 | Q60: -60961.2 | R60: -59973.53 | S60: -987.67 | T60: 1.6468432 | V60: -145895.27 | X60: -20431.75
A61: * CASCO Y MAQUINA | B61: CASCO Y MAQUINA | D61: -7900.31 | E61: -7135.77 | F61: -7900.31 | G61: -7645.44 | H61: -7900.3 | I61: 0 | J61: 0 | K61: 0 | L61: 0 | M61: 0 | N61: 0 | O61: 0 | Q61: -38482.13 | R61: -37433.64 | S61: -1048.49 | T61: 2.8009299 | V61: -91483.9 | X61: -11439.12
A62: * PANDI | B62: PANDI | D62: -3843.69 | E62: -3471.71 | F62: -3751.15 | G62: -3648.51 | H62: -3770.13 | I62: 0 | J62: 0 | K62: 0 | L62: 0 | M62: 0 | N62: 0 | O62: 0 | Q62: -18485.19 | R62: -18546.04 | S62: 60.85 | T62: -0.32810239 | V62: -44716.7 | X62: -13443.37
A63: * DEDUCIBLES Y OTROS | B63: DEDUCIBLES Y OTROS | D63: -819.92 | E63: -740.58 | F63: -819.92 | G63: -793.48 | H63: -819.98 | I63: 0 | J63: 0 | K63: 0 | L63: 0 | M63: 0 | N63: 0 | O63: 0 | Q63: -3993.88 | R63: -3993.85 | S63: -0.03 | T63: 0.0007511549 | V63: -9694.67 | X63: 4450.74
B65: OPERATING COST | D65: -257655.46 | E65: -363867.56 | F65: -317744.82 | G65: -395328.26 | H65: -384113.31 | I65: 0 | J65: 0 | K65: 0 | L65: 0 | M65: 0 | N65: 0 | O65: 0 | Q65: -1718709.4 | R65: -1661502.3 | S65: -57207.15 | T65: 3.4430979 | V65: -3964889.2 | X65: -1358441.6
B67: BARE BOAT EQUIVALENT | D67: 179906.61 | E67: 521186.26 | F67: 671368.56 | G67: 325355.35 | H67: 611848.26 | I67: 0 | J67: 0 | K67: 0 | L67: 0 | M67: 0 | N67: 0 | O67: 0 | Q67: 2309665 | R67: 1657140.2 | S67: 652524.88 | T67: 39.376565 | V67: 4465230.1 | X67: 1198639.2
A69: * DEPRECIACION NAVES | B69: DEPRECIACION NAVES | D69: -29795.8 | E69: -29602.04 | F69: -29602.19 | G69: -29676.88 | H69: -29611.75 | I69: 0 | J69: 0 | K69: 0 | L69: 0 | M69: 0 | N69: 0 | O69: 0 | Q69: -148288.66 | R69: -146174.75 | S69: -2113.91 | T69: 1.4461526 | V69: -350819.4 | X69: -148208.41
B70: COSTO IGV | D70: 0 | E70: 0 | F70: 0 | G70: 0 | H70: 0 | I70: 0 | J70: 0 | K70: 0 | L70: 0 | M70: 0 | N70: 0 | O70: 0 | Q70: 0 | R70: 0 | S70: 0 | T70: 0 | V70: 0 | X70: 0
B72: RESULTADO DE NAVE | D72: 0 | E72: 0 | F72: 0 | G72: 0 | H72: 0 | I72: 0 | J72: 0 | K72: 0 | L72: 0 | M72: 0 | N72: 0 | O72: 0 | Q72: 0 | R72: 0 | S72: 0 | T72: 0 | V72: 0 | X72: 0
T73: 0
A74: ** GTOS. ADMINIST. NAVE | B74: GTOS. ADMINISTRAT. NAVE | D74: -1023.61 | E74: -571.47 | F74: -634.51 | G74: -551.41 | H74: -546.75 | I74: 0 | J74: 0 | K74: 0 | L74: 0 | M74: 0 | N74: 0 | O74: 0 | Q74: -3327.75 | R74: -4651.1 | S74: 561.07 | T74: -12.063168 | V74: -11162.64 | X74: -4209.8
B75: GTOS. REPRESENTACION | D75: 0 | E75: 0 | F75: 0 | G75: 0 | H75: 0 | I75: 0 | J75: 0 | K75: 0 | L75: 0 | M75: 0 | N75: 0 | O75: 0 | Q75: 0 | R75: 0 | S75: 0 | T75: 0 | V75: 0 | X75: 0
B76: GTOS. VIAJE | D76: 0 | E76: 0 | F76: 0 | G76: 0 | H76: 0 | I76: 0 | J76: 0 | K76: 0 | L76: 0 | M76: 0 | N76: 0 | O76: 0 | Q76: 0 | R76: 0 | S76: 0 | T76: 0 | V76: 0 | X76: 0
A77: * GTOS. INFORMATICA | B77: GTOS. INFORMATICA | D77: -926.61 | E77: -571.47 | F77: -634.51 | G77: 0 | H77: 0 | I77: 0 | J77: 0 | K77: 0 | L77: 0 | M77: 0 | N77: 0 | O77: 0 | Q77: -2132.59 | R77: -2790.66 | S77: 658.07 | T77: -23.58116 | V77: -11162.64 | X77: -1861.88
A78: * GTOS. HONORARIOS | B78: GTOS. Honorarios | D78: 0 | E78: 0 | F78: 0 | G78: 0 | H78: 0 | I78: 0 | J78: 0 | K78: 0 | L78: 0 | M78: 0 | N78: 0 | O78: 0 | Q78: 0 | R78: 0 | S78: 0 | T78: 0 | V78: 0 | X78: 0
B79: SUSCRIPCIONES/PUBLICIDAD | D79: 0 | E79: 0 | F79: 0 | G79: 0 | H79: 0 | I79: 0 | J79: 0 | K79: 0 | L79: 0 | M79: 0 | N79: 0 | O79: 0 | Q79: 0 | R79: 0 | S79: 0 | T79: 0 | V79: 0 | X79: 0
A80: * UTILES DE ESCRITORIO | B80: UTILES DE ESCRITORIO | D80: -97 | E80: 0 | F80: 0 | G80: 0 | H80: 0 | I80: 0 | J80: 0 | K80: 0 | L80: 0 | M80: 0 | N80: 0 | O80: 0 | Q80: -97 | R80: 0 | S80: -97 | T80: 0 | V80: 0 | X80: -12.93
T81: 0
T82: 0
T83: 0
T84: 0
T85: 0
B87: M1 - MARGEN DIRECTO | D87: 149087.2 | E87: 491012.75 | F87: 641131.86 | G87: 295127.06 | H87: 581689.76 | I87: 0 | J87: 0 | K87: 0 | L87: 0 | M87: 0 | N87: 0 | O87: 0 | Q87: 2158048.6 | R87: 1506314.3 | S87: 650972.04 | T87: 43.216216 | V87: 4103248 | X87: 1046221
B89: GTOS. ADMINIST. GENERALES | D89: 0 | E89: 0 | F89: 0 | G89: 0 | H89: 0 | I89: 0 | J89: 0 | K89: 0 | L89: 0 | M89: 0 | N89: 0 | O89: 0 | Q89: 0 | R89: 0 | S89: 0 | T89: 0 | V89: 0 | X89: 0
B90: GTOS . ADMINIST. DEPRECIACION | D90: 0 | E90: 0 | F90: 0 | G90: 0 | H90: 0 | I90: 0 | J90: 0 | K90: 0 | L90: 0 | M90: 0 | N90: 0 | O90: 0 | Q90: 0 | R90: 0 | S90: 0 | T90: 0 | V90: 0 | X90: 0
B91: GTOS.ADM.DIRECTO FLOTA | D91: 0 | E91: 0 | F91: 0 | G91: 0 | H91: 0 | I91: 0 | J91: 0 | K91: 0 | L91: 0 | M91: 0 | N91: 0 | O91: 0 | Q91: 0 | R91: 0 | S91: 0 | T91: 0 | V91: 0 | X91: 0
B93: M3 - MARGEN OPERACIONAL | D93: 149087.2 | E93: 491012.75 | F93: 641131.86 | G93: 295127.06 | H93: 581689.76 | I93: 0 | J93: 0 | K93: 0 | L93: 0 | M93: 0 | N93: 0 | O93: 0 | Q93: 2158048.6 | R93: 1506314.3 | S93: 651734.32 | T93: 43.266821 | V93: 4103248 | X93: 1046221
B95: OTROS INGR./EGRESOS | D95: 0 | E95: 0 | F95: 0 | G95: 0 | H95: 0 | I95: 0 | J95: 0 | K95: 0 | L95: 0 | M95: 0 | N95: 0 | O95: 0 | Q95: 0 | R95: 0 | S95: 0 | T95: 0 | V95: 0 | X95: -135.42
A96: * INGRESOS FINANCIEROS | B96: INGRESOS FINANCIEROS | D96: 0 | E96: 0 | F96: 0 | G96: 0 | H96: 0 | I96: 0 | J96: 0 | K96: 0 | L96: 0 | M96: 0 | N96: 0 | O96: 0 | Q96: 0 | R96: 0 | S96: 0 | T96: 0 | V96: 0 | X96: 0
A97: * GASTOS FINANCIEROS | B97: GASTOS FINANCIEROS | D97: 0 | E97: 0 | F97: 0 | G97: 0 | H97: 0 | I97: 0 | J97: 0 | K97: 0 | L97: 0 | M97: 0 | N97: 0 | O97: 0 | Q97: 0 | R97: 0 | S97: 0 | T97: 0 | V97: 0 | X97: 0
B98: ING. (GTOS.) AÑO ANTERIOR | D98: 0 | E98: 0 | F98: 0 | G98: 0 | H98: 0 | I98: 0 | J98: 0 | K98: 0 | L98: 0 | M98: 0 | N98: 0 | O98: 0 | Q98: 0 | R98: 0 | S98: 0 | T98: 0 | V98: 0 | X98: 0
A99: * ING. (GTOS.) GESTION | B99: ING. (GTOS.) GESTION | D99: 0 | E99: 0 | F99: 0 | G99: 0 | H99: 0 | I99: 0 | J99: 0 | K99: 0 | L99: 0 | M99: 0 | N99: 0 | O99: 0 | Q99: 0 | R99: 0 | S99: 0 | T99: 0 | V99: 0 | X99: -135.42
B100: NPETRAL/PERSEUS | D100: 0 | E100: 0 | F100: 0 | G100: 0 | H100: 0 | I100: 0 | J100: 0 | K100: 0 | L100: 0 | M100: 0 | N100: 0 | O100: 0 | Q100: 0 | R100: 0 | S100: 0 | T100: 0 | V100: 0 | X100: 0
B101: INT.MINORITARIO Y RES.RENADSA | D101: 0 | E101: 0 | F101: 0 | G101: 0 | H101: 0 | I101: 0 | J101: 0 | K101: 0 | L101: 0 | M101: 0 | N101: 0 | O101: 0 | Q101: 0 | R101: 0 | S101: 0 | T101: 0 | V101: 0 | X101: 0
A102: * RESULT. DE TRASLACION/DIF. CAMB | B102: RESULT. DE TRASLACION | D102: 0 | E102: 0 | F102: 0 | G102: 0 | H102: 0 | I102: 0 | J102: 0 | K102: 0 | L102: 0 | M102: 0 | N102: 0 | O102: 0 | Q102: 0 | R102: 0 | S102: 0 | T102: 0 | V102: 0 | X102: 0
B104: M4 - RESULTADO ANTES IMPTO | D104: 149087.2 | E104: 491012.75 | F104: 641131.86 | G104: 295127.06 | H104: 581689.76 | I104: 0 | J104: 0 | K104: 0 | L104: 0 | M104: 0 | N104: 0 | O104: 0 | Q104: 2158048.6 | R104: 1506314.3 | S104: 651734.32 | T104: 43.266821 | V104: 4103248 | X104: 1046085.5
A106: **** TIME CHARTER EQUIVALENT (TC | B106: TIME CHARTER EQUIVALENT (TCE) | D106: 14114.905 | E106: 31609.065 | F106: 31906.883 | G106: 24022.787 | H106: 32127.793 | I106: 0 | J106: 0 | K106: 0 | L106: 0 | M106: 0 | N106: 0 | O106: 0 | Q106: 44759.716 | R106: 36873.805 | S106: 7885.9114 | T106: 21.386216 | V106: 23096.217 | X106: 21529.685
A107: ***** COSTO DIA NAVE (DRC) | B107: COSTO DIA NAVE (DRC) | D107: -8311.4665 | E107: -12995.27 | F107: -10249.833 | G107: -13177.609 | H107: -12390.752 | I107: 0 | J107: 0 | K107: 0 | L107: 0 | M107: 0 | N107: 0 | O107: 0 | Q107: -19096.771 | R107: -18461.136 | S107: -635.635 | T107: 3.4430979 | V107: -10862.71 | X107: -11437.581
A108: ***** COSTO DIA (DRC SIN DIQUE) | B108: COSTO DIA (DRC SIN DIQUE) | D108: -6347.8094 | E108: -10821.221 | F108: -8286.1755 | G108: -11148.496 | H108: -10427.095 | I108: 0 | J108: 0 | K108: 0 | L108: 0 | M108: 0 | N108: 0 | O108: 0 | Q108: -15714.917 | R108: -15079.282 | S108: -635.63489 | T108: 4.2152861 | V108: -8861.3938 | X108: -10942.807
A109: ****** RESULTADO DIARIO | B109: RESULTADO DIARIO | D109: 4809.2645 | E109: 17536.17 | F109: 20681.673 | G109: 9837.5687 | H109: 18764.186 | I109: 0 | J109: 0 | K109: 0 | L109: 0 | M109: 0 | N109: 0 | O109: 0 | Q109: 23978.318 | R109: 16736.826 | S109: 7241.4924 | T109: 43.266821 | V109: 11241.775 | X109: 8807.658
A110: DIAS OPERATIVOS - TIME CHAR | B110: DIAS OPERATIVOS | D110: 31 | E110: 28 | F110: 31 | G110: 30 | H110: 31 | I110: 0 | J110: 0 | K110: 0 | L110: 0 | M110: 0 | N110: 0 | O110: 0 | Q110: 90 | R110: 90 | S110: 180 | T110: 200 | V110: 365 | X110: 118.77
A111: DIAS OPERATIVOS - COSTO DRC | B111: DIAS DE EXCEPCION | D111: 31 | E111: 28 | F111: 31 | G111: 30 | H111: 31 | I111: 0 | J111: 0 | K111: 0 | L111: 0 | M111: 0 | N111: 0 | O111: 0 | Q111: 90 | R111: 90 | S111: 180 | T111: 200 | V111: 365 | X111: 151
A112: NUMERO DE VIAJES - NAVES | B112: NRO DE VIAJES | D112: 1 | E112: 4 | F112: 4 | G112: 2 | H112: 4 | I112: 0 | J112: 0 | K112: 0 | L112: 0 | M112: 0 | N112: 0 | O112: 0 | Q112: 9 | R112: 0 | S112: 9 | T112: 0 | X112: 10
B114: EBITDA | D114: 239756.37 | E114: 581488.16 | F114: 731607.43 | G114: 385677.31 | H114: 672174.88 | I114: 0 | J114: 0 | K114: 0 | L114: 0 | M114: 0 | N114: 0 | O114: 0 | Q114: 2610704.1 | R114: 1956855.9 | S114: 653085.96 | T114: 33.374249 | V114: 5184547.9 | X114: 1253193.8
D117: =+D24/D110 -> 14114.905 | E117: =+E24/E110 -> 31609.065 | F117: =+F24/F110 -> 31906.883 | G117: =+G24/G110 -> 24022.787 | H117: =+H24/H110 -> 32127.793 | I117: =+I24/I110 -> #DIV/0! | J117: =+J24/J110 -> #DIV/0! | K117: =+K24/K110 -> #DIV/0! | ... R117: =+R24/R110 -> 36873.805 | W117: =+W24/W110 -> #DIV/0! | X117: =+X24/X110 -> 21529.685
D118: =+D65/D111 -> -8311.4665 | E118: =+E65/E111 -> -12995.27 | F118: =+F65/F111 -> -10249.833 | G118: =+G65/G111 -> -13177.609 | H118: =+H65/H111 -> -12390.752 | I118: =+I65/I111 -> #DIV/0! | J118: =+J65/J111 -> #DIV/0! | K118: =+K65/K111 -> #DIV/0! | ... R118: =+R65/R111 -> -18461.136 | W118: =+W65/W111 -> #DIV/0! | X118: =+X65/X111 -> -8996.3017
D119: =+(D65-D58)/D111 -> -6347.8094 | E119: =+(E65-E58)/E111 -> -10821.221 | F119: =+(F65-F58)/F111 -> -8286.1755 | G119: =+(G65-G58)/G111 -> -11148.496 | H119: =+(H65-H58)/H111 -> -10427.095 | I119: =+(I65-I58)/I111 -> #DIV/0! | J119: =+(J65-J58)/J111 -> #DIV/0! | K119: =+(K65-K58)/K111 -> #DIV/0! | ... R119: =+(R65-R58)/R111 -> -15079.282 | W119: =+(W65-W58)/W111 -> #DIV/0! | X119: =+(X65-X58)/X111 -> -8607.1334
D120: =+D106-D117 -> 0 | E120: =+E106-E117 -> 0 | F120: =+F106-F117 -> 0 | G120: =+G106-G117 -> 0 | H120: =+H106-H117 -> 0 | I120: =+I106-I117 -> #DIV/0! | J120: =+J106-J117 -> #DIV/0! | K120: =+K106-K117 -> #DIV/0! | ... R120: =+R106-R117 -> 0 | W120: =+W106-W117 -> #VALUE! | X120: =+X106-X117 -> 0
D121: =+D107-D118 -> 0 | E121: =+E107-E118 -> 0 | F121: =+F107-F118 -> 0 | G121: =+G107-G118 -> 0 | H121: =+H107-H118 -> 0 | I121: =+I107-I118 -> #DIV/0! | J121: =+J107-J118 -> #DIV/0! | K121: =+K107-K118 -> #DIV/0! | ... R121: =+R107-R118 -> 0 | W121: =+W107-W118 -> #DIV/0! | X121: =+X107-X118 -> -2441.2798
D122: =+D108-D119 -> 0 | E122: =+E108-E119 -> 0 | F122: =+F108-F119 -> 0 | G122: =+G108-G119 -> 0 | H122: =+H108-H119 -> 0 | I122: =+I108-I119 -> #DIV/0! | J122: =+J108-J119 -> #DIV/0! | K122: =+K108-K119 -> #DIV/0! | ... R122: =+R108-R119 -> 0 | W122: =+W108-W119 -> #VALUE! | X122: =+X108-X119 -> -2335.6732

Sheet MOQUEGUA GRR3
B2: US$ Dolar | C2: Enero | D2: Febrero | E2: Marzo | F2: Abril | G2: Mayo | H2: Junio | I2: Julio | J2: Agosto | K2: Setiembre | L2: Octubre | M2: Noviembre | N2: Diciembre | O2: Acum. 2026 | P2: Ppto.Acum a 3 | Q2: Variacion | R2: Ppto Anual | S2: % | T2: Ppto Mens | U2: Real A o anterior
B3: ** VENTAS | C3: -551026.33 | D3: -1155413 | E3: -1436461.6 | F3: 0 | G3: 0 | H3: 0 | I3: 0 | J3: 0 | K3: 0 | L3: 0 | M3: 0 | N3: 0 | O3: -3142901 | P3: -2750040 | Q3: 392860.95 | R3: -11408070 | S3: -14.2856 | T3: -947780 | U3: 0
B4: 704121 FLETES A TERC-NAV P | C4: 0 | D4: 0 | E4: 0 | F4: 0 | G4: 0 | H4: 0 | I4: 0 | J4: 0 | K4: 0 | L4: 0 | M4: 0 | N4: 0 | O4: 0 | P4: -2249040 | Q4: -2249040 | R4: -9558070 | S4: 100 | T4: -784780 | U4: 0
B5: 703213 FLETES A T-NAV PR L | C5: -197159.69 | D5: -1018421.9 | E5: -1132813.4 | F5: 0 | G5: 0 | H5: 0 | I5: 0 | J5: 0 | K5: 0 | L5: 0 | M5: 0 | N5: 0 | O5: -2348395.1 | P5: 0 | Q5: 2348395.1 | R5: 0 | S5: 0 | T5: 0 | U5: 0
B6: * HIRE | C6: -197159.69 | D6: -1018421.9 | E6: -1132813.4 | F6: 0 | G6: 0 | H6: 0 | I6: 0 | J6: 0 | K6: 0 | L6: 0 | M6: 0 | N6: 0 | O6: -2348395.1 | P6: -2249040 | Q6: 99355.06 | R6: -9558070 | S6: -4.4177 | T6: -784780 | U6: 0
B7: 704123 DEMORAS | C7: 0 | D7: 0 | E7: 0 | F7: 0 | G7: 0 | H7: 0 | I7: 0 | J7: 0 | K7: 0 | L7: 0 | M7: 0 | N7: 0 | O7: 0 | P7: -440000 | Q7: -440000 | R7: -1710000 | S7: 100 | T7: -160000 | U7: 0
B8: 703115 DEMORAS EXPORTACION | C8: -153291.04 | D8: 297956.27 | E8: -200973.33 | F8: 0 | G8: 0 | H8: 0 | I8: 0 | J8: 0 | K8: 0 | L8: 0 | M8: 0 | N8: 0 | O8: -56308.1 | P8: 0 | Q8: 56308.1 | R8: 0 | S8: 0 | T8: 0 | U8: 0
B9: 703215 DEMORAS -LOCAL | C9: -178274.29 | D9: -428181.62 | E9: -25238.13 | F9: 0 | G9: 0 | H9: 0 | I9: 0 | J9: 0 | K9: 0 | L9: 0 | M9: 0 | N9: 0 | O9: -631694.04 | P9: 0 | Q9: 631694.04 | R9: 0 | S9: 0 | T9: 0 | U9: 0
B10: * DEMORAS | C10: -331565.33 | D10: -130225.35 | E10: -226211.46 | F10: 0 | G10: 0 | H10: 0 | I10: 0 | J10: 0 | K10: 0 | L10: 0 | M10: 0 | N10: 0 | O10: -688002.14 | P10: -440000 | Q10: 248002.14 | R10: -1710000 | S10: -56.3641 | T10: -160000 | U10: 0
B11: 704136 SERV DE ATENC EN PU | C11: 0 | D11: 0 | E11: 0 | F11: 0 | G11: 0 | H11: 0 | I11: 0 | J11: 0 | K11: 0 | L11: 0 | M11: 0 | N11: 0 | O11: 0 | P11: -61000 | Q11: -61000 | R11: -140000 | S11: 100 | T11: -3000 | U11: 0
B12: 703118 SERV ATENC EN PUE E | C12: -20295.62 | D12: 20295.62 | E12: -20000 | F12: 0 | G12: 0 | H12: 0 | I12: 0 | J12: 0 | K12: 0 | L12: 0 | M12: 0 | N12: 0 | O12: -20000 | P12: 0 | Q12: 20000 | R12: 0 | S12: 0 | T12: 0 | U12: 0
B13: 703218 SERV ATENC EN PUE L | C13: -2005.69 | D13: -27061.33 | E13: -57436.73 | F13: 0 | G13: 0 | H13: 0 | I13: 0 | J13: 0 | K13: 0 | L13: 0 | M13: 0 | N13: 0 | O13: -86503.75 | P13: 0 | Q13: 86503.75 | R13: 0 | S13: 0 | T13: 0 | U13: 0
B14: * INGRESOS DE PUERTO | C14: -22301.31 | D14: -6765.71 | E14: -77436.73 | F14: 0 | G14: 0 | H14: 0 | I14: 0 | J14: 0 | K14: 0 | L14: 0 | M14: 0 | N14: 0 | O14: -106503.75 | P14: -61000 | Q14: 45503.75 | R14: -140000 | S14: -74.5963 | T14: -3000 | U14: 0
... B130: ******* EBITDA | C130: -239756.37 | D130: -581488.16 | E130: -731607.43 | F130: 0 | G130: 0 | H130: 0 | I130: 0 | J130: 0 | K130: 0 | L130: 0 | M130: 0 | N130: 0 | O130: -1552852 | P130: -1223010.1 | Q130: 329841.89 | R130: -5184547.9 | S130: -26.9697 | T130: -463425.05 | U130: 0

Sheet Hoja2
B2: US$ Dolar | C2: Enero | D2: Febrero | E2: Marzo | F2: Abril | G2: Mayo | H2: Junio | I2: Julio | J2: Agosto | K2: Setiembre | L2: Octubre | M2: Noviembre | N2: Diciembre | O2: Acum. 2025 | P2: Ppto.Acum a 11 | Q2: Variacion | R2: Ppto Anual | S2: % | T2: Ppto Mens | U2: Real A o anterior
B3: ** VENTAS | C3: 0 | D3: 0 | E3: 0 | F3: 0 | G3: 0 | H3: 0 | I3: 0 | J3: 0 | K3: 0 | L3: -8089557.2 | M3: -843919.19 | N3: 0 | O3: -8933476.4 | P3: -8835050.9 | Q3: 98425.46 | R3: -9405058.7 | S3: -1.114 | T3: -854357.81 | U3: 0
B4: 704121 FLETES A TERC-NAV P | C4: 0 | D4: 0 | E4: 0 | F4: 0 | G4: 0 | H4: 0 | I4: 0 | J4: 0 | K4: 0 | L4: 0 | M4: 0 | N4: 0 | O4: 0 | P4: -7294890 | Q4: -7294890 | R4: -7731065 | S4: 100 | T4: -707525 | U4: 0
B5: 703213 FLETES A T-NAV PR L | C5: 0 | D5: 0 | E5: 0 | F5: 0 | G5: 0 | H5: 0 | I5: 0 | J5: 0 | K5: 0 | L5: -5958195.2 | M5: -804314.52 | N5: 0 | O5: -6762509.7 | P5: 0 | Q5: 6762509.7 | R5: 0 | S5: 0 | T5: 0 | U5: 0
B6: * HIRE | C6: 0 | D6: 0 | E6: 0 | F6: 0 | G6: 0 | H6: 0 | I6: 0 | J6: 0 | K6: 0 | L6: -5958195.2 | M6: -804314.52 | N6: 0 | O6: -6762509.7 | P6: -7294890 | Q6: -532380.28 | R6: -7731065 | S6: 7.298 | T6: -707525 | U6: 0
B7: 704123 DEMORAS | C7: 0 | D7: 0 | E7: 0 | F7: 0 | G7: 0 | H7: 0 | I7: 0 | J7: 0 | K7: 0 | L7: 0 | M7: 0 | N7: 0 | O7: 0 | P7: -1439160.9 | Q7: -1439160.9 | R7: -1569993.7 | S7: 100 | T7: -130832.81 | U7: 0
B8: 703115 DEMORAS EXPORTACION | C8: 0 | D8: 0 | E8: 0 | F8: 0 | G8: 0 | H8: 0 | I8: 0 | J8: 0 | K8: 0 | L8: -43416.17 | M8: 88599.65 | N8: 0 | O8: 45183.48 | P8: 0 | Q8: -45183.48 | R8: 0 | S8: 0 | T8: 0 | U8: 0
B9: 703215 DEMORAS -LOCAL | C9: 0 | D9: 0 | E9: 0 | F9: 0 | G9: 0 | H9: 0 | I9: 0 | J9: 0 | K9: 0 | L9: -1917851.9 | M9: -107482.9 | N9: 0 | O9: -2025334.8 | P9: 0 | Q9: 2025334.8 | R9: 0 | S9: 0 | T9: 0 | U9: 0
B10: * DEMORAS | C10: 0 | D10: 0 | E10: 0 | F10: 0 | G10: 0 | H10: 0 | I10: 0 | J10: 0 | K10: 0 | L10: -1961268.1 | M10: -18883.25 | N10: 0 | O10: -1980151.3 | P10: -1439160.9 | Q10: 540990.4 | R10: -1569993.7 | S10: -37.5907 | T10: -130832.81 | U10: 0
B11: 704136 SERV DE ATENC EN PU | C11: 0 | D11: 0 | E11: 0 | F11: 0 | G11: 0 | H11: 0 | I11: 0 | J11: 0 | K11: 0 | L11: 0 | M11: 0 | N11: 0 | O11: 0 | P11: -101000 | Q11: -101000 | R11: -104000 | S11: 100 | T11: -16000 | U11: 0
B12: 703118 SERV ATENC EN PUE E | C12: 0 | D12: 0 | E12: 0 | F12: 0 | G12: 0 | H12: 0 | I12: 0 | J12: 0 | K12: 0 | L12: 11508 | M12: 39000 | N12: 0 | O12: 50508 | P12: 0 | Q12: -50508 | R12: 0 | S12: 0 | T12: 0 | U12: 0
B13: 703218 SERV ATENC EN PUE L | C13: 0 | D13: 0 | E13: 0 | F13: 0 | G13: 0 | H13: 0 | I13: 0 | J13: 0 | K13: 0 | L13: -181601.92 | M13: -59721.42 | N13: 0 | O13: -241323.34 | P13: 0 | Q13: 241323.34 | R13: 0 | S13: 0 | T13: 0 | U13: 0
B14: * INGRESOS DE PUERTO | C14: 0 | D14: 0 | E14: 0 | F14: 0 | G14: 0 | H14: 0 | I14: 0 | J14: 0 | K14: 0 | L14: -170093.92 | M14: -20721.42 | N14: 0 | O14: -190815.34 | P14: -101000 | Q14: 89815.34 | R14: -104000 | S14: -88.9261 | T14: -16000 | U14: 0
... B141: ******* EBITDA | C141: 0 | D141: 0 | E141: 0 | F141: 0 | G141: 0 | H141: 0 | I141: 0 | J141: 0 | K141: 0 | L141: -3570612.6 | M141: -377015.16 | N141: 0 | O141: -3947627.8 | P141: -3621587.1 | Q141: 326040.62 | R141: -3784174.9 | S141: -9.0027 | T141: -392021.95 | U141: 0

Sheet Tablones
Z1: =+PETRAL!Z1 -> 5
B2: Control Presupuestal
B3: =+PETRAL!B3 -> 46143 | D3: TABLONES
Q5: REAL | R5: PRESUP. | V5: PPTO. | X5: Real Acum.
B6: (US$ Dólares) | D6: ENE | E6: FEB | F6: MAR | G6: ABR | H6: MAY | I6: JUN | J6: JUL | K6: AGO | L6: SET | M6: OCT | N6: NOV | O6: DIC | Q6: ACUMUL. | R6: ACUMUL. | S6: VARIACION | T6: % | V6: ANUAL | X6: =+PETRAL!X6 -> 45778
B8: VENTAS | D8: 1171040.6 | E8: 955778.87 | F8: 1222513.1 | G8: 1057662.1 | H8: 915690.05 | I8: 0 | J8: 0 | K8: 0 | L8: 0 | M8: 0 | N8: 0 | O8: 0 | Q8: 5322684.6 | R8: 5247975 | S8: 74709.63 | T8: 1.4235897 | V8: 11025680 | X8: 5013071.8
A9: * HIRE | B9: HIRE | D9: 844069.75 | E9: 808897.03 | F9: 859884.72 | G9: 814061.18 | H9: 588616.35 | I9: 0 | J9: 0 | K9: 0 | L9: 0 | M9: 0 | N9: 0 | O9: 0 | Q9: 3915529 | R9: 4047975 | S9: -132445.97 | T9: -3.2719068 | V9: 8635680 | X9: 3661399.3
B10: VENTA DE TERCEROS | D10: 0 | E10: 0 | F10: 0 | G10: 0 | H10: 0 | I10: 0 | J10: 0 | K10: 0 | L10: 0 | M10: 0 | N10: 0 | O10: 0 | Q10: 0 | R10: 0 | S10: 0 | T10: 0 | V10: 0 | X10: 0
A11: * DEMORAS | B11: DEMORAS | D11: 273123.92 | E11: 85124.65 | F11: 336325.55 | G11: 188440.91 | H11: 293507.16 | I11: 0 | J11: 0 | K11: 0 | L11: 0 | M11: 0 | N11: 0 | O11: 0 | Q11: 1176522.2 | R11: 900000 | S11: 276522.19 | T11: 30.724688 | V11: 1750000 | X11: 1160979.3
A12: * INGRESOS DE PUERTO | B12: INGRESOS DE PUERTO | D12: 53846.9 | E12: 61757.19 | F12: 26302.78 | G12: 55160 | H12: 33566.54 | I12: 0 | J12: 0 | K12: 0 | L12: 0 | M12: 0 | N12: 0 | O12: 0 | Q12: 230633.41 | R12: 300000 | S12: -69366.59 | T12: -23.122197 | V12: 640000 | X12: 190693.28
A13: * OTROS INGRESOS | B13: OTROS INGRESOS | D13: 0 | E13: 0 | F13: 0 | G13: 0 | H13: 0 | I13: 0 | J13: 0 | K13: 0 | L13: 0 | M13: 0 | N13: 0 | O13: 0 | Q13: 0 | R13: 0 | S13: 0 | T13: 0 | V13: 0 | X13: 0
B15: COSTOS DIRECTOS | D15: -380007.34 | E15: -445325.4 | F15: -133696.13 | G15: -304286.12 | H15: -251189.65 | I15: 0 | J15: 0 | K15: 0 | L15: 0 | M15: 0 | N15: 0 | O15: 0 | Q15: -1514504.6 | R15: -1802144.9 | S15: 287640.21 | T15: -15.960993 | V15: -3912743.4 | X15: -1595430.4
A16: * COMBUSTIBLE | B16: COMBUSTIBLE | D16: -119578.39 | E16: -127935.08 | F16: -77787.76 | G16: -107266.88 | H16: -138748.29 | I16: 0 | J16: 0 | K16: 0 | L16: 0 | M16: 0 | N16: 0 | O16: 0 | Q16: -571316.4 | R16: -797144.85 | S16: 225828.45 | T16: -28.329663 | V16: -1768743.4 | X16: -699598.52
A17: * GASTOS DE PUERTO | B17: GASTOS DE PUERTO | D17: -260428.95 | E17: -317390.32 | F17: -52458.38 | G17: -197019.24 | H17: -111426.36 | I17: 0 | J17: 0 | K17: 0 | L17: 0 | M17: 0 | N17: 0 | O17: 0 | Q17: -938723.25 | R17: -1005000 | S17: 66276.75 | T17: -6.5947015 | V17: -2144000 | X17: -895831.83
B18: COSTOS DE DEMORA | D18: 0 | E18: 0 | F18: 0 | G18: 0 | H18: 0 | I18: 0 | J18: 0 | K18: 0 | L18: 0 | M18: 0 | N18: 0 | O18: 0 | Q18: 0 | R18: 0 | S18: 0 | T18: 0 | V18: 0 | X18: 0
B19: COMISION BROCKERAGE | D19: 0 | E19: 0 | F19: 0 | G19: 0 | H19: 0 | I19: 0 | J19: 0 | K19: 0 | L19: 0 | M19: 0 | N19: 0 | O19: 0 | Q19: 0 | R19: 0 | S19: 0 | T19: 0 | V19: 0 | X19: 0
B20: COMISIONES VARIAS | D20: 0 | E20: 0 | F20: 0 | G20: 0 | H20: 0 | I20: 0 | J20: 0 | K20: 0 | L20: 0 | M20: 0 | N20: 0 | O20: 0 | Q20: 0 | R20: 0 | S20: 0 | T20: 0 | V20: 0 | X20: 0
A21: * OTROS COSTOS DIRECTOS | B21: OTROS COSTOS DIRECTOS | D21: 0 | E21: 0 | F21: -3449.99 | G21: 0 | H21: -1015 | I21: 0 | J21: 0 | K21: 0 | L21: 0 | M21: 0 | N21: 0 | O21: 0 | Q21: -4464.99 | R21: 0 | S21: -4464.99 | T21: 0 | V21: 0 | X21: 0
B22: GASTO PUERTO POR RECIBIR | D22: 0 | E22: 0 | F22: 0 | G22: 0 | H22: 0 | I22: 0 | J22: 0 | K22: 0 | L22: 0 | M22: 0 | N22: 0 | O22: 0 | Q22: 0 | R22: 0 | S22: 0 | T22: 0 | V22: 0 | X22: 0
B24: TIME CHARTER EQUIVALENT | D24: 791033.23 | E24: 510453.47 | F24: 1088816.9 | G24: 753375.97 | H24: 664500.4 | I24: 0 | J24: 0 | K24: 0 | L24: 0 | M24: 0 | N24: 0 | O24: 0 | Q24: 3808180 | R24: 3445830.1 | S24: 362349.84 | T24: 10.515604 | V24: 7112936.6 | X24: 3417641.5
B26: COSTO DE ARRIENDO NAVES | D26: 0 | E26: 0 | F26: 0 | G26: 0 | H26: 0 | I26: 0 | J26: 0 | K26: 0 | L26: 0 | M26: 0 | N26: 0 | O26: 0 | Q26: 0 | R26: 0 | S26: 0 | T26: 0 | V26: 0 | X26: 0
B28: MARGEN BRUTO | D28: 791033.23 | E28: 510453.47 | F28: 1088816.9 | G28: 753375.97 | H28: 664500.4 | I28: 0 | J28: 0 | K28: 0 | L28: 0 | M28: 0 | N28: 0 | O28: 0 | Q28: 3808180 | R28: 3445830.1 | S28: 362349.84 | T28: 10.515604 | V28: 7112936.6 | X28: 3417641.5
B30: GTOS. PERSONAL A BORDO | D30: -167083.49 | E30: -199245.36 | F30: -168976.35 | G30: -160871.15 | H30: -164645.54 | I30: 0 | J30: 0 | K30: 0 | L30: 0 | M30: 0 | N30: 0 | O30: 0 | Q30: -860821.89 | R30: -928141.88 | S30: 67319.99 | T30: -7.2532003 | V30: -2172021.5 | X30: -780384.43
B31: GASTOS DE PERSONAL | D31: -167083.49 | E31: -199245.36 | F31: -168976.35 | G31: -160871.15 | H31: -164645.54 | I31: 0 | J31: 0 | K31: 0 | L31: 0 | M31: 0 | N31: 0 | O31: 0 | Q31: -860821.89 | R31: -928141.88 | S31: 67319.99 | T31: -7.2532003 | V31: -2172021.5 | X31: -780384.43
A33: * SUELDOS | B33: SUELDOS | D33: -106436.85 | E33: -146001.06 | F33: -94427.89 | G33: -99041.96 | H33: -94680.08 | I33: 0 | J33: 0 | K33: 0 | L33: 0 | M33: 0 | N33: 0 | O33: 0 | Q33: -540587.84 | R33: -523020.72 | S33: -17567.12 | T33: 3.3587809 | V33: -1205715.7 | X33: -474804.85
A34: * VACACIONES | B34: VACACIONES | D34: -5946.48 | E34: -5197.26 | F34: -8114.44 | G34: -3904.9 | H34: -10960.45 | I34: 0 | J34: 0 | K34: 0 | L34: 0 | M34: 0 | N34: 0 | O34: 0 | Q34: -34123.53 | R34: -40071.25 | S34: 5947.72 | T34: -14.842861 | V34: -97697.77 | X34: -22934.83
A35: * GRATIFICACIONES | B35: GRATIFICACIONES | D35: -9437.85 | E35: -10807.28 | F35: -18247.81 | G35: -12990.4 | H35: -19652.7 | I35: 0 | J35: 0 | K35: 0 | L35: 0 | M35: 0 | N35: 0 | O35: 0 | Q35: -71136.04 | R35: -106070.91 | S35: 34934.87 | T35: -32.935392 | V35: -243953.31 | X35: -62879.05
A36: * BENEFICIOS SOCIALES | B36: BENEFICIOS SOCIALES | D36: -10898.35 | E36: -7528.37 | F36: -11263.49 | G36: 3249.31 | H36: -7781.14 | I36: 0 | J36: 0 | K36: 0 | L36: 0 | M36: 0 | N36: 0 | O36: 0 | Q36: -34222.04 | R36: -45833.1 | S36: 11611.06 | T36: -25.333351 | V36: -111745.8 | X36: -32690.4
A37: * ESSALUD | B37: ESSALUD | D37: -5844.39 | E37: -8418.46 | F37: -5903.92 | G37: -5330.18 | H37: -5793.57 | I37: 0 | J37: 0 | K37: 0 | L37: 0 | M37: 0 | N37: 0 | O37: 0 | Q37: -31290.52 | R37: -35659.45 | S37: 4368.93 | T37: -12.251815 | V37: -86941.45 | X37: -30459.86
A38: * E.P.S. /GASTOS MEDICOS | B38: E.P.S. /GASTOS MEDICOS | D38: -3940.29 | E38: -4756.12 | F38: -2926.23 | G38: -379.22 | H38: -5351.98 | I38: 0 | J38: 0 | K38: 0 | L38: 0 | M38: 0 | N38: 0 | O38: 0 | Q38: -17353.84 | R38: -18000 | S38: 646.16 | T38: -3.5897778 | V38: -43200 | X38: -20776.96
A39: * VESTUARIO | B39: VESTUARIO | D39: -5435.43 | E39: -8.7 | F39: 0 | G39: -12.75 | H39: 0 | I39: 0 | J39: 0 | K39: 0 | L39: 0 | M39: 0 | N39: 0 | O39: 0 | Q39: -5456.88 | R39: -4250 | S39: -1206.88 | T39: 28.397176 | V39: -10200 | X39: -2613.63
A40: * CAPACITACION | B40: CAPACITACION | D40: -28.93 | E40: -40.14 | F40: 0 | G40: -199.01 | H40: -578.26 | I40: 0 | J40: 0 | K40: 0 | L40: 0 | M40: 0 | N40: 0 | O40: 0 | Q40: -846.34 | R40: -4000 | S40: 3153.66 | T40: -78.8415 | V40: -9600 | X40: -1473.88
A41: * TRASLADO DE TRIPULACION | B41: TRASLADO DE TRIPULACION | D41: -6980.65 | E41: -4484.72 | F41: -8437 | G41: -7381.07 | H41: -7914.73 | I41: 0 | J41: 0 | K41: 0 | L41: 0 | M41: 0 | N41: 0 | O41: 0 | Q41: -35198.17 | R41: -36000 | S41: 801.83 | T41: -2.2273056 | V41: -86400 | X41: -34927.27
A42: * OTROS GTOS. DE PERSONAL | B42: OTROS GTOS. DE PERSONAL | D42: -12153.54 | E42: -11988.96 | F42: -11700.03 | G42: -11887.56 | H42: -11981.9 | I42: 0 | J42: 0 | K42: 0 | L42: 0 | M42: 0 | N42: 0 | O42: 0 | Q42: -59711.99 | R42: -65516.8 | S42: 5804.81 | T42: -8.8600328 | V42: -157240.32 | X42: -58782.8
A43: * VIVERES DE TRIPULACION | B43: VIVERES DE TRIPULACION | D43: 19.27 | E43: -14.29 | F43: -7955.54 | G43: -22993.41 | H43: 49.27 | I43: 0 | J43: 0 | K43: 0 | L43: 0 | M43: 0 | N43: 0 | O43: 0 | Q43: -30894.7 | R43: -49719.65 | S43: 18824.95 | T43: -37.862193 | V43: -119327.16 | X43: -38040.9
B45: GASTOS DE LA NAVE | D45: -73760.1 | E45: -131615.3 | F45: -96764.81 | G45: -92506.02 | H45: -97393.13 | I45: 0 | J45: 0 | K45: 0 | L45: 0 | M45: 0 | N45: 0 | O45: 0 | Q45: -492039.36 | R45: -400670 | S45: -91369.36 | T45: 22.804143 | V45: -911892 | W45: 0 | X45: -370459.65
A46: * LUBRICANTES | B46: LUBRICANTES | D46: -18300 | E46: -28016.81 | F46: -1.31 | G46: -4531.57 | H46: -24493.32 | I46: 0 | J46: 0 | K46: 0 | L46: 0 | M46: 0 | N46: 0 | O46: 0 | Q46: -75343.01 | R46: -40940 | S46: -34403.01 | T46: 84.032755 | V46: -119820 | X46: -44169.82
A47: * REPUESTOS Y MANTENIMIEN | B47: REPUESTOS Y MANTENIMIENTO | D47: -10335.88 | E47: -75697.49 | F47: -62322.06 | G47: -36500.46 | H47: -20426.61 | I47: 0 | J47: 0 | K47: 0 | L47: 0 | M47: 0 | N47: 0 | O47: 0 | Q47: -205282.5 | R47: -189000 | S47: -16282.5 | T47: 8.6150794 | V47: -384000 | X47: -119119.57
A48: * MATERIAL CONSUMIBLE | B48: MATERIAL CONSUMIBLE | D48: -29609.8 | E48: -4375.92 | F48: -17524.22 | G48: -22403.02 | H48: -23457.11 | I48: 0 | J48: 0 | K48: 0 | L48: 0 | M48: 0 | N48: 0 | O48: 0 | Q48: -97370.07 | R48: -66000 | S48: -31370.07 | T48: 47.530409 | V48: -158400 | X48: -88566.88
A49: * CERTIF. /INSPECCION | B49: CERTIF. /INSPECCION | D49: -615.6 | E49: -3713.66 | F49: -1036.49 | G49: -10613.02 | H49: -12051.48 | I49: 0 | J49: 0 | K49: 0 | L49: 0 | M49: 0 | N49: 0 | O49: 0 | Q49: -28030.25 | R49: -20450 | S49: -7580.25 | T49: 37.067237 | V49: -47400 | X49: -22219.44
B50: OTROS COSTOS | D50: -2242.82 | E50: -7155.42 | F50: -3224.73 | G50: -5801.95 | H50: -4308.61 | I50: 0 | J50: 0 | K50: 0 | L50: 0 | M50: 0 | N50: 0 | O50: 0 | Q50: -22733.53 | R50: -21000 | S50: -1733.53 | T50: 8.2549048 | V50: -50400 | X50: -33103.94
A51: * SQE | B51: SQE | D51: 0 | E51: 0 | F51: 0 | G51: 0 | H51: 0 | I51: 0 | J51: 0 | K51: 0 | L51: 0 | M51: 0 | N51: 0 | O51: 0 | Q51: 0 | R51: 0 | S51: 0 | T51: 0 | V51: 0 | X51: 0
B52: VIGILANCIA Y SEGURIDAD PRIVADA | D52: 0 | E52: 0 | F52: 0 | G52: 0 | H52: 0 | I52: 0 | J52: 0 | K52: 0 | L52: 0 | M52: 0 | N52: 0 | O52: 0 | Q52: 0 | R52: 0 | S52: 0 | T52: 0 | V52: 0 | X52: 0
B53: AGENCIMIENTO | D53: 0 | E53: 0 | F53: 0 | G53: 0 | H53: 0 | I53: 0 | J53: 0 | K53: 0 | L53: 0 | M53: 0 | N53: 0 | O53: 0 | Q53: 0 | R53: 0 | S53: 0 | T53: 0 | V53: 0 | X53: 0
A54: * COMUNICACIONES | B54: COMUNICACIONES | D54: -2442.82 | E54: -4145.42 | F54: -2024.73 | G54: -1831.58 | H54: -2654.61 | I54: 0 | J54: 0 | K54: 0 | L54: 0 | M54: 0 | N54: 0 | O54: 0 | Q54: -13099.16 | R54: -16000 | S54: 2900.84 | T54: -18.13025 | V54: -38400 | X54: -27772.96
A55: * OTROS GTOS. DE LA NAVE | B55: OTROS GTOS. DE LA NAVE | D55: 200 | E55: -3010 | F55: -1200 | G55: -3970.37 | H55: -1654 | I55: 0 | J55: 0 | K55: 0 | L55: 0 | M55: 0 | N55: 0 | O55: 0 | Q55: -9634.37 | R55: -5000 | S55: -4634.37 | T55: 92.6874 | V55: -12000 | X55: -5330.98
A56: * GASTO ADM.DIRECTO FLOTA | B56: GASTO ADM.DIRECTO FLOTA | D56: -12656 | E56: -12656 | F56: -12656 | G56: -12656 | H56: -12656 | I56: 0 | J56: 0 | K56: 0 | L56: 0 | M56: 0 | N56: 0 | O56: 0 | Q56: -63280 | R56: -63280 | S56: 0 | T56: 0 | V56: -151872 | X56: -63280
A58: * DEPRECIACION CARENA DIQUE | B58: DEPRECIACION CARENA DIQUE | D58: -40468.16 | E58: -40468.17 | F58: -40468.16 | G58: -40468.16 | H58: -40468.16 | I58: 0 | J58: 0 | K58: 0 | L58: 0 | M58: 0 | N58: 0 | O58: 0 | Q58: -202340.81 | R58: -202340.8 | S58: -0.01 | T58: 4.942157e-06 | V58: -485617.92 | X58: 0
B60: SEGUROS | D60: -11699.29 | E60: -10567.17 | F60: -11637.53 | G60: -11274.4 | H60: -11650.3 | I60: 0 | J60: 0 | K60: 0 | L60: 0 | M60: 0 | N60: 0 | O60: 0 | Q60: -56828.69 | R60: -55895.28 | S60: -933.41 | T60: 1.6699263 | V60: -135983.9 | X60: -26466.4
A61: * CASCO Y MAQUINA | B61: CASCO Y MAQUINA | D61: -7985.81 | E61: -7213 | F61: -7985.81 | G61: -7728.21 | H61: -7985.81 | I61: 0 | J61: 0 | K61: 0 | L61: 0 | M61: 0 | N61: 0 | O61: 0 | Q61: -38898.64 | R61: -37850.19 | S61: -1048.45 | T61: 2.7699993 | V61: -92491.13 | X61: -11832.77
A62: * PANDI | B62: PANDI | D62: -2865.09 | E62: -2587.87 | F62: -2803.33 | G62: -2725.16 | H62: -2816 | I62: 0 | J62: 0 | K62: 0 | L62: 0 | M62: 0 | N62: 0 | O62: 0 | Q62: -13797.45 | R62: -13912.56 | S62: 115.11 | T62: -0.82738188 | V62: -33462.86 | X62: -11613.24
A63: * DEDUCIBLES Y OTROS | B63: DEDUCIBLES Y OTROS | D63: -848.39 | E63: -766.3 | F63: -848.39 | G63: -821.03 | H63: -848.49 | I63: 0 | J63: 0 | K63: 0 | L63: 0 | M63: 0 | N63: 0 | O63: 0 | Q63: -4132.6 | R63: -4132.53 | S63: -0.07 | T63: 0.0016938776 | V63: -10029.91 | X63: -3020.39
B65: OPERATING COST | D65: -293011.04 | E65: -381896 | F65: -317846.85 | G65: -305119.73 | H65: -314157.13 | I65: 0 | J65: 0 | K65: 0 | L65: 0 | M65: 0 | N65: 0 | O65: 0 | Q65: -1612030.8 | R65: -1587048 | S65: -24982.79 | T65: 1.5741673 | V65: -3705515.3 | X65: -1177310.5
B67: BARE BOAT EQUIVALENT | D67: 498022.19 | E67: 128557.47 | F67: 770970.07 | G67: 448256.24 | H67: 350343.27 | I67: 0 | J67: 0 | K67: 0 | L67: 0 | M67: 0 | N67: 0 | O67: 0 | Q67: 2196149.2 | R67: 1858782.2 | S67: 337367.05 | T67: 18.149897 | V67: 3407421.3 | X67: 2240331
A69: * DEPRECIACION NAVES | B69: DEPRECIACION NAVES | D69: -124102.92 | E69: -124200.37 | F69: -124235.77 | G69: -124473.22 | H69: -124419.75 | I69: 0 | J69: 0 | K69: 0 | L69: 0 | M69: 0 | N69: 0 | O69: 0 | Q69: -621432.03 | R69: -617024.55 | S69: -4407.48 | T69: 0.71431193 | V69: -1480858.9 | X69: -609804.24
B70: COSTO IGV | D70: 0 | E70: 0 | F70: 0 | G70: 0 | H70: 0 | I70: 0 | J70: 0 | K70: 0 | L70: 0 | M70: 0 | N70: 0 | O70: 0 | Q70: 0 | R70: 0 | S70: 0 | T70: 0 | V70: 0 | X70: 0
X71: 0
B72: RESULTADO DE NAVE | D72: 0 | E72: 0 | F72: 0 | G72: 0 | H72: 0 | I72: 0 | J72: 0 | K72: 0 | L72: 0 | M72: 0 | N72: 0 | O72: 0 | Q72: 0 | R72: 0 | S72: 0 | T72: 0 | V72: 0 | X72: 0
T73: 0 | X73: 0
A74: ** GTOS. ADMINIST. NAVE | B74: GTOS. ADMINISTRAT. NAVE | D74: -899.7 | E74: -571.47 | F74: -634.51 | G74: -551.41 | H74: -546.75 | I74: 0 | J74: 0 | K74: 0 | L74: 0 | M74: 0 | N74: 0 | O74: 0 | Q74: -3203.84 | R74: -879.25 | S74: -1578.13 | T74: 179.48593 | V74: -2110.2 | X74: -1842.34
B75: GTOS. REPRESENTACION | D75: 0 | E75: 0 | F75: 0 | G75: 0 | H75: 0 | I75: 0 | J75: 0 | K75: 0 | L75: 0 | M75: 0 | N75: 0 | O75: 0 | Q75: 0 | R75: 0 | S75: 0 | T75: 0 | V75: 0 | X75: 0
B76: GTOS. VIAJE | D76: 0 | E76: 0 | F76: 0 | G76: 0 | H76: 0 | I76: 0 | J76: 0 | K76: 0 | L76: 0 | M76: 0 | N76: 0 | O76: 0 | Q76: 0 | R76: 0 | S76: 0 | T76: 0 | V76: 0 | X76: 0
A77: * GTOS. INFORMATICA | B77: GTOS. INFORMATICA | D77: -899.7 | E77: -571.47 | F77: -634.51 | G77: 0 | H77: 0 | I77: 0 | J77: 0 | K77: 0 | L77: 0 | M77: 0 | N77: 0 | O77: 0 | Q77: -2105.68 | R77: -527.55 | S77: -1578.13 | T77: 299.14321 | V77: -2110.2 | X77: 0
A78: * GTOS. HONORARIOS | B78: GTOS. Honorarios | D78: 0 | E78: 0 | F78: 0 | G78: 0 | H78: 0 | I78: 0 | J78: 0 | K78: 0 | L78: 0 | M78: 0 | N78: 0 | O78: 0 | Q78: 0 | R78: 0 | S78: 0 | T78: 0 | V78: 0 | X78: 0
B79: SUSCRIPCIONES/PUBLICIDAD | D79: 0 | E79: 0 | F79: 0 | G79: 0 | H79: 0 | I79: 0 | J79: 0 | K79: 0 | L79: 0 | M79: 0 | N79: 0 | O79: 0 | Q79: 0 | R79: 0 | S79: 0 | T79: 0 | V79: 0 | X79: 0
A80: * UTILES DE ESCRITORIO | B80: UTILES DE ESCRITORIO | D80: 0 | E80: 0 | F80: 0 | G80: 0 | H80: 0 | I80: 0 | J80: 0 | K80: 0 | L80: 0 | M80: 0 | N80: 0 | O80: 0 | Q80: 0 | R80: 0 | S80: 0 | T80: 0 | V80: 0 | X80: 0
T81: 0 | V81: 0
T82: 0 | V82: 0
T83: 0 | V83: 0
T84: 0 | V84: 0
T85: 0 | V85: 0
B87: M1 - MARGEN DIRECTO | D87: 373019.57 | E87: 3785.63 | F87: 646099.79 | G87: 323231.61 | H87: 225376.77 | I87: 0 | J87: 0 | K87: 0 | L87: 0 | M87: 0 | N87: 0 | O87: 0 | Q87: 1571513.4 | R87: 1240878.4 | S87: 331381.44 | T87: 26.705392 | V87: 1924452.2 | X87: 1628684.4
B89: GTOS. ADMINIST. GENERALES | D89: 0 | E89: 0 | F89: 0 | G89: 0 | H89: 0 | I89: 0 | J89: 0 | K89: 0 | L89: 0 | M89: 0 | N89: 0 | O89: 0 | Q89: 0 | R89: 0 | S89: 0 | T89: 0 | V89: 0 | X89: 0
B90: GTOS . ADMINIST. DEPRECIACION | D90: 0 | E90: 0 | F90: 0 | G90: 0 | H90: 0 | I90: 0 | J90: 0 | K90: 0 | L90: 0 | M90: 0 | N90: 0 | O90: 0 | Q90: 0 | R90: 0 | S90: 0 | T90: 0 | V90: 0 | X90: 0
B91: GTOS.ADM.DIRECTO FLOTA | D91: 0 | E91: 0 | F91: 0 | G91: 0 | H91: 0 | I91: 0 | J91: 0 | K91: 0 | L91: 0 | M91: 0 | N91: 0 | O91: 0 | Q91: 0 | R91: 0 | S91: 0 | T91: 0 | V91: 0 | X91: 0
B93: M3 - MARGEN OPERACIONAL | D93: 373019.57 | E93: 3785.63 | F93: 646099.79 | G93: 323231.61 | H93: 225376.77 | I93: 0 | J93: 0 | K93: 0 | L93: 0 | M93: 0 | N93: 0 | O93: 0 | Q93: 1571513.4 | R93: 1240878.4 | S93: 330634.98 | T93: 26.645236 | V93: 1924452.2 | X93: 1628684.4
B95: OTROS INGR./EGRESOS | D95: -16937.08 | E95: -15298.01 | F95: -16566.18 | G95: -13608.95 | H95: -15332.22 | I95: 0 | J95: 0 | K95: 0 | L95: 0 | M95: 0 | N95: 0 | O95: 0 | Q95: -77742.44 | R95: -93006.9 | S95: 15264.46 | T95: -16.41218 | V95: -188380.58 | X95: -135160.5
A96: * INGRESOS FINANCIEROS | B96: INGRESOS FINANCIEROS | D96: 0 | E96: 0 | F96: 0 | G96: 0 | H96: 0 | I96: 0 | J96: 0 | K96: 0 | L96: 0 | M96: 0 | N96: 0 | O96: 0 | Q96: 0 | R96: 0 | S96: 0 | T96: 0 | V96: 0 | X96: 0
A97: * GASTOS FINANCIEROS | B97: GASTOS FINANCIEROS | D97: -16937.08 | E97: -15298.01 | F97: -16566.18 | G97: -13608.95 | H97: -15332.22 | I97: 0 | J97: 0 | K97: 0 | L97: 0 | M97: 0 | N97: 0 | O97: 0 | Q97: -77742.44 | R97: -93006.9 | S97: 15264.46 | T97: -16.41218 | V97: -188380.58 | X97: -135160.5
B98: ING. (GTOS.) AÑO ANTERIOR | D98: 0 | E98: 0 | F98: 0 | G98: 0 | H98: 0 | I98: 0 | J98: 0 | K98: 0 | L98: 0 | M98: 0 | N98: 0 | O98: 0 | Q98: 0 | R98: 0 | S98: 0 | T98: 0 | V98: 0 | X98: 0
A99: * ING. (GTOS.) GESTION | B99: ING. (GTOS.) GESTION | D99: 0 | E99: 0 | F99: 0 | G99: 0 | H99: 0 | I99: 0 | J99: 0 | K99: 0 | L99: 0 | M99: 0 | N99: 0 | O99: 0 | Q99: 0 | R99: 0 | S99: 0 | T99: 0 | V99: 0 | X99: 0
B100: NPETRAL/PERSEUS | D100: 0 | E100: 0 | F100: 0 | G100: 0 | H100: 0 | I100: 0 | J100: 0 | K100: 0 | L100: 0 | M100: 0 | N100: 0 | O100: 0 | Q100: 0 | R100: 0 | S100: 0 | T100: 0 | V100: 0 | X100: 0
B101: INT.MINORITARIO Y RES.RENADSA | D101: 0 | E101: 0 | F101: 0 | G101: 0 | H101: 0 | I101: 0 | J101: 0 | K101: 0 | L101: 0 | M101: 0 | N101: 0 | O101: 0 | Q101: 0 | R101: 0 | S101: 0 | T101: 0 | V101: 0 | X101: 0
A102: * RESULT. DE TRASLACION/DIF. | B102: RESULT. DE TRASLACION | D102: 0 | E102: 0 | F102: 0 | G102: 0 | H102: 0 | I102: 0 | J102: 0 | K102: 0 | L102: 0 | M102: 0 | N102: 0 | O102: 0 | Q102: 0 | R102: 0 | S102: 0 | T102: 0 | V102: 0 | X102: 0
B104: M4 - RESULTADO ANTES IMPTO | D104: 356082.49 | E104: -11512.38 | F104: 629533.61 | G104: 309622.66 | H104: 210044.55 | I104: 0 | J104: 0 | K104: 0 | L104: 0 | M104: 0 | N104: 0 | O104: 0 | Q104: 1493770.9 | R104: 1147871.5 | S104: 345899.44 | T104: 30.133987 | V104: 1736071.6 | X104: 1493523.9
A106: **** TIME CHARTER EQUIVALENT (TC | B106: TIME CHARTER EQUIVALENT (TCE) | C106: =-IF(C110 = 0,0,C24/C110) -> 0 | D106: 25517.201 | E106: 18230.481 | F106: 35123.126 | G106: 25112.532 | H106: 21435.497 | I106: 0 | J106: 0 | K106: 0 | L106: 0 | M106: 0 | N106: 0 | O106: 0 | Q106: 25219.735 | R106: 38287.002 | S106: -13067.267 | T106: 34.129773 | V106: 19487.498 | X106: 22633.387
A107: ***** COSTO DIA NAVE (DRC) | B107: COSTO DIA NAVE (DRC) | C107: =-IF(C111 = 0, 0,C65/C111) -> 0 | D107: -9451.969 | E107: -13639.143 | F107: -10253.124 | G107: -10170.658 | H107: -10134.101 | I107: 0 | J107: 0 | K107: 0 | L107: 0 | M107: 0 | N107: 0 | O107: 0 | Q107: -10675.7 | R107: -17633.866 | S107: 6958.1659 | T107: -39.459106 | V107: -10152.097 | X107: -7796.7581
A108: ***** COSTO DIA (DRC SIN DIQUE) | B108: COSTO DIA (DRC SIN DIQUE) | C108: =-IF(C111 = 0,0,(C65-C58)/C111) -> 0 | D108: -8146.5445 | E108: -12193.851 | F108: -8947.6997 | G108: -8821.719 | H108: -8828.6765 | I108: 0 | J108: 0 | K108: 0 | L108: 0 | M108: 0 | N108: 0 | O108: 0 | Q108: -9335.695 | R108: -15385.635 | S108: 6049.9401 | T108: -39.322005 | V108: -8821.6367 | X108: -7796.7581
A109: ****** RESULTADO DIARIO | B109: RESULTADO DIARIO | C109: =-IF(C111 = 0, 0,C104/C111) -> 0 | D109: 11486.532 | E109: -411.15643 | F109: 20307.536 | G109: 10320.755 | H109: 6775.6306 | I109: 0 | J109: 0 | K109: 0 | L109: 0 | M109: 0 | N109: 0 | O109: 0 | Q109: 9892.5227 | R109: 12754.128 | S109: -2861.605 | T109: -22.436697 | V109: 4756.3605 | X109: 9890.887
A110: DIAS OPERATIVOS - TIME CHAR | B110: DIAS OPERATIVOS | D110: 31 | E110: 28 | F110: 31 | G110: 30 | H110: 31 | I110: 0 | J110: 0 | K110: 0 | L110: 0 | M110: 0 | N110: 0 | O110: 0 | Q110: 151 | R110: 90 | S110: 61 | T110: 67.777778 | V110: 365 | X110: 151
A111: DIAS OPERATIVOS - COSTO DRC | B111: DIAS DE EXCEPCION | D111: 31 | E111: 28 | F111: 31 | G111: 30 | H111: 31 | I111: 0 | J111: 0 | K111: 0 | L111: 0 | M111: 0 | N111: 0 | O111: 0 | Q111: 151 | R111: 90 | S111: 61 | T111: 67.777778 | V111: 365 | X111: 151
A112: NUMERO DE VIAJES - NAVES | B112: NRO DE VIAJES | D112: 3 | E112: 3 | F112: 3 | G112: 3 | H112: 2 | I112: 0 | J112: 0 | K112: 0 | L112: 0 | M112: 0 | N112: 0 | O112: 0 | Q112: 14 | R112: 0 | S112: 14 | T112: 0 | V112: 0 | X112: 14
B114: EBITDA | D114: 537590.65 | E114: 168454.17 | F114: 810803.72 | G114: 488172.99 | H114: 390264.68 | I114: 0 | J114: 0 | K114: 0 | L114: 0 | M114: 0 | N114: 0 | O114: 0 | Q114: 2395286.2 | R114: 2060243.7 | S114: 335788.93 | T114: 16.298505 | V114: 3890929 | X114: 2238488.7
D117: =+D24/D110 -> 25517.201 | E117: =+E24/E110 -> 18230.481 | F117: =+F24/F110 -> 35123.126 | G117: =+G24/G110 -> 25112.532 | H117: =+H24/H110 -> 21435.497 | I117: =+I24/I110 -> #DIV/0! | J117: =+J24/J110 -> #DIV/0! | K117: =+K24/K110 -> #DIV/0! | ... R117: =+R24/R110 -> 38287.002 | X117: =+X24/X110 -> 22633.387
D118: =+D65/D111 -> -9451.969 | E118: =+E65/E111 -> -13639.143 | F118: =+F65/F111 -> -10253.124 | G118: =+G65/G111 -> -10170.658 | H118: =+H65/H111 -> -10134.101 | I118: =+I65/I111 -> #DIV/0! | J118: =+J65/J111 -> #DIV/0! | K118: =+K65/K111 -> #DIV/0! | ... R118: =+R65/R111 -> -17633.866 | X118: =+X65/X111 -> -7796.7581
D119: =+(D65-D58)/D111 -> -8146.5445 | E119: =+(E65-E58)/E111 -> -12193.851 | F119: =+(F65-F58)/F111 -> -8947.6997 | G119: =+(G65-G58)/G111 -> -8821.719 | H119: =+(H65-H58)/H111 -> -8828.6765 | I119: =+(I65-I58)/I111 -> #DIV/0! | J119: =+(J65-J58)/J111 -> #DIV/0! | K119: =+(K65-K58)/K111 -> #DIV/0! | ... R119: =+(R65-R58)/R111 -> -15385.635 | X119: =+(X65-X58)/X111 -> -7796.7581
D120: =+D106-D117 -> 0 | E120: =+E106-E117 -> 0 | F120: =+F106-F117 -> 0 | G120: =+G106-G117 -> 0 | H120: =+H106-H117 -> 0 | I120: =+I106-I117 -> #DIV/0! | J120: =+J106-J117 -> #DIV/0! | K120: =+K106-K117 -> #DIV/0! | ... R120: =+R106-R117 -> 0 | X120: =+X106-X117 -> 0
D121: =+D107-D118 -> 0 | E121: =+E107-E118 -> 0 | F121: =+F107-F118 -> 0 | G121: =+G107-G118 -> 0 | H121: =+H107-H118 -> 0 | I121: =+I107-I118 -> #DIV/0! | J121: =+J107-J118 -> #DIV/0! | K121: =+K107-K118 -> #DIV/0! | ... R121: =+R107-R118 -> 0 | X121: =+X107-X118 -> 0
D122: =+D108-D119 -> 0 | E122: =+E108-E119 -> 0 | F122: =+F108-F119 -> 0 | G122: =+G108-G119 -> 0 | H122: =+H108-H119 -> 0 | I122: =+I108-I119 -> #DIV/0! | J122: =+J108-J119 -> #DIV/0! | K122: =+K108-K119 -> #DIV/0! | ... R122: =+R108-R119 -> 0 | X122: =+X108-X119 -> 0

Sheet TABLONES GRR3
B2: US$ Dolar | C2: Enero | D2: Febrero | E2: Marzo | F2: Abril | G2: Mayo | H2: Junio | I2: Julio | J2: Agosto | K2: Setiembre | L2: Octubre | M2: Noviembre | N2: Diciembre | O2: Acum. 2026 | P2: Ppto.Acum a 3 | Q2: Variacion | R2: Ppto Anual | S2: % | T2: Ppto Mens | U2: Real A o anterior
B3: ** VENTAS | C3: -1171040.6 | D3: -955778.87 | E3: -1222513.1 | F3: 0 | G3: 0 | H3: 0 | I3: 0 | J3: 0 | K3: 0 | L3: 0 | M3: 0 | N3: 0 | O3: -3349332.5 | P3: -3148785 | Q3: 200547.49 | R3: -11025680 | S3: -6.369 | T3: -1049595 | U3: 0
B4: 704121 FLETES A TERC-NAV P | C4: 0 | D4: 0 | E4: 0 | F4: 0 | G4: 0 | H4: 0 | I4: 0 | J4: 0 | K4: 0 | L4: 0 | M4: 0 | N4: 0 | O4: 0 | P4: -2428785 | Q4: -2428785 | R4: -8635680 | S4: 100 | T4: -809595 | U4: 0
B5: 703213 FLETES A T-NAV PR L | C5: -844069.75 | D5: -808897.03 | E5: -859884.72 | F5: 0 | G5: 0 | H5: 0 | I5: 0 | J5: 0 | K5: 0 | L5: 0 | M5: 0 | N5: 0 | O5: -2512851.5 | P5: 0 | Q5: 2512851.5 | R5: 0 | S5: 0 | T5: 0 | U5: 0
B6: * HIRE | C6: -844069.75 | D6: -808897.03 | E6: -859884.72 | F6: 0 | G6: 0 | H6: 0 | I6: 0 | J6: 0 | K6: 0 | L6: 0 | M6: 0 | N6: 0 | O6: -2512851.5 | P6: -2428785 | Q6: 84066.5 | R6: -8635680 | S6: -3.4613 | T6: -809595 | U6: 0
B7: 704123 DEMORAS | C7: 0 | D7: 0 | E7: 0 | F7: 0 | G7: 0 | H7: 0 | I7: 0 | J7: 0 | K7: 0 | L7: 0 | M7: 0 | N7: 0 | O7: 0 | P7: -540000 | Q7: -540000 | R7: -1750000 | S7: 100 | T7: -180000 | U7: 0
B8: 703115 DEMORAS EXPORTACION | C8: 240599.03 | D8: 13999.95 | E8: -204215.85 | F8: 0 | G8: 0 | H8: 0 | I8: 0 | J8: 0 | K8: 0 | L8: 0 | M8: 0 | N8: 0 | O8: 50383.13 | P8: 0 | Q8: -50383.13 | R8: 0 | S8: 0 | T8: 0 | U8: 0
B9: 703215 DEMORAS -LOCAL | C9: -513722.95 | D9: -99124.6 | E9: -132109.7 | F9: 0 | G9: 0 | H9: 0 | I9: 0 | J9: 0 | K9: 0 | L9: 0 | M9: 0 | N9: 0 | O9: -744957.25 | P9: 0 | Q9: 744957.25 | R9: 0 | S9: 0 | T9: 0 | U9: 0
B10: * DEMORAS | C10: -273123.92 | D10: -85124.65 | E10: -336325.55 | F10: 0 | G10: 0 | H10: 0 | I10: 0 | J10: 0 | K10: 0 | L10: 0 | M10: 0 | N10: 0 | O10: -694574.12 | P10: -540000 | Q10: 154574.12 | R10: -1750000 | S10: -28.6248 | T10: -180000 | U10: 0
B11: 704136 SERV DE ATENC EN PU | C11: 0 | D11: 0 | E11: 0 | F11: 0 | G11: 0 | H11: 0 | I11: 0 | J11: 0 | K11: 0 | L11: 0 | M11: 0 | N11: 0 | O11: 0 | P11: -180000 | Q11: -180000 | R11: -640000 | S11: 100 | T11: -60000 | U11: 0
B12: 703118 SERV ATENC EN PUE E | C12: 20000 | D12: -6000 | E12: 26000 | F12: 0 | G12: 0 | H12: 0 | I12: 0 | J12: 0 | K12: 0 | L12: 0 | M12: 0 | N12: 0 | O12: 40000 | P12: 0 | Q12: -40000 | R12: 0 | S12: 0 | T12: 0 | U12: 0
B13: 703218 SERV ATENC EN PUE L | C13: -73846.9 | D13: -55757.19 | E13: -52302.78 | F13: 0 | G13: 0 | H13: 0 | I13: 0 | J13: 0 | K13: 0 | L13: 0 | M13: 0 | N13: 0 | O13: -181906.87 | P13: 0 | Q13: 181906.87 | R13: 0 | S13: 0 | T13: 0 | U13: 0
B14: * INGRESOS DE PUERTO | C14: -53846.9 | D14: -61757.19 | E14: -26302.78 | F14: 0 | G14: 0 | H14: 0 | I14: 0 | J14: 0 | K14: 0 | L14: 0 | M14: 0 | N14: 0 | O14: -141906.87 | P14: -180000 | Q14: -38093.13 | R14: -640000 | S14: 21.1628 | T14: -60000 | U14: 0
... B125: ******* EBITDA | C125: -537590.65 | D125: -168454.17 | E125: -810803.72 | F125: 0 | G125: 0 | H125: 0 | I125: 0 | J125: 0 | K125: 0 | L125: 0 | M125: 0 | N125: 0 | O125: -1516848.5 | P125: -1247890.5 | Q125: 268958.02 | R125: -3890929 | S125: -21.553 | T125: -412047.57 | U125: 0

Sheet Hoja3
B2: US$ Dolar | C2: Enero | D2: Febrero | E2: Marzo | F2: Abril | G2: Mayo | H2: Junio | I2: Julio | J2: Agosto | K2: Setiembre | L2: Octubre | M2: Noviembre | N2: Diciembre | O2: Acum. 2025 | P2: Ppto.Acum a 11 | Q2: Variacion | R2: Ppto Anual | S2: % | T2: Ppto Mens | U2: Real A o anterior
B3: ** VENTAS | C3: 0 | D3: 0 | E3: 0 | F3: 0 | G3: 0 | H3: 0 | I3: 0 | J3: 0 | K3: 0 | L3: -9188732 | M3: -685632.22 | N3: 0 | O3: -9874364.2 | P3: -9531536.3 | Q3: 342827.83 | R3: -10570994 | S3: -3.5968 | T3: -994882.85 | U3: 0
B4: 704121 FLETES A TERC-NAV P | C4: 0 | D4: 0 | E4: 0 | F4: 0 | G4: 0 | H4: 0 | I4: 0 | J4: 0 | K4: 0 | L4: 0 | M4: 0 | N4: 0 | O4: 0 | P4: -7659375 | Q4: -7659375 | R4: -8535000 | S4: 100 | T4: -814050 | U4: 0
B5: 703213 FLETES A T-NAV PR L | C5: 0 | D5: 0 | E5: 0 | F5: 0 | G5: 0 | H5: 0 | I5: 0 | J5: 0 | K5: 0 | L5: -6495536.3 | M5: -306386.56 | N5: 0 | O5: -6801922.8 | P5: 0 | Q5: 6801922.8 | R5: 0 | S5: 0 | T5: 0 | U5: 0
B6: * HIRE | C6: 0 | D6: 0 | E6: 0 | F6: 0 | G6: 0 | H6: 0 | I6: 0 | J6: 0 | K6: 0 | L6: -6495536.3 | M6: -306386.56 | N6: 0 | O6: -6801922.8 | P6: -7659375 | Q6: -857452.15 | R6: -8535000 | S6: 11.1948 | T6: -814050 | U6: 0
B7: 704123 DEMORAS | C7: 0 | D7: 0 | E7: 0 | F7: 0 | G7: 0 | H7: 0 | I7: 0 | J7: 0 | K7: 0 | L7: 0 | M7: 0 | N7: 0 | O7: 0 | P7: -1329161.4 | Q7: -1329161.4 | R7: -1449994.2 | S7: 100 | T7: -120832.85 | U7: 0
B8: 703115 DEMORAS EXPORTACION | C8: 0 | D8: 0 | E8: 0 | F8: 0 | G8: 0 | H8: 0 | I8: 0 | J8: 0 | K8: 0 | L8: -121922.94 | M8: 110941.22 | N8: 0 | O8: -10981.72 | P8: 0 | Q8: 10981.72 | R8: 0 | S8: 0 | T8: 0 | U8: 0
B9: 703215 DEMORAS -LOCAL | C9: 0 | D9: 0 | E9: 0 | F9: 0 | G9: 0 | H9: 0 | I9: 0 | J9: 0 | K9: 0 | L9: -2232862.1 | M9: -451389.86 | N9: 0 | O9: -2684252 | P9: 0 | Q9: 2684252 | R9: 0 | S9: 0 | T9: 0 | U9: 0
B10: * DEMORAS | C10: 0 | D10: 0 | E10: 0 | F10: 0 | G10: 0 | H10: 0 | I10: 0 | J10: 0 | K10: 0 | L10: -2354785 | M10: -340448.64 | N10: 0 | O10: -2695233.7 | P10: -1329161.4 | Q10: 1366072.3 | R10: -1449994.2 | S10: -102.777 | T10: -120832.85 | U10: 0
B11: 704136 SERV DE ATENC EN PU | C11: 0 | D11: 0 | E11: 0 | F11: 0 | G11: 0 | H11: 0 | I11: 0 | J11: 0 | K11: 0 | L11: 0 | M11: 0 | N11: 0 | O11: 0 | P11: -543000 | Q11: -543000 | R11: -586000 | S11: 100 | T11: -60000 | U11: 0
B12: 703118 SERV ATENC EN PUE E | C12: 0 | D12: 0 | E12: 0 | F12: 0 | G12: 0 | H12: 0 | I12: 0 | J12: 0 | K12: 0 | L12: 7510 | M12: -9904 | N12: 0 | O12: -2394 | P12: 0 | Q12: 2394 | R12: 0 | S12: 0 | T12: 0 | U12: 0
B13: 703218 SERV ATENC EN PUE L | C13: 0 | D13: 0 | E13: 0 | F13: 0 | G13: 0 | H13: 0 | I13: 0 | J13: 0 | K13: 0 | L13: -345920.63 | M13: -28893.02 | N13: 0 | O13: -374813.65 | P13: 0 | Q13: 374813.65 | R13: 0 | S13: 0 | T13: 0 | U13: 0
B14: * INGRESOS DE PUERTO | C14: 0 | D14: 0 | E14: 0 | F14: 0 | G14: 0 | H14: 0 | I14: 0 | J14: 0 | K14: 0 | L14: -338410.63 | M14: -38797.02 | N14: 0 | O14: -377207.65 | P14: -543000 | Q14: -165792.35 | R14: -586000 | S14: 30.5327 | T14: -60000 | U14: 0
... B134: ******* EBITDA | C134: 0 | D134: 0 | E134: 0 | F134: 0 | G134: 0 | H134: 0 | I134: 0 | J134: 0 | K134: 0 | L134: -3894595.4 | M134: -225060.95 | N134: 0 | O134: -4119656.3 | P134: -3753646.6 | Q134: 366009.72 | R134: -4214174.1 | S134: -9.7508 | T134: -456319.51 | U134: 0

Sheet Flota Contratada
Z1: =+PETRAL!Z1 -> 5
B2: Control Presupuestal
B3: =+PETRAL!B3 -> 46143 | D3: FLOTA CONTRATADA
Q5: REAL | R5: PRESUP. | V5: PPTO. | X5: Real Acum.
B6: (US$ Dólares) | D6: ENE | E6: FEB | F6: MAR | G6: ABR | H6: MAY | I6: JUN | J6: JUL | K6: AGO | L6: SET | M6: OCT | N6: NOV | O6: DIC | Q6: ACUMUL. | R6: ACUMUL. | S6: VARIACION | T6: % | V6: ANUAL | X6: =+PETRAL!X6 -> 45778
B8: VENTAS | D8: 0 | E8: 0 | F8: 0 | G8: 0 | H8: 472589.52 | I8: 0 | J8: 0 | K8: 0 | L8: 0 | M8: 0 | N8: 0 | O8: 0 | Q8: 472589.52 | R8: 0 | S8: 472589.52 | T8: 0 | V8: 0 | X8: 0
A9: * HIRE | B9: HIRE | D9: 0 | E9: 0 | F9: 0 | G9: 0 | H9: 362131.63 | I9: 0 | J9: 0 | K9: 0 | L9: 0 | M9: 0 | N9: 0 | O9: 0 | Q9: 362131.63 | R9: 0 | S9: 362131.63 | T9: 0 | V9: 0 | X9: 0
B10: VENTA DE TERCEROS | D10: 0 | E10: 0 | F10: 0 | G10: 0 | H10: 0 | I10: 0 | J10: 0 | K10: 0 | L10: 0 | M10: 0 | N10: 0 | O10: 0 | Q10: 0 | R10: 0 | S10: 0 | T10: 0 | V10: 0 | X10: 0
A11: * DEMORAS | B11: DEMORAS | D11: 0 | E11: 0 | F11: 0 | G11: 0 | H11: 110457.89 | I11: 0 | J11: 0 | K11: 0 | L11: 0 | M11: 0 | N11: 0 | O11: 0 | Q11: 110457.89 | R11: 0 | S11: 110457.89 | T11: 0 | V11: 0 | X11: 0
A12: * INGRESOS DE PUERTO | B12: INGRESOS DE PUERTO | D12: 0 | E12: 0 | F12: 0 | G12: 0 | H12: 0 | I12: 0 | J12: 0 | K12: 0 | L12: 0 | M12: 0 | N12: 0 | O12: 0 | Q12: 0 | R12: 0 | S12: 0 | T12: 0 | V12: 0 | X12: 0
A13: * OTROS INGRESOS | B13: OTROS INGRESOS | D13: 0 | E13: 0 | F13: 0 | G13: 0 | H13: 0 | I13: 0 | J13: 0 | K13: 0 | L13: 0 | M13: 0 | N13: 0 | O13: 0 | Q13: 0 | R13: 0 | S13: 0 | T13: 0 | V13: 0 | X13: 0
B15: COSTOS DIRECTOS | D15: 0 | E15: 0 | F15: 0 | G15: 0 | H15: -112500 | I15: 0 | J15: 0 | K15: 0 | L15: 0 | M15: 0 | N15: 0 | O15: 0 | Q15: -112500 | R15: 0 | S15: -112500 | T15: 0 | V15: 0 | X15: 16617.69
A16: * COMBUSTIBLE | B16: COMBUSTIBLE | D16: 0 | E16: 0 | F16: 0 | G16: 0 | H16: 0 | I16: 0 | J16: 0 | K16: 0 | L16: 0 | M16: 0 | N16: 0 | O16: 0 | Q16: 0 | R16: 0 | S16: 0 | T16: 0 | V16: 0 | X16: 0
A17: * GASTOS DE PUERTO | B17: GASTOS DE PUERTO | D17: 0 | E17: 0 | F17: 0 | G17: 0 | H17: 0 | I17: 0 | J17: 0 | K17: 0 | L17: 0 | M17: 0 | N17: 0 | O17: 0 | Q17: 0 | R17: 0 | S17: 0 | T17: 0 | V17: 0 | X17: 16617.69
A18: * COSTOS DEMORAS | B18: COSTOS DE DEMORA | D18: 0 | E18: 0 | F18: 0 | G18: 0 | H18: -112500 | I18: 0 | J18: 0 | K18: 0 | L18: 0 | M18: 0 | N18: 0 | O18: 0 | Q18: -112500 | R18: 0 | S18: -112500 | T18: 0 | V18: 0 | X18: 0
B19: COMISIONES VARIAS | D19: 0 | E19: 0 | F19: 0 | G19: 0 | H19: 0 | I19: 0 | J19: 0 | K19: 0 | L19: 0 | M19: 0 | N19: 0 | O19: 0 | Q19: 0 | R19: 0 | S19: 0 | T19: 0 | V19: 0 | X19: 0
B20: OTROS COSTOS DIRECTOS | D20: 0 | E20: 0 | F20: 0 | G20: 0 | H20: 0 | I20: 0 | J20: 0 | K20: 0 | L20: 0 | M20: 0 | N20: 0 | O20: 0 | Q20: 0 | R20: 0 | S20: 0 | T20: 0 | V20: 0 | X20: 0
B24: TIME CHARTER EQUIVALENT | D24: 0 | E24: 0 | F24: 0 | G24: 0 | H24: 360089.52 | I24: 0 | J24: 0 | K24: 0 | L24: 0 | M24: 0 | N24: 0 | O24: 0 | Q24: 360089.52 | R24: 0 | S24: 360089.52 | T24: 0 | V24: 0 | X24: 16617.69
A26: * COSTOS DE HIRE | B26: COSTO DE ARRIENDO NAVES | D26: 0 | E26: 0 | F26: 0 | G26: 0 | H26: -417912.29 | I26: 0 | J26: 0 | K26: 0 | L26: 0 | M26: 0 | N26: 0 | O26: 0 | Q26: -417912.29 | R26: 0 | S26: -417912.29 | T26: 0 | V26: 0 | X26: 0
B28: MARGEN BRUTO | D28: 0 | E28: 0 | F28: 0 | G28: 0 | H28: -57822.77 | I28: 0 | J28: 0 | K28: 0 | L28: 0 | M28: 0 | N28: 0 | O28: 0 | Q28: -57822.77 | R28: 0 | S28: -57822.77 | T28: 0 | V28: 0 | X28: 16617.69
B30: GTOS. PERSONAL A BORDO | D30: 0 | E30: 0 | F30: 0 | G30: 0 | H30: 0 | I30: 0 | J30: 0 | K30: 0 | L30: 0 | M30: 0 | N30: 0 | O30: 0 | Q30: 0 | R30: 0 | S30: 0 | T30: 0 | V30: 0 | X30: 0
B31: GASTOS DE PERSONAL | D31: 0 | E31: 0 | F31: 0 | G31: 0 | H31: 0 | I31: 0 | J31: 0 | K31: 0 | L31: 0 | M31: 0 | N31: 0 | O31: 0 | Q31: 0 | R31: 0 | S31: 0 | T31: 0 | V31: 0 | X31: 0
B33: SUELDOS | D33: 0 | E33: 0 | F33: 0 | G33: 0 | H33: 0 | I33: 0 | J33: 0 | K33: 0 | L33: 0 | M33: 0 | N33: 0 | O33: 0 | Q33: 0 | R33: 0 | S33: 0 | T33: 0 | V33: 0 | X33: 0
B34: VACACIONES | D34: 0 | E34: 0 | F34: 0 | G34: 0 | H34: 0 | I34: 0 | J34: 0 | K34: 0 | L34: 0 | M34: 0 | N34: 0 | O34: 0 | Q34: 0 | R34: 0 | S34: 0 | T34: 0 | V34: 0 | X34: 0
B35: GRATIFICACIONES | D35: 0 | E35: 0 | F35: 0 | G35: 0 | H35: 0 | I35: 0 | J35: 0 | K35: 0 | L35: 0 | M35: 0 | N35: 0 | O35: 0 | Q35: 0 | R35: 0 | S35: 0 | T35: 0 | V35: 0 | X35: 0
B36: BENEFICIOS SOCIALES | D36: 0 | E36: 0 | F36: 0 | G36: 0 | H36: 0 | I36: 0 | J36: 0 | K36: 0 | L36: 0 | M36: 0 | N36: 0 | O36: 0 | Q36: 0 | R36: 0 | S36: 0 | T36: 0 | V36: 0 | X36: 0
B37: ESSALUD | D37: 0 | E37: 0 | F37: 0 | G37: 0 | H37: 0 | I37: 0 | J37: 0 | K37: 0 | L37: 0 | M37: 0 | N37: 0 | O37: 0 | Q37: 0 | R37: 0 | S37: 0 | T37: 0 | V37: 0 | X37: 0
B38: E.P.S. /GASTOS MEDICOS | D38: 0 | E38: 0 | F38: 0 | G38: 0 | H38: 0 | I38: 0 | J38: 0 | K38: 0 | L38: 0 | M38: 0 | N38: 0 | O38: 0 | Q38: 0 | R38: 0 | S38: 0 | T38: 0 | V38: 0 | X38: 0
B39: VESTUARIO | D39: 0 | E39: 0 | F39: 0 | G39: 0 | H39: 0 | I39: 0 | J39: 0 | K39: 0 | L39: 0 | M39: 0 | N39: 0 | O39: 0 | Q39: 0 | R39: 0 | S39: 0 | T39: 0 | V39: 0 | X39: 0
B40: CAPACITACION | D40: 0 | E40: 0 | F40: 0 | G40: 0 | H40: 0 | I40: 0 | J40: 0 | K40: 0 | L40: 0 | M40: 0 | N40: 0 | O40: 0 | Q40: 0 | R40: 0 | S40: 0 | T40: 0 | V40: 0 | X40: 0
B41: TRASLADO DE TRIPULACION | D41: 0 | E41: 0 | F41: 0 | G41: 0 | H41: 0 | I41: 0 | J41: 0 | K41: 0 | L41: 0 | M41: 0 | N41: 0 | O41: 0 | Q41: 0 | R41: 0 | S41: 0 | T41: 0 | V41: 0 | X41: 0
... B60: CASCO Y MAQUINA | D60: 0 | E60: 0 | F60: 0 | G60: 0 | H60: 0 | I60: 0 | J60: 0 | K60: 0 | L60: 0 | M60: 0 | N60: 0 | O60: 0 | Q60: 0 | R60: 0 | S60: 0 | T60: 0 | V60: 0 | X60: 0
A61: * PANDI | B61: PANDI | D61: 0 | E61: 0 | F61: 0 | G61: 0 | H61: 0 | I61: 0 | J61: 0 | K61: 0 | L61: 0 | M61: 0 | N61: 0 | O61: 0 | Q61: 0 | R61: 0 | S61: 0 | T61: 0 | V61: 0 | X61: 0
B62: DEDUCIBLES Y OTROS | D62: 0 | E62: 0 | F62: 0 | G62: 0 | H62: 0 | I62: 0 | J62: 0 | K62: 0 | L62: 0 | M62: 0 | N62: 0 | O62: 0 | Q62: 0 | R62: 0 | S62: 0 | T62: 0 | V62: 0 | X62: 0
X63: 0
B64: OPERATING COST | D64: 0 | E64: 0 | F64: 0 | G64: 0 | H64: 0 | I64: 0 | J64: 0 | K64: 0 | L64: 0 | M64: 0 | N64: 0 | O64: 0 | Q64: 0 | R64: 0 | S64: 0 | T64: 0 | V64: 0 | X64: 0
B66: BARE BOAT EQUIVALENT | D66: 0 | E66: 0 | F66: 0 | G66: 0 | H66: 360089.52 | I66: 0 | J66: 0 | K66: 0 | L66: 0 | M66: 0 | N66: 0 | O66: 0 | Q66: 360089.52 | R66: 0 | S66: 360089.52 | T66: 0 | V66: 0 | X66: 16617.69
B68: DEPRECIACION NAVES | D68: 0 | E68: 0 | F68: 0 | G68: 0 | H68: 0 | I68: 0 | J68: 0 | K68: 0 | L68: 0 | M68: 0 | N68: 0 | O68: 0 | Q68: 0 | R68: 0 | S68: 0 | T68: 0 | V68: 0 | X68: 0
B69: COSTO IGV | D69: 0 | E69: 0 | F69: 0 | G69: 0 | H69: 0 | I69: 0 | J69: 0 | K69: 0 | L69: 0 | M69: 0 | N69: 0 | O69: 0 | Q69: 0 | R69: 0 | S69: 0 | T69: 0 | V69: 0 | X69: 0
A73: * GTOS. ADMINIST. NAVE | B73: GTOS. ADMINISTRAT. NAVE | D73: 0 | E73: 0 | F73: 0 | G73: 0 | H73: 0 | I73: 0 | J73: 0 | K73: 0 | L73: 0 | M73: 0 | N73: 0 | O73: 0 | Q73: 0 | R73: 0 | S73: 0 | T73: 0 | V73: 0 | X73: 0
B74: GTOS. INFORMATICA | D74: 0 | E74: 0 | F74: 0 | G74: 0 | H74: 0 | I74: 0 | J74: 0 | K74: 0 | L74: 0 | M74: 0 | N74: 0 | O74: 0 | Q74: 0 | R74: 0 | S74: 0 | T74: 0 | V74: 0 | X74: 0
B75: GTOS. Honorarios | D75: 0 | E75: 0 | F75: 0 | G75: 0 | H75: 0 | I75: 0 | J75: 0 | K75: 0 | L75: 0 | M75: 0 | N75: 0 | O75: 0 | Q75: 0 | R75: 0 | S75: 0 | T75: 0 | V75: 0 | X75: 0
B76: SUSCRIPCIONES/PUBLICIDAD | D76: 0 | E76: 0 | F76: 0 | G76: 0 | H76: 0 | I76: 0 | J76: 0 | K76: 0 | L76: 0 | M76: 0 | N76: 0 | O76: 0 | Q76: 0 | R76: 0 | S76: 0 | T76: 0 | V76: 0 | X76: 0
B77: UTILES DE ESCRITORIO | D77: 0 | E77: 0 | F77: 0 | G77: 0 | H77: 0 | I77: 0 | J77: 0 | K77: 0 | L77: 0 | M77: 0 | N77: 0 | O77: 0 | Q77: 0 | R77: 0 | S77: 0 | T77: 0 | V77: 0 | X77: 0
B79: GASTOS DE REPRESENTACION | Q79: 0 | S79: 0 | T79: 0 | V79: 0 | X79: 0
B86: M1 - MARGEN DIRECTO | D86: 0 | E86: 0 | F86: 0 | G86: 0 | H86: -57822.77 | I86: 0 | J86: 0 | K86: 0 | L86: 0 | M86: 0 | N86: 0 | O86: 0 | Q86: -57822.77 | R86: 0 | S86: -57822.77 | T86: 0 | V86: 0 | X86: 16617.69
B88: GTOS. ADMINIST. GENERALES | D88: 0 | E88: 0 | F88: 0 | G88: 0 | H88: 0 | I88: 0 | J88: 0 | K88: 0 | L88: 0 | M88: 0 | N88: 0 | O88: 0 | Q88: 0 | R88: 0 | S88: 0 | T88: 0 | V88: 0 | X88: 0
B89: GTOS . ADMINIST. DEPRECIACION | D89: 0 | E89: 0 | F89: 0 | G89: 0 | H89: 0 | I89: 0 | J89: 0 | K89: 0 | L89: 0 | M89: 0 | N89: 0 | O89: 0 | Q89: 0 | R89: 0 | S89: 0 | T89: 0 | V89: 0 | X89: 0
B92: M3 - MARGEN OPERACIONAL. | D92: 0 | E92: 0 | F92: 0 | G92: 0 | H92: -57822.77 | I92: 0 | J92: 0 | K92: 0 | L92: 0 | M92: 0 | N92: 0 | O92: 0 | P92: 0 | Q92: -57822.77 | R92: 0 | S92: -57822.77 | T92: 0 | V92: 0 | X92: 16617.69
B94: OTROS INGR./EGRESOS | D94: 0 | E94: 0 | F94: 0 | G94: 0 | H94: 0 | I94: 0 | J94: 0 | K94: 0 | L94: 0 | M94: 0 | N94: 0 | O94: 0 | Q94: 0 | R94: 0 | S94: 0 | T94: 0 | V94: 0 | X94: 0
B95: INGRESOS FINANCIEROS | D95: 0 | E95: 0 | F95: 0 | G95: 0 | H95: 0 | I95: 0 | J95: 0 | K95: 0 | L95: 0 | M95: 0 | N95: 0 | O95: 0 | Q95: 0 | R95: 0 | S95: 0 | T95: 0 | V95: 0 | X95: 0
B96: GASTOS FINANCIEROS | D96: 0 | E96: 0 | F96: 0 | G96: 0 | H96: 0 | I96: 0 | J96: 0 | K96: 0 | L96: 0 | M96: 0 | N96: 0 | O96: 0 | Q96: 0 | R96: 0 | S96: 0 | T96: 0 | V96: 0 | X96: 0
B97: ING. (GTOS.) AÑO ANTERIOR | D97: 0 | E97: 0 | F97: 0 | G97: 0 | H97: 0 | I97: 0 | J97: 0 | K97: 0 | L97: 0 | M97: 0 | N97: 0 | O97: 0 | Q97: 0 | R97: 0 | S97: 0 | T97: 0 | V97: 0 | X97: 0
B98: ING. (GTOS.) GESTION | D98: 0 | E98: 0 | F98: 0 | G98: 0 | H98: 0 | I98: 0 | J98: 0 | K98: 0 | L98: 0 | M98: 0 | N98: 0 | O98: 0 | Q98: 0 | R98: 0 | S98: 0 | T98: 0 | V98: 0 | X98: 0
B99: INT.MINORITARIO Y RES.RENADSA | D99: 0 | E99: 0 | F99: 0 | G99: 0 | H99: 0 | I99: 0 | J99: 0 | K99: 0 | L99: 0 | M99: 0 | N99: 0 | O99: 0 | Q99: 0 | R99: 0 | S99: 0 | T99: 0 | V99: 0 | X99: 0
B100: RESULT. DE TRASLACION/DIF. CAMBIO | D100: 0 | E100: 0 | F100: 0 | G100: 0 | H100: 0 | I100: 0 | J100: 0 | K100: 0 | L100: 0 | M100: 0 | N100: 0 | O100: 0 | Q100: 0 | R100: 0 | S100: 0 | T100: 0 | V100: 0 | X100: 0
B103: M4 - RESULTADO ANTES IMPTO. | D103: 0 | E103: 0 | F103: 0 | G103: 0 | H103: -57822.77 | I103: 0 | J103: 0 | K103: 0 | L103: 0 | M103: 0 | N103: 0 | O103: 0 | Q103: -57822.77 | R103: 0 | S103: -57822.77 | T103: 0 | V103: 0 | X103: 16617.69
A105: 5000 | B105: TIME CHARTER EQUIVALENT (TCE) | D105: 0 | E105: 0 | F105: 0 | G105: 0 | H105: 0 | I105: 0 | J105: 0 | K105: 0 | L105: 0 | M105: 0 | N105: 0 | O105: 0 | Q105: 0 | R105: 0 | S105: 0 | T105: 0 | V105: 0 | X105: 0
A106: 5001 | B106: COSTO DIA NAVE (DRC) | D106: 0 | E106: 0 | F106: 0 | G106: 0 | H106: 0 | I106: 0 | J106: 0 | K106: 0 | L106: 0 | M106: 0 | N106: 0 | O106: 0 | Q106: 0 | R106: 0 | S106: 0 | T106: 0 | V106: 0 | X106: 0
A107: 5002 | B107: COSTO DIA (DRC SIN DIQUE) | D107: 0 | E107: 0 | F107: 0 | G107: 0 | H107: 0 | I107: 0 | J107: 0 | K107: 0 | L107: 0 | M107: 0 | N107: 0 | O107: 0 | Q107: 0 | R107: 0 | S107: 0 | T107: 0 | V107: 0 | X107: 0
A108: 5003 | B108: RESULTADO DIARIO | D108: 0 | E108: 0 | F108: 0 | G108: 0 | H108: 0 | I108: 0 | J108: 0 | K108: 0 | L108: 0 | M108: 0 | N108: 0 | O108: 0 | Q108: 0 | R108: 0 | S108: 0 | T108: 0 | V108: 0 | X108: 0
A109: 5006 | B109: DIAS OFF-HIRE | D109: 0 | E109: 0 | F109: 0 | G109: 0 | H109: 0 | I109: 0 | J109: 0 | K109: 0 | L109: 0 | M109: 0 | N109: 0 | O109: 0 | Q109: 0 | R109: 0 | S109: 0 | T109: 0 | V109: 0 | X109: 0
A110: 5007 | B110: NRO DE FAENAS | D110: 0 | E110: 0 | F110: 0 | G110: 0 | H110: 0 | I110: 0 | J110: 0 | K110: 0 | L110: 0 | M110: 0 | N110: 0 | O110: 0 | Q110: 0 | R110: 0 | S110: 0 | T110: 0 | V110: 0 | X110: 0
A111: 5008 | B111: NRO DE VIAJES | D111: 0 | E111: 0 | F111: 0 | G111: 0 | H111: 0 | I111: 0 | J111: 0 | K111: 0 | L111: 0 | M111: 0 | N111: 0 | O111: 0 | Q111: 0 | R111: 0 | S111: 0 | T111: 0 | V111: 0 | X111: 0
B113: EBITDA | D113: 0 | E113: 0 | F113: 0 | G113: 0 | H113: -57822.77 | I113: 0 | J113: 0 | K113: 0 | L113: 0 | M113: 0 | N113: 0 | O113: 0 | Q113: -57822.77 | R113: 0 | S113: -57822.77 | T113: 0 | V113: 0 | X113: 16617.69
H114: SPCC: Huemul

Sheet FLOTA CONTRATADA GRR3
B2: US$ Dólar | C2: Enero | D2: Febrero | E2: Marzo | F2: Abril | G2: Mayo | H2: Junio | I2: Julio | J2: Agosto | K2: Setiembre | L2: Octubre | M2: Noviembre | N2: Diciembre | O2: Acum. 2025 | P2: Ppto.Acum a 10 | Q2: Variación | R2: Ppto Anual | S2: % | T2: Ppto Mensual | U2: Real Año anterior
B3: ** VENTAS | C3: 0 | D3: 0 | E3: 0 | F3: 0 | G3: 0 | H3: 0 | I3: 0 | J3: 0 | K3: 0 | L3: 0 | M3: =+_xlfn.XLOOKUP($B3,Hoja4!$B:$B,Hoja4!M:M,0) -> 0 | N3: =+_xlfn.XLOOKUP($B3,Hoja4!$B:$B,Hoja4!N:N,0) -> 0 | O3: =+_xlfn.XLOOKUP($B3,Hoja4!$B:$B,Hoja4!O:O,0) -> 0 | P3: =+_xlfn.XLOOKUP($B3,Hoja4!$B:$B,Hoja4!P:P,0) -> 0 | Q3: =+_xlfn.XLOOKUP($B3,Hoja4!$B:$B,Hoja4!Q:Q,0) -> 0 | R3: =+_xlfn.XLOOKUP($B3,Hoja4!$B:$B,Hoja4!R:R,0) -> 0 | S3: =+_xlfn.XLOOKUP($B3,Hoja4!$B:$B,Hoja4!S:S,0) -> 0 | T3: =+_xlfn.XLOOKUP($B3,Hoja4!$B:$B,Hoja4!T:T,0) -> 0 | U3: -4275156.7
B4: 703114 FLETES A T-NAV CO E | C4: 0 | D4: 0 | E4: 0 | F4: 0 | G4: 0 | H4: 0 | I4: 0 | J4: 0 | K4: 0 | L4: 0 | M4: =+_xlfn.XLOOKUP($B4,Hoja4!$B:$B,Hoja4!M:M,0) -> 0 | N4: =+_xlfn.XLOOKUP($B4,Hoja4!$B:$B,Hoja4!N:N,0) -> 0 | O4: =+_xlfn.XLOOKUP($B4,Hoja4!$B:$B,Hoja4!O:O,0) -> 0 | P4: =+_xlfn.XLOOKUP($B4,Hoja4!$B:$B,Hoja4!P:P,0) -> 0 | Q4: =+_xlfn.XLOOKUP($B4,Hoja4!$B:$B,Hoja4!Q:Q,0) -> 0 | R4: =+_xlfn.XLOOKUP($B4,Hoja4!$B:$B,Hoja4!R:R,0) -> 0 | S4: =+_xlfn.XLOOKUP($B4,Hoja4!$B:$B,Hoja4!S:S,0) -> 0 | T4: =+_xlfn.XLOOKUP($B4,Hoja4!$B:$B,Hoja4!T:T,0) -> 0 | U4: -2311707.6
B5: 703214 FLETES A T-NAV CO L | C5: 0 | D5: 0 | E5: 0 | F5: 0 | G5: 0 | H5: 0 | I5: 0 | J5: 0 | K5: 0 | L5: 0 | M5: =+_xlfn.XLOOKUP($B5,Hoja4!$B:$B,Hoja4!M:M,0) -> 0 | N5: =+_xlfn.XLOOKUP($B5,Hoja4!$B:$B,Hoja4!N:N,0) -> 0 | O5: =+_xlfn.XLOOKUP($B5,Hoja4!$B:$B,Hoja4!O:O,0) -> 0 | P5: =+_xlfn.XLOOKUP($B5,Hoja4!$B:$B,Hoja4!P:P,0) -> 0 | Q5: =+_xlfn.XLOOKUP($B5,Hoja4!$B:$B,Hoja4!Q:Q,0) -> 0 | R5: =+_xlfn.XLOOKUP($B5,Hoja4!$B:$B,Hoja4!R:R,0) -> 0 | S5: =+_xlfn.XLOOKUP($B5,Hoja4!$B:$B,Hoja4!S:S,0) -> 0 | T5: =+_xlfn.XLOOKUP($B5,Hoja4!$B:$B,Hoja4!T:T,0) -> 0 | U5: 0
B6: * VENTAS TERCEROS | C6: 0 | D6: 0 | E6: 0 | F6: 0 | G6: 0 | H6: 0 | I6: 0 | J6: 0 | K6: 0 | L6: 0 | M6: =+_xlfn.XLOOKUP($B6,Hoja4!$B:$B,Hoja4!M:M,0) -> 0 | N6: =+_xlfn.XLOOKUP($B6,Hoja4!$B:$B,Hoja4!N:N,0) -> 0 | O6: =+_xlfn.XLOOKUP($B6,Hoja4!$B:$B,Hoja4!O:O,0) -> 0 | P6: =+_xlfn.XLOOKUP($B6,Hoja4!$B:$B,Hoja4!P:P,0) -> 0 | Q6: =+_xlfn.XLOOKUP($B6,Hoja4!$B:$B,Hoja4!Q:Q,0) -> 0 | R6: =+_xlfn.XLOOKUP($B6,Hoja4!$B:$B,Hoja4!R:R,0) -> 0 | S6: =+_xlfn.XLOOKUP($B6,Hoja4!$B:$B,Hoja4!S:S,0) -> 0 | T6: =+_xlfn.XLOOKUP($B6,Hoja4!$B:$B,Hoja4!T:T,0) -> 0 | U6: -2311707.6
B7: 703115 DEMORAS EXPORTACION | C7: 0 | D7: 0 | E7: 0 | F7: 0 | G7: 0 | H7: 0 | I7: 0 | J7: 0 | K7: 0 | L7: 0 | M7: =+_xlfn.XLOOKUP($B7,Hoja4!$B:$B,Hoja4!M:M,0) -> 0 | N7: =+_xlfn.XLOOKUP($B7,Hoja4!$B:$B,Hoja4!N:N,0) -> 0 | O7: =+_xlfn.XLOOKUP($B7,Hoja4!$B:$B,Hoja4!O:O,0) -> 0 | P7: =+_xlfn.XLOOKUP($B7,Hoja4!$B:$B,Hoja4!P:P,0) -> 0 | Q7: =+_xlfn.XLOOKUP($B7,Hoja4!$B:$B,Hoja4!Q:Q,0) -> 0 | R7: =+_xlfn.XLOOKUP($B7,Hoja4!$B:$B,Hoja4!R:R,0) -> 0 | S7: =+_xlfn.XLOOKUP($B7,Hoja4!$B:$B,Hoja4!S:S,0) -> 0 | T7: =+_xlfn.XLOOKUP($B7,Hoja4!$B:$B,Hoja4!T:T,0) -> 0 | U7: 113655
B8: 703215 DEMORAS -LOCAL | C8: 0 | D8: 0 | E8: 0 | F8: 0 | G8: 0 | H8: 0 | I8: 0 | J8: 0 | K8: 0 | L8: 0 | M8: =+_xlfn.XLOOKUP($B8,Hoja4!$B:$B,Hoja4!M:M,0) -> 0 | N8: =+_xlfn.XLOOKUP($B8,Hoja4!$B:$B,Hoja4!N:N,0) -> 0 | O8: =+_xlfn.XLOOKUP($B8,Hoja4!$B:$B,Hoja4!O:O,0) -> 0 | P8: =+_xlfn.XLOOKUP($B8,Hoja4!$B:$B,Hoja4!P:P,0) -> 0 | Q8: =+_xlfn.XLOOKUP($B8,Hoja4!$B:$B,Hoja4!Q:Q,0) -> 0 | R8: =+_xlfn.XLOOKUP($B8,Hoja4!$B:$B,Hoja4!R:R,0) -> 0 | S8: =+_xlfn.XLOOKUP($B8,Hoja4!$B:$B,Hoja4!S:S,0) -> 0 | T8: =+_xlfn.XLOOKUP($B8,Hoja4!$B:$B,Hoja4!T:T,0) -> 0 | U8: -1755765
B9: * DEMORAS | C9: 0 | D9: 0 | E9: 0 | F9: 0 | G9: 0 | H9: 0 | I9: 0 | J9: 0 | K9: 0 | L9: 0 | M9: =+_xlfn.XLOOKUP($B9,Hoja4!$B:$B,Hoja4!M:M,0) -> 0 | N9: =+_xlfn.XLOOKUP($B9,Hoja4!$B:$B,Hoja4!N:N,0) -> 0 | O9: =+_xlfn.XLOOKUP($B9,Hoja4!$B:$B,Hoja4!O:O,0) -> 0 | P9: =+_xlfn.XLOOKUP($B9,Hoja4!$B:$B,Hoja4!P:P,0) -> 0 | Q9: =+_xlfn.XLOOKUP($B9,Hoja4!$B:$B,Hoja4!Q:Q,0) -> 0 | R9: =+_xlfn.XLOOKUP($B9,Hoja4!$B:$B,Hoja4!R:R,0) -> 0 | S9: =+_xlfn.XLOOKUP($B9,Hoja4!$B:$B,Hoja4!S:S,0) -> 0 | T9: =+_xlfn.XLOOKUP($B9,Hoja4!$B:$B,Hoja4!T:T,0) -> 0 | U9: -1642110
B10: 703118 SERV ATENC EN PUE E | C10: 0 | D10: 0 | E10: 0 | F10: 0 | G10: 0 | H10: 0 | I10: 0 | J10: 0 | K10: 0 | L10: 0 | M10: =+_xlfn.XLOOKUP($B10,Hoja4!$B:$B,Hoja4!M:M,0) -> 0 | N10: =+_xlfn.XLOOKUP($B10,Hoja4!$B:$B,Hoja4!N:N,0) -> 0 | O10: =+_xlfn.XLOOKUP($B10,Hoja4!$B:$B,Hoja4!O:O,0) -> 0 | P10: =+_xlfn.XLOOKUP($B10,Hoja4!$B:$B,Hoja4!P:P,0) -> 0 | Q10: =+_xlfn.XLOOKUP($B10,Hoja4!$B:$B,Hoja4!Q:Q,0) -> 0 | R10: =+_xlfn.XLOOKUP($B10,Hoja4!$B:$B,Hoja4!R:R,0) -> 0 | S10: =+_xlfn.XLOOKUP($B10,Hoja4!$B:$B,Hoja4!S:S,0) -> 0 | T10: =+_xlfn.XLOOKUP($B10,Hoja4!$B:$B,Hoja4!T:T,0) -> 0 | U10: 32000
B11: 703218 SERV ATENC EN PUE L | C11: 0 | D11: 0 | E11: 0 | F11: 0 | G11: 0 | H11: 0 | I11: 0 | J11: 0 | K11: 0 | L11: 0 | M11: =+_xlfn.XLOOKUP($B11,Hoja4!$B:$B,Hoja4!M:M,0) -> 0 | N11: =+_xlfn.XLOOKUP($B11,Hoja4!$B:$B,Hoja4!N:N,0) -> 0 | O11: =+_xlfn.XLOOKUP($B11,Hoja4!$B:$B,Hoja4!O:O,0) -> 0 | P11: =+_xlfn.XLOOKUP($B11,Hoja4!$B:$B,Hoja4!P:P,0) -> 0 | Q11: =+_xlfn.XLOOKUP($B11,Hoja4!$B:$B,Hoja4!Q:Q,0) -> 0 | R11: =+_xlfn.XLOOKUP($B11,Hoja4!$B:$B,Hoja4!R:R,0) -> 0 | S11: =+_xlfn.XLOOKUP($B11,Hoja4!$B:$B,Hoja4!S:S,0) -> 0 | T11: =+_xlfn.XLOOKUP($B11,Hoja4!$B:$B,Hoja4!T:T,0) -> 0 | U11: -353339.08
B12: * INGRESOS DE PUERTO | C12: 0 | D12: 0 | E12: 0 | F12: 0 | G12: 0 | H12: 0 | I12: 0 | J12: 0 | K12: 0 | L12: 0 | M12: =+_xlfn.XLOOKUP($B12,Hoja4!$B:$B,Hoja4!M:M,0) -> 0 | N12: =+_xlfn.XLOOKUP($B12,Hoja4!$B:$B,Hoja4!N:N,0) -> 0 | O12: =+_xlfn.XLOOKUP($B12,Hoja4!$B:$B,Hoja4!O:O,0) -> 0 | P12: =+_xlfn.XLOOKUP($B12,Hoja4!$B:$B,Hoja4!P:P,0) -> 0 | Q12: =+_xlfn.XLOOKUP($B12,Hoja4!$B:$B,Hoja4!Q:Q,0) -> 0 | R12: =+_xlfn.XLOOKUP($B12,Hoja4!$B:$B,Hoja4!R:R,0) -> 0 | S12: =+_xlfn.XLOOKUP($B12,Hoja4!$B:$B,Hoja4!S:S,0) -> 0 | T12: =+_xlfn.XLOOKUP($B12,Hoja4!$B:$B,Hoja4!T:T,0) -> 0 | U12: -321339.08
B13: * OTROS INGRESOS | C13: 0 | D13: 0 | E13: 0 | F13: 0 | G13: 0 | H13: 0 | I13: 0 | J13: 0 | K13: 0 | L13: 0 | M13: =+_xlfn.XLOOKUP($B13,Hoja4!$B:$B,Hoja4!M:M,0) -> 0 | N13: =+_xlfn.XLOOKUP($B13,Hoja4!$B:$B,Hoja4!N:N,0) -> 0 | O13: =+_xlfn.XLOOKUP($B13,Hoja4!$B:$B,Hoja4!O:O,0) -> 0 | P13: =+_xlfn.XLOOKUP($B13,Hoja4!$B:$B,Hoja4!P:P,0) -> 0 | Q13: =+_xlfn.XLOOKUP($B13,Hoja4!$B:$B,Hoja4!Q:Q,0) -> 0 | R13: =+_xlfn.XLOOKUP($B13,Hoja4!$B:$B,Hoja4!R:R,0) -> 0 | S13: =+_xlfn.XLOOKUP($B13,Hoja4!$B:$B,Hoja4!S:S,0) -> 0 | T13: =+_xlfn.XLOOKUP($B13,Hoja4!$B:$B,Hoja4!T:T,0) -> 0 | U13: 0
B14: ** COSTOS DIRECTOS | C14: -111.25 | D14: 0 | E14: -16506.44 | F14: 0 | G14: 0 | H14: 2304.75 | I14: 0 | J14: 0 | K14: 0 | L14: 0 | M14: =+_xlfn.XLOOKUP($B14,Hoja4!$B:$B,Hoja4!M:M,0) -> 0 | N14: =+_xlfn.XLOOKUP($B14,Hoja4!$B:$B,Hoja4!N:N,0) -> 0 | O14: =+_xlfn.XLOOKUP($B14,Hoja4!$B:$B,Hoja4!O:O,0) -> 0 | P14: =+_xlfn.XLOOKUP($B14,Hoja4!$B:$B,Hoja4!P:P,0) -> 0 | Q14: =+_xlfn.XLOOKUP($B14,Hoja4!$B:$B,Hoja4!Q:Q,0) -> 0 | R14: =+_xlfn.XLOOKUP($B14,Hoja4!$B:$B,Hoja4!R:R,0) -> 0 | S14: =+_xlfn.XLOOKUP($B14,Hoja4!$B:$B,Hoja4!S:S,0) -> 0 | T14: =+_xlfn.XLOOKUP($B14,Hoja4!$B:$B,Hoja4!T:T,0) -> 0 | U14: 1688729.5
... B47: ******* EBITDA | C47: -111.25 | D47: 0 | E47: -16506.44 | F47: 0 | G47: 0 | H47: 2304.75 | I47: 0 | J47: 0 | K47: 0 | L47: 0 | M47: =+_xlfn.XLOOKUP($B47,Hoja4!$B:$B,Hoja4!M:M,0) -> 0 | N47: =+_xlfn.XLOOKUP($B47,Hoja4!$B:$B,Hoja4!N:N,0) -> 0 | O47: =+_xlfn.XLOOKUP($B47,Hoja4!$B:$B,Hoja4!O:O,0) -> 0 | P47: =+_xlfn.XLOOKUP($B47,Hoja4!$B:$B,Hoja4!P:P,0) -> 0 | Q47: =+_xlfn.XLOOKUP($B47,Hoja4!$B:$B,Hoja4!Q:Q,0) -> 0 | R47: =+_xlfn.XLOOKUP($B47,Hoja4!$B:$B,Hoja4!R:R,0) -> 0 | S47: =+_xlfn.XLOOKUP($B47,Hoja4!$B:$B,Hoja4!S:S,0) -> 0 | T47: =+_xlfn.XLOOKUP($B47,Hoja4!$B:$B,Hoja4!T:T,0) -> 0 | U47: -310890.95

Sheet Hoja4
B2: US$ Dolar | C2: Enero | D2: Febrero | E2: Marzo | F2: Abril | G2: Mayo | H2: Junio | I2: Julio | J2: Agosto | K2: Setiembre | L2: Octubre | M2: Noviembre | N2: Diciembre | O2: Acum. 2025 | P2: Ppto.Acum a 11 | Q2: Variacion | R2: Ppto Anual | S2: % | T2: Ppto Mens | U2: Real A o anterior
B3: *** VENTAS | C3: 0 | D3: 0 | E3: 0 | F3: 0 | G3: 0 | H3: 0 | I3: 0 | J3: 0 | K3: 0 | L3: 0 | M3: 0 | N3: 0 | O3: 0 | P3: 0 | Q3: 0 | R3: 0 | S3: 0 | T3: 0 | U3: 0
B4: ** OTROS INGRESOS | C4: 0 | D4: 0 | E4: 0 | F4: 0 | G4: 0 | H4: 0 | I4: 0 | J4: 0 | K4: 0 | L4: 0 | M4: 0 | N4: 0 | O4: 0 | P4: 0 | Q4: 0 | R4: 0 | S4: 0 | T4: 0 | U4: 0
B5: 703117 OTROS ING OPERAC E | C5: 0 | D5: 0 | E5: 0 | F5: 0 | G5: 0 | H5: 0 | I5: 0 | J5: 0 | K5: 0 | L5: 0 | M5: 0 | N5: 0 | O5: 0 | P5: 0 | Q5: 0 | R5: 0 | S5: 0 | T5: 0 | U5: 0
B6: * OTROS INGRESOS | C6: 0 | D6: 0 | E6: 0 | F6: 0 | G6: 0 | H6: 0 | I6: 0 | J6: 0 | K6: 0 | L6: 0 | M6: 0 | N6: 0 | O6: 0 | P6: 0 | Q6: 0 | R6: 0 | S6: 0 | T6: 0 | U6: 0
B7: ** COSTOS DIRECTOS | C7: 0 | D7: 0 | E7: 0 | F7: 0 | G7: 0 | H7: 0 | I7: 0 | J7: 0 | K7: 0 | L7: -14312.94 | M7: 0 | N7: 0 | O7: -14312.94 | P7: 0 | Q7: 14312.94 | R7: 0 | S7: 0 | T7: 0 | U7: 0
B8: 638105 GASTO DE PUERTO TE | C8: 0 | D8: 0 | E8: 0 | F8: 0 | G8: 0 | H8: 0 | I8: 0 | J8: 0 | K8: 0 | L8: 2304.75 | M8: 0 | N8: 0 | O8: 2304.75 | P8: 0 | Q8: -2304.75 | R8: 0 | S8: 0 | T8: 0 | U8: 0
B9: 638106 COSTO PUERTO ESTIM | C9: 0 | D9: 0 | E9: 0 | F9: 0 | G9: 0 | H9: 0 | I9: 0 | J9: 0 | K9: 0 | L9: -16617.69 | M9: 0 | N9: 0 | O9: -16617.69 | P9: 0 | Q9: 16617.69 | R9: 0 | S9: 0 | T9: 0 | U9: 0
B10: * GASTOS DE PUERTO | C10: 0 | D10: 0 | E10: 0 | F10: 0 | G10: 0 | H10: 0 | I10: 0 | J10: 0 | K10: 0 | L10: -14312.94 | M10: 0 | N10: 0 | O10: -14312.94 | P10: 0 | Q10: 14312.94 | R10: 0 | S10: 0 | T10: 0 | U10: 0
B11: **** TIME CHARTER EQUIVALENT | C11: 0 | D11: 0 | E11: 0 | F11: 0 | G11: 0 | H11: 0 | I11: 0 | J11: 0 | K11: 0 | L11: -14312.94 | M11: 0 | N11: 0 | O11: -14312.94 | P11: 0 | Q11: 14312.94 | R11: 0 | S11: 0 | T11: 0 | U11: 0
B12: ***** MARGEN BRUTO | C12: 0 | D12: 0 | E12: 0 | F12: 0 | G12: 0 | H12: 0 | I12: 0 | J12: 0 | K12: 0 | L12: -14312.94 | M12: 0 | N12: 0 | O12: -14312.94 | P12: 0 | Q12: 14312.94 | R12: 0 | S12: 0 | T12: 0 | U12: 0
B13: * GASTOS PERSONAL ABORDO | C13: 0 | D13: 0 | E13: 0 | F13: 0 | G13: 0 | H13: 0 | I13: 0 | J13: 0 | K13: 0 | L13: 0 | M13: 0 | N13: 0 | O13: 0 | P13: 0 | Q13: 0 | R13: 0 | S13: 0 | T13: 0 | U13: 0
B14: ** GASTOS DE LA NAVE | C14: 0 | D14: 0 | E14: 0 | F14: 0 | G14: 0 | H14: 0 | I14: 0 | J14: 0 | K14: 0 | L14: 0 | M14: 0 | N14: 0 | O14: 0 | P14: 0 | Q14: 0 | R14: 0 | S14: 0 | T14: 0 | U14: 0
... B31: ******** EBITDA | C31: 0 | D31: 0 | E31: 0 | F31: 0 | G31: 0 | H31: 0 | I31: 0 | J31: 0 | K31: 0 | L31: -14312.94 | M31: 0 | N31: 0 | O31: -14312.94 | P31: 0 | Q31: 14312.94 | R31: 0 | S31: 0 | T31: 0 | U31: 0

Sheet Gastos Adm
Z1: =+PETRAL!Z1 -> 5
B2: Control Presupuestal
B3: =+PETRAL!B3 -> 46143 | D3: GASTOS ADMINISTRATIVOS
B5: Titulos | D5: Holding (Presupuesto) | E5: Diciembre | F5: 2014 | G5: Todas | H5: 44
B6: Pivote | D6: 4 | E6: =+D6+4 -> 8 | F6: =+E6+4 -> 12 | G6: =+F6+4 -> 16 | H6: =+G6+4 -> 20 | I6: =+H6+4 -> 24 | J6: =+I6+4 -> 28 | K6: =+J6+4 -> 32 | L6: =+K6+4 -> 36 | ... O6: =+N6+4 -> 48 | Q6: 56 | R6: 58 | S6: VAR | V6: 54
B7: Diás del mes | D7: 31 | E7: 28 | F7: 31 | G7: 30 | H7: 31 | I7: 30 | J7: 31 | K7: 31 | L7: 30 | M7: 31 | N7: 30 | O7: 31 | Q7: =SUM(D7:N7) -> 334 | R7: =Q7 -> 334 | S7: 28
Q9: REAL | R9: PRESUP. | V9: PPTO. | X9: Real Acum.
B10: (US$ Dólares Americanos) | D10: ENE | E10: FEB | F10: MAR | G10: ABR | H10: MAY | I10: JUN | J10: JUL | K10: AGO | L10: SET | M10: OCT | N10: NOV | O10: DIC | Q10: ACUMUL. | R10: ACUMUL. | S10: VARIACION | T10: % | V10: ANUAL | X10: =+PETRAL!X6 -> 45778
B12: VENTAS | D12: =+D13 -> 0 | E12: =+E13 -> 0 | F12: =+F13 -> 0 | G12: =+G13 -> 0 | H12: =+H13 -> 0 | I12: =+I13 -> 0 | J12: =+J13 -> 0 | K12: =+K13 -> 0 | ... O12: =+O13 -> 0 | Q12: =+Q13 -> 0 | R12: =+R13 -> 0 | S12: =+S13 -> 0 | T12: =IF(ISERROR($S12/R12*100),0,$S12/R12*100) -> 0 | V12: 0 | X12: 0
A13: * OTROS INGRESOS | B13: OTROS INGRESOS | D13: 0 | E13: 0 | F13: 0 | G13: 0 | H13: 0 | I13: 0 | J13: 0 | K13: 0 | L13: 0 | M13: 0 | N13: 0 | O13: 0 | Q13: 0 | R13: 0 | S13: 0 | T13: 0 | V13: 0 | X13: 0
B16: GTOS. ADMINISTRATIVOS | D16: -114668.52 | E16: -134254.6 | F16: -117455.56 | G16: -98144.67 | H16: -84460 | I16: 0 | J16: 0 | K16: 0 | L16: 0 | M16: 0 | N16: 0 | O16: 0 | Q16: -548983.35 | R16: -473085.71 | S16: -75897.64 | T16: 16.043106 | V16: -1089986.3 | X16: -375273.87
B17: GASTOS DE PERSONAL | D17: -59398.21 | E17: -78673.06 | F17: -57016.24 | G17: -57716.77 | H17: -60666.05 | I17: 0 | J17: 0 | K17: 0 | L17: 0 | M17: 0 | N17: 0 | O17: 0 | Q17: -313470.33 | R17: -294361.71 | S17: -19108.62 | T17: 6.491544 | V17: -676220.18 | X17: -208471.69
A18: * SUELDOS DE ADMINISTRACION | B18: SUELDOS ADMINISTR. | D18: -37491.3 | E18: -57483.28 | F18: -37659.82 | G18: -36991.06 | H18: -39241.82 | I18: 0 | J18: 0 | K18: 0 | L18: 0 | M18: 0 | N18: 0 | O18: 0 | Q18: -208867.28 | R18: -203030.81 | S18: -5836.47 | T18: 2.8746721 | V18: -456043.29 | X18: -141038.37
A19: * GRATIFICACIONES | B19: GRATIFICACIONES | D19: -6101.11 | E19: -6090.21 | F19: -5856.72 | G19: -6172.54 | H19: -6374.85 | I19: 0 | J19: 0 | K19: 0 | L19: 0 | M19: 0 | N19: 0 | O19: 0 | Q19: -30595.43 | R19: -31394.95 | S19: 799.52 | T19: -2.5466516 | V19: -75347.88 | X19: -20881.52
A20: * BENEFICIOS SOCIALES | B20: BENEFICIOS SOCIALES | D20: -3587.33 | E20: -3504.4 | F20: -3500.21 | G20: -3525.07 | H20: -3614.1 | I20: 0 | J20: 0 | K20: 0 | L20: 0 | M20: 0 | N20: 0 | O20: 0 | Q20: -17731.11 | R20: -17154.75 | S20: -576.36 | T20: 3.3597692 | V20: -41171.4 | X20: -12139.03
A21: * ESSALUD | B21: ESSALUD | D21: -2470.95 | E21: -2466.54 | F21: -2479.13 | G21: -2499.87 | H21: -2581.82 | I21: 0 | J21: 0 | K21: 0 | L21: 0 | M21: 0 | N21: 0 | O21: 0 | Q21: -12498.31 | R21: -12198.8 | S21: -299.51 | T21: 2.4552415 | V21: -29277.12 | X21: -8290.9
B22: IMP. EXT. SOLIDARIDAD | D22: 0 | E22: 0 | F22: 0 | G22: 0 | H22: 0 | I22: 0 | J22: 0 | K22: 0 | L22: 0 | M22: 0 | N22: 0 | O22: 0 | Q22: 0 | R22: 0 | S22: 0 | T22: 0 | V22: 0 | X22: 0
A23: * E.P.S. /GASTOS MEDICOS | B23: E.P.S. | D23: -1885.85 | E23: -1801.66 | F23: -1396.3 | G23: -1388.23 | H23: -1313.14 | I23: 0 | J23: 0 | K23: 0 | L23: 0 | M23: 0 | N23: 0 | O23: 0 | Q23: -7785.18 | R23: -4519.3 | S23: -3265.88 | T23: 72.265174 | V23: -11479.05 | X23: -3206.6
A24: * CAPACITACION | B24: CAPACITACION | D24: 0 | E24: 0 | F24: 0 | G24: -86.13 | H24: 0 | I24: 0 | J24: 0 | K24: 0 | L24: 0 | M24: 0 | N24: 0 | O24: 0 | Q24: -86.13 | R24: 0 | S24: -86.13 | T24: 0 | V24: 0 | X24: 0
A25: * OTROS GASTOS DE PERSONAL | B25: OTROS GTOS. PERSONAL | D25: -7861.67 | E25: -7326.97 | F25: -6124.06 | G25: -7053.87 | H25: -7540.32 | I25: 0 | J25: 0 | K25: 0 | L25: 0 | M25: 0 | N25: 0 | O25: 0 | Q25: -35906.89 | R25: -26063.1 | S25: -9843.79 | T25: 37.769068 | V25: -62901.44 | X25: -22915.27
B26: INDEMNIZACIONES | D26: 0 | E26: 0 | F26: 0 | G26: 0 | H26: 0 | I26: 1 | J26: 2 | K26: 3 | L26: 4 | M26: 5 | N26: 6 | O26: 7 | Q26: 0 | R26: 0 | S26: 0 | T26: 0 | V26: 0 | X26: 0
B28: GASTOS GENERALES | D28: -55270.31 | E28: -55581.54 | F28: -60439.32 | G28: -40427.9 | H28: -23793.95 | I28: 0 | J28: 0 | K28: 0 | L28: 0 | M28: 0 | N28: 0 | O28: 0 | Q28: -235513.02 | R28: -178724 | S28: -56789.02 | T28: 31.774703 | V28: -413766.17 | X28: -166802.18
A29: * GASTOS DE VIAJE | B29: GASTOS DE VIAJE | D29: -62.06 | E29: -435.08 | F29: -2648.71 | G29: -1264.66 | H29: -245.56 | I29: 0 | J29: 0 | K29: 0 | L29: 0 | M29: 0 | N29: 0 | O29: 0 | Q29: -4656.07 | R29: -4350 | S29: -306.07 | T29: 7.036092 | V29: -10440 | X29: -5421.72
B30: MOVILIDAD LOCAL | D30: 0 | E30: 0 | F30: 0 | G30: 0 | H30: 0 | I30: 0 | J30: 0 | K30: 0 | L30: 0 | M30: 0 | N30: 0 | O30: 0 | Q30: 0 | R30: 0 | S30: 0 | T30: 0 | V30: 0 | X30: 0
A31: * TELECOMUNICACIONES | B31: TELECOMUNICACIONES | D31: -109.51 | E31: -109.71 | F31: -106.81 | G31: -107.05 | H31: -106.99 | I31: 0 | J31: 0 | K31: 0 | L31: 0 | M31: 0 | N31: 0 | O31: 0 | Q31: -540.07 | R31: -850 | S31: 309.93 | T31: -36.462353 | V31: -2040 | X31: -465.58
B32: AGUA | D32: 0 | E32: 0 | F32: 0 | G32: 0 | H32: 0 | I32: 0 | J32: 0 | K32: 0 | L32: 0 | M32: 0 | N32: 0 | O32: 0 | Q32: 0 | R32: 0 | S32: 0 | T32: 0 | V32: 0 | X32: 0
A33: * ENERGIA | B33: ENERGIA | D33: -250.2 | E33: -392.85 | F33: -389.15 | G33: -292.03 | H33: -323.75 | I33: 0 | J33: 0 | K33: 0 | L33: 0 | M33: 0 | N33: 0 | O33: 0 | Q33: -1647.98 | R33: -1100 | S33: -547.98 | T33: 49.816364 | V33: -2640 | X33: -1255.97
A34: * HONORARIOS | B34: HONORARIOS | D34: -37821.35 | E34: -28281.32 | F34: -43957.21 | G34: -19907.33 | H34: -14840.12 | I34: 0 | J34: 0 | K34: 0 | L34: 0 | M34: 0 | N34: 0 | O34: 0 | Q34: -144807.33 | R34: -86116.65 | S34: -58690.68 | T34: 68.152535 | V34: -230139.96 | X34: -101065.15
A35: * MANTENIMIENTO | B35: MANTENIMIENTO | D35: -5831.34 | E35: -9291.33 | F35: -3856.98 | G35: -10315.73 | H35: -409.4 | I35: 0 | J35: 0 | K35: 0 | L35: 0 | M35: 0 | N35: 0 | O35: 0 | Q35: -29704.78 | R35: -24000 | S35: -5704.78 | T35: 23.769917 | V35: -57600 | X35: -26688.23
A36: * SQE | B36: SQE | D36: 0 | E36: 0 | F36: 0 | G36: 0 | H36: 0 | I36: 0 | J36: 0 | K36: 0 | L36: 0 | M36: 0 | N36: 0 | O36: 0 | Q36: 0 | R36: 0 | S36: 0 | T36: 0 | V36: 0 | X36: -385.64
A37: * VIGILANCIA Y SEGURIDAD PRIV | B37: SERVICIO PERSONAL - SEGURIDAD | D37: -28132.66 | E37: -27905.14 | F37: -27692.25 | G37: -25312 | H37: -25312 | I37: 0 | J37: 0 | K37: 0 | L37: 0 | M37: 0 | N37: 0 | O37: 0 | Q37: -134354.05 | R37: -134960 | S37: 605.95 | T37: -0.44898488 | V37: -312144 | X37: -131584.1
A38: * GASTOS DE REPRESENTACION | B38: GTOS. DE REPRESENT. | D38: -25.89 | E38: -1.89 | F38: 0 | G38: 0 | H38: 0 | I38: 0 | J38: 0 | K38: 0 | L38: 0 | M38: 0 | N38: 0 | O38: 0 | Q38: -27.78 | R38: -250 | S38: 222.22 | T38: -88.888 | V38: -600 | X38: -559.57
A39: * SEGUROS DE OFICINAS | B39: SEGUROS DE OFICINAS | D39: 0 | E39: -546.42 | F39: 0 | G39: 0 | H39: 0 | I39: 0 | J39: 0 | K39: 0 | L39: 0 | M39: 0 | N39: 0 | O39: 0 | Q39: -546.42 | R39: -300 | S39: -246.42 | T39: 82.14 | V39: -720 | X39: 0
A40: * SUSCRIPCIONES/PUBLICIDAD | B40: SUSCRIPC./PUBLICAC. | D40: -3196.91 | E40: -5898.06 | F40: -600 | G40: -2346.16 | H40: -4143.63 | I40: 0 | J40: 0 | K40: 0 | L40: 0 | M40: 0 | N40: 0 | O40: 0 | Q40: -16184.76 | R40: -8350 | S40: -7834.76 | T40: 93.829461 | V40: -20040 | X40: -6464.28
A41: * GASTOS DE INFORMATICA | B41: GTOS. DE INFORMATICA | D41: -3531.35 | E41: -2568.03 | F41: -4369.55 | G41: -4413.55 | H41: -1996.8 | I41: 0 | J41: 0 | K41: 0 | L41: 0 | M41: 0 | N41: 0 | O41: 0 | Q41: -16879.28 | R41: -36508.05 | S41: 19628.77 | T41: -53.765594 | V41: -60747.89 | X41: -7774.63
A42: * PAPELERIA Y UTILES | B42: PAPELERIA Y UTILES | D42: -115.61 | E42: -398.98 | F42: -262.66 | G42: -315.09 | H42: -261.39 | I42: 0 | J42: 0 | K42: 0 | L42: 0 | M42: 0 | N42: 0 | O42: 0 | Q42: -1353.73 | R42: -600 | S42: -753.73 | T42: 125.62167 | V42: -1440 | X42: -530.74
A43: * OTROS TRIBUTOS | B43: OTROS TRIBUTOS | D43: -1063.36 | E43: -4622.65 | F43: -1425.94 | G43: -1063.36 | H43: -1063.36 | I43: 0 | J43: 0 | K43: 0 | L43: 0 | M43: 0 | N43: 0 | O43: 0 | Q43: -9238.67 | R43: -5850 | S43: -3388.67 | T43: 57.925983 | V43: -14040 | X43: -8741.08
A44: * GTOS . ADMINIST. DEPRECIACI | B44: DEPRECIACION | D44: -442.07 | E44: -442.08 | F44: -442.06 | G44: -402.94 | H44: -402.95 | I44: 0 | J44: 0 | K44: 0 | L44: 0 | M44: 0 | N44: 0 | O44: 0 | Q44: -2132.1 | R44: -2049.3 | S44: -82.8 | T44: 4.040404 | V44: -4918.32 | X44: -2425.49
A45: * GTOS.ADM.DIRECTO FLOTA | B45: GTOS. ADM.DIRECTO FLOTA | D45: 25312 | E45: 25312 | F45: 25312 | G45: 25312 | H45: 25312 | I45: 0 | J45: 0 | K45: 0 | L45: 0 | M45: 0 | N45: 0 | O45: 0 | Q45: 126560 | R45: 126560 | S45: 0 | T45: 0 | V45: 303744 | X45: 126560
B48: OTROS INGR./EGRESOS | D48: -5452.95 | E48: 42177.23 | F48: 13284.71 | G48: -51433.01 | H48: 3425.35 | I48: 0 | J48: 0 | K48: 0 | L48: 0 | M48: 0 | N48: 0 | O48: 0 | Q48: 2001.33 | R48: 50848.11 | S48: -48846.78 | T48: -96.064101 | V48: 84093.48 | X48: 14198.69
A49: * INGRESOS FINANCIEROS | B49: ING. FINANCIEROS | D49: 15490.9 | E49: 24326.8 | F49: 17151.87 | G49: 13391.97 | H49: 8336.37 | I49: 0 | J49: 0 | K49: 0 | L49: 0 | M49: 0 | N49: 0 | O49: 0 | Q49: 78697.91 | R49: 80892.46 | S49: -2194.55 | T49: -2.7129228 | V49: 168732.24 | X49: 53737.58
A50: * GASTOS FINANCIEROS | B50: GASTOS FINANCIEROS | D50: -943.91 | E50: -907.68 | F50: -1150.69 | G50: -992.15 | H50: -1704.18 | I50: 0 | J50: 0 | K50: 0 | L50: 0 | M50: 0 | N50: 0 | O50: 0 | Q50: -5698.61 | R50: -5478.15 | S50: -220.46 | T50: 4.0243513 | V50: -23572.56 | X50: -4619.43
B51: ING. (GTOS.) AÑO ANTER. | D51: 0 | E51: 0 | F51: 0 | G51: 0 | H51: 0 | I51: 0 | J51: 0 | K51: 0 | L51: 0 | M51: 0 | N51: 0 | O51: 0 | Q51: 0 | R51: 0 | S51: 0 | T51: 100 | V51: 0 | X51: 0
A52: * ING. (GTOS.) GESTION | B52: ING. (GTOS.) GESTION | D52: -1.07 | E52: -3676.68 | F52: -1987.44 | G52: -47172.01 | H52: -2474.29 | I52: 0 | J52: 0 | K52: 0 | L52: 0 | M52: 0 | N52: 0 | O52: 0 | Q52: -55311.49 | R52: -34566.2 | S52: -20745.29 | T52: 60.016114 | V52: -85066.2 | X52: -57750.47
B53: NPETRAL/PERSEUS | D53: 0 | E53: 0 | F53: 0 | G53: 0 | H53: 0 | I53: 0 | J53: 0 | K53: 0 | L53: 0 | M53: 0 | N53: 0 | O53: 0 | Q53: 0 | R53: 0 | S53: 0 | T53: 100 | V53: 0 | X53: 0
B54: INTERES MINORITARIO | D54: 0 | E54: 0 | F54: 0 | G54: 0 | H54: 0 | I54: 0 | J54: 0 | K54: 0 | L54: 0 | M54: 0 | N54: 0 | O54: 0 | Q54: 0 | R54: 0 | S54: 0 | T54: 100 | V54: 0 | X54: 0
A55: * RESULT. DE TRASLACION/DIF. | B55: RESULT. DE TRASLACION | D55: -19998.87 | E55: 22434.79 | F55: -729.03 | G55: -16660.82 | H55: -732.55 | I55: 0 | J55: 0 | K55: 0 | L55: 0 | M55: 0 | N55: 0 | O55: 0 | Q55: -15686.48 | R55: 10000 | S55: -25686.48 | T55: -256.8648 | V55: 24000 | X55: 22831.01
B56: M4 - RESULTADO ANTES IMPTO | D56: -120121.47 | E56: -92077.37 | F56: -104170.85 | G56: -149577.68 | H56: -81034.65 | I56: 0 | J56: 0 | K56: 0 | L56: 0 | M56: 0 | N56: 0 | O56: 0 | Q56: -546982.02 | R56: -422237.6 | S56: -124744.42 | T56: 29.543655 | V56: -1005892.9 | X56: -361075.18
Q57: ok | S57: ok | T57: ok | V57: ok | X57: ok
B59: EBITDA | D59: -114226.45 | E59: -133812.52 | F59: -117013.5 | G59: -97741.73 | H59: -84057.05 | I59: 0 | J59: 0 | K59: 0 | L59: 0 | M59: 0 | N59: 0 | O59: 0 | Q59: -546851.25 | R59: -471036.41 | S59: -75814.84 | T59: 16.095325 | V59: -1085068 | X59: -372848.38

Sheet GTOS ADM GRR3
B2: US$ Dolar | C2: Enero | D2: Febrero | E2: Marzo | F2: Abril | G2: Mayo | H2: Junio | I2: Julio | J2: Agosto | K2: Setiembre | L2: Octubre | M2: Noviembre | N2: Diciembre | O2: Acum. 2026 | P2: Ppto.Acum a 3 | Q2: Variacion | R2: Ppto Anual | S2: % | T2: Ppto Mens | U2: Real A o anterior
B3: ** VENTAS | C3: 0 | D3: 0 | E3: 0 | F3: 0 | G3: 0 | H3: 0 | I3: 0 | J3: 0 | K3: 0 | L3: 0 | M3: 0 | N3: 0 | O3: 0 | P3: 0 | Q3: 0 | R3: 0 | S3: 0 | T3: 0 | U3: 0
B4: * OTROS INGRESOS | C4: 0 | D4: 0 | E4: 0 | F4: 0 | G4: 0 | H4: 0 | I4: 0 | J4: 0 | K4: 0 | L4: 0 | M4: 0 | N4: 0 | O4: 0 | P4: 0 | Q4: 0 | R4: 0 | S4: 0 | T4: 0 | U4: 0
B5: * COSTOS DIRECTOS | C5: 0 | D5: 0 | E5: 0 | F5: 0 | G5: 0 | H5: 0 | I5: 0 | J5: 0 | K5: 0 | L5: 0 | M5: 0 | N5: 0 | O5: 0 | P5: 0 | Q5: 0 | R5: 0 | S5: 0 | T5: 0 | U5: 0
B6: *** TIME CHARTER EQUIVALENT | C6: 0 | D6: 0 | E6: 0 | F6: 0 | G6: 0 | H6: 0 | I6: 0 | J6: 0 | K6: 0 | L6: 0 | M6: 0 | N6: 0 | O6: 0 | P6: 0 | Q6: 0 | R6: 0 | S6: 0 | T6: 0 | U6: 0
B7: **** MARGEN BRUTO | C7: 0 | D7: 0 | E7: 0 | F7: 0 | G7: 0 | H7: 0 | I7: 0 | J7: 0 | K7: 0 | L7: 0 | M7: 0 | N7: 0 | O7: 0 | P7: 0 | Q7: 0 | R7: 0 | S7: 0 | T7: 0 | U7: 0
B8: * GASTOS PERSONAL ABORDO | C8: 0 | D8: 0 | E8: 0 | F8: 0 | G8: 0 | H8: 0 | I8: 0 | J8: 0 | K8: 0 | L8: 0 | M8: 0 | N8: 0 | O8: 0 | P8: 0 | Q8: 0 | R8: 0 | S8: 0 | T8: 0 | U8: 0
B9: ** GASTOS DE LA NAVE | C9: 0 | D9: 0 | E9: 0 | F9: 0 | G9: 0 | H9: 0 | I9: 0 | J9: 0 | K9: 0 | L9: 0 | M9: 0 | N9: 0 | O9: 0 | P9: 0 | Q9: 0 | R9: 0 | S9: 0 | T9: 0 | U9: 0
B10: * OTROS COSTOS | C10: 0 | D10: 0 | E10: 0 | F10: 0 | G10: 0 | H10: 0 | I10: 0 | J10: 0 | K10: 0 | L10: 0 | M10: 0 | N10: 0 | O10: 0 | P10: 0 | Q10: 0 | R10: 0 | S10: 0 | T10: 0 | U10: 0
B11: * SEGUROS | C11: 0 | D11: 0 | E11: 0 | F11: 0 | G11: 0 | H11: 0 | I11: 0 | J11: 0 | K11: 0 | L11: 0 | M11: 0 | N11: 0 | O11: 0 | P11: 0 | Q11: 0 | R11: 0 | S11: 0 | T11: 0 | U11: 0
B12: *** OPERATING COST | C12: 0 | D12: 0 | E12: 0 | F12: 0 | G12: 0 | H12: 0 | I12: 0 | J12: 0 | K12: 0 | L12: 0 | M12: 0 | N12: 0 | O12: 0 | P12: 0 | Q12: 0 | R12: 0 | S12: 0 | T12: 0 | U12: 0
B13: **** BARE BOAT EQUIVALENT | C13: 0 | D13: 0 | E13: 0 | F13: 0 | G13: 0 | H13: 0 | I13: 0 | J13: 0 | K13: 0 | L13: 0 | M13: 0 | N13: 0 | O13: 0 | P13: 0 | Q13: 0 | R13: 0 | S13: 0 | T13: 0 | U13: 0
B14: * GTOS. ADMINIST. NAVE | C14: 0 | D14: 0 | E14: 0 | F14: 0 | G14: 0 | H14: 0 | I14: 0 | J14: 0 | K14: 0 | L14: 0 | M14: 0 | N14: 0 | O14: 0 | P14: 0 | Q14: 0 | R14: 0 | S14: 0 | T14: 0 | U14: 0
... B114: ******* EBITDA | C114: 114226.45 | D114: 133812.52 | E114: 117013.5 | F114: 0 | G114: 0 | H114: 0 | I114: 0 | J114: 0 | K114: 0 | L114: 0 | M114: 0 | N114: 0 | O114: 365052.47 | P114: 304572.09 | Q114: -60480.38 | R114: 1085068 | S114: -19.8575 | T114: 105900.16 | U114: 0

Sheet Hoja5
B2: US$ Dolar | C2: Enero | D2: Febrero | E2: Marzo | F2: Abril | G2: Mayo | H2: Junio | I2: Julio | J2: Agosto | K2: Setiembre | L2: Octubre | M2: Noviembre | N2: Diciembre | O2: Acum. 2025 | P2: Ppto.Acum a 11 | Q2: Variacion | R2: Ppto Anual | S2: % | T2: Ppto Mens | U2: Real A o anterior
B3: *** VENTAS | C3: 0 | D3: 0 | E3: 0 | F3: 0 | G3: 0 | H3: 0 | I3: 0 | J3: 0 | K3: 0 | L3: 0 | M3: 0 | N3: 0 | O3: 0 | P3: 0 | Q3: 0 | R3: 0 | S3: 0 | T3: 0 | U3: 0
B4: ** OTROS INGRESOS | C4: 0 | D4: 0 | E4: 0 | F4: 0 | G4: 0 | H4: 0 | I4: 0 | J4: 0 | K4: 0 | L4: 0 | M4: 0 | N4: 0 | O4: 0 | P4: 0 | Q4: 0 | R4: 0 | S4: 0 | T4: 0 | U4: 0
B5: 703117 OTROS ING OPERAC E | C5: 0 | D5: 0 | E5: 0 | F5: 0 | G5: 0 | H5: 0 | I5: 0 | J5: 0 | K5: 0 | L5: 0 | M5: 0 | N5: 0 | O5: 0 | P5: 0 | Q5: 0 | R5: 0 | S5: 0 | T5: 0 | U5: 0
B6: * OTROS INGRESOS | C6: 0 | D6: 0 | E6: 0 | F6: 0 | G6: 0 | H6: 0 | I6: 0 | J6: 0 | K6: 0 | L6: 0 | M6: 0 | N6: 0 | O6: 0 | P6: 0 | Q6: 0 | R6: 0 | S6: 0 | T6: 0 | U6: 0
B7: * COSTOS DIRECTOS | C7: 0 | D7: 0 | E7: 0 | F7: 0 | G7: 0 | H7: 0 | I7: 0 | J7: 0 | K7: 0 | L7: 0 | M7: 0 | N7: 0 | O7: 0 | P7: 0 | Q7: 0 | R7: 0 | S7: 0 | T7: 0 | U7: 0
B8: **** TIME CHARTER EQUIVALENT | C8: 0 | D8: 0 | E8: 0 | F8: 0 | G8: 0 | H8: 0 | I8: 0 | J8: 0 | K8: 0 | L8: 0 | M8: 0 | N8: 0 | O8: 0 | P8: 0 | Q8: 0 | R8: 0 | S8: 0 | T8: 0 | U8: 0
B9: ***** MARGEN BRUTO | C9: 0 | D9: 0 | E9: 0 | F9: 0 | G9: 0 | H9: 0 | I9: 0 | J9: 0 | K9: 0 | L9: 0 | M9: 0 | N9: 0 | O9: 0 | P9: 0 | Q9: 0 | R9: 0 | S9: 0 | T9: 0 | U9: 0
B10: * GASTOS PERSONAL ABORDO | C10: 0 | D10: 0 | E10: 0 | F10: 0 | G10: 0 | H10: 0 | I10: 0 | J10: 0 | K10: 0 | L10: 0 | M10: 0 | N10: 0 | O10: 0 | P10: 0 | Q10: 0 | R10: 0 | S10: 0 | T10: 0 | U10: 0
B11: ** GASTOS DE LA NAVE | C11: 0 | D11: 0 | E11: 0 | F11: 0 | G11: 0 | H11: 0 | I11: 0 | J11: 0 | K11: 0 | L11: 0 | M11: 0 | N11: 0 | O11: 0 | P11: 0 | Q11: 0 | R11: 0 | S11: 0 | T11: 0 | U11: 0
B12: * OTROS COSTOS | C12: 0 | D12: 0 | E12: 0 | F12: 0 | G12: 0 | H12: 0 | I12: 0 | J12: 0 | K12: 0 | L12: 0 | M12: 0 | N12: 0 | O12: 0 | P12: 0 | Q12: 0 | R12: 0 | S12: 0 | T12: 0 | U12: 0
B13: * SEGUROS | C13: 0 | D13: 0 | E13: 0 | F13: 0 | G13: 0 | H13: 0 | I13: 0 | J13: 0 | K13: 0 | L13: 0 | M13: 0 | N13: 0 | O13: 0 | P13: 0 | Q13: 0 | R13: 0 | S13: 0 | T13: 0 | U13: 0
B14: *** OPERATING COST | C14: 0 | D14: 0 | E14: 0 | F14: 0 | G14: 0 | H14: 0 | I14: 0 | J14: 0 | K14: 0 | L14: 0 | M14: 0 | N14: 0 | O14: 0 | P14: 0 | Q14: 0 | R14: 0 | S14: 0 | T14: 0 | U14: 0
... B126: ******** EBITDA | C126: 0 | D126: 0 | E126: 0 | F126: 0 | G126: 0 | H126: 0 | I126: 0 | J126: 0 | K126: 0 | L126: 797700.94 | M126: 101178.15 | N126: 0 | O126: 898879.09 | P126: 670868.71 | Q126: -228010.38 | R126: 746929.7 | S126: -33.9873 | T126: 59510.99 | U126: 0
